Workbook
Name tax_rate: Assumptions!$T$40
Name acq: Assumptions!$H$8
Name year: Assumptions!$T$41
Name tgt: Assumptions!$L$8

Sheet 5-Yr Summary
A1: UrbanWind | BP1: @
A2: 5-Year Summary
B4: 44562 | C4: 44593 | D4: 44621 | E4: 44652 | F4: 44682 | G4: 44713 | H4: 44743 | I4: 44774 | J4: 44805 | K4: 44835 | L4: 44866 | M4: 44896 | N4: 2022 | O4: 44927 | P4: 44958 | Q4: 44986 | R4: 45017 | S4: 45047 | T4: 45078 | U4: 45108 | V4: 45139 | W4: 45170 | X4: 45200 | Y4: 45231 | Z4: 45261 | AA4: 2023 | AB4: 45292 | AC4: 45323 | AD4: 45352 | AE4: 45383 | AF4: 45413 | AG4: 45444 | AH4: 45474 | AI4: 45505 | AJ4: 45536 | AK4: 45566 | AL4: 45597 | AM4: 45627 | AN4: 2024 | AO4: 45658 | AP4: 45689 | AQ4: 45717 | AR4: 45748 | AS4: 45778 | AT4: 45809 | AU4: 45839 | AV4: 45870 | AW4: 45901 | AX4: 45931 | AY4: 45962 | AZ4: 45992 | BA4: 2025 | BB4: 46023 | BC4: 46054 | BD4: 46082 | BE4: 46113 | BF4: 46143 | BG4: 46174 | BH4: 46204 | BI4: 46235 | BJ4: 46266 | BK4: 46296 | BL4: 46327 | BM4: 46357 | BN4: 2026
A5: Income
A6: MMR (Services/Platform) | B6: ='Sales Forecast'!H32 -> 30 | C6: ='Sales Forecast'!I32 -> 120 | D6: ='Sales Forecast'!J32 -> 330 | E6: ='Sales Forecast'!K32 -> 615 | F6: ='Sales Forecast'!L32 -> 975 | G6: ='Sales Forecast'!M32 -> 1365 | H6: ='Sales Forecast'!N32 -> 1785 | I6: ='Sales Forecast'!O32 -> 2235 | ... M6: ='Sales Forecast'!S32 -> 4335 | N6: =SUM(B6:M6) -> 21495 | O6: ='Sales Forecast'!T32 -> 4920 | P6: ='Sales Forecast'!U32 -> 5520 | Q6: ='Sales Forecast'!V32 -> 6135 | R6: ='Sales Forecast'!W32 -> 6765 | S6: ='Sales Forecast'!X32 -> 7410 | T6: ='Sales Forecast'!Y32 -> 8085 | U6: ='Sales Forecast'!Z32 -> 8775 | V6: ='Sales Forecast'!AA32 -> 9480 | ... Z6: ='Sales Forecast'!AE32 -> 12465 | AA6: =SUM(O6:Z6) -> 102375 | AB6: ='Sales Forecast'!AF32 -> 13320 | AC6: ='Sales Forecast'!AG32 -> 14205 | AD6: ='Sales Forecast'!AH32 -> 15105 | AE6: ='Sales Forecast'!AI32 -> 16005 | AF6: ='Sales Forecast'!AJ32 -> 16905 | AG6: ='Sales Forecast'!AK32 -> 17805 | AH6: ='Sales Forecast'!AL32 -> 18705 | AI6: ='Sales Forecast'!AM32 -> 19605 | ... AM6: ='Sales Forecast'!AQ32 -> 23205 | AN6: =SUM(AB6:AM6) -> 219075 | AO6: ='Sales Forecast'!AR32 -> 24180 | AP6: ='Sales Forecast'!AS32 -> 25200 | AQ6: ='Sales Forecast'!AT32 -> 26280 | AR6: ='Sales Forecast'!AU32 -> 27420 | AS6: ='Sales Forecast'!AV32 -> 28605 | AT6: ='Sales Forecast'!AW32 -> 29790 | AU6: ='Sales Forecast'!AX32 -> 31005 | AV6: ='Sales Forecast'!AY32 -> 32220 | ... AZ6: ='Sales Forecast'!BC32 -> 37080 | BA6: =SUM(AO6:AZ6) -> 365730 | BB6: ='Sales Forecast'!BD32 -> 38340 | BC6: ='Sales Forecast'!BE32 -> 39660 | BD6: ='Sales Forecast'!BF32 -> 41010 | BE6: ='Sales Forecast'!BG32 -> 42420 | BF6: ='Sales Forecast'!BH32 -> 43875 | BG6: ='Sales Forecast'!BI32 -> 45375 | BH6: ='Sales Forecast'!BJ32 -> 46920 | BI6: ='Sales Forecast'!BK32 -> 48525 | ... BM6: ='Sales Forecast'!BO32 -> 55440 | BN6: =SUM(BB6:BM6) -> 557205
A7: Equipment Sales | B7: ='Sales Forecast'!H31 -> 40000 | C7: ='Sales Forecast'!I31 -> 230000 | D7: ='Sales Forecast'!J31 -> 480000 | E7: ='Sales Forecast'!K31 -> 620000 | F7: ='Sales Forecast'!L31 -> 820000 | G7: ='Sales Forecast'!M31 -> 840000 | H7: ='Sales Forecast'!N31 -> 860000 | I7: ='Sales Forecast'!O31 -> 880000 | ... M7: ='Sales Forecast'!S31 -> 960000 | N7: =SUM(B7:M7) -> 8490000 | O7: ='Sales Forecast'!T33 -> 0 | P7: ='Sales Forecast'!U31 -> 1050000 | Q7: ='Sales Forecast'!V31 -> 1080000 | R7: ='Sales Forecast'!W31 -> 1110000 | S7: ='Sales Forecast'!X31 -> 1140000 | T7: ='Sales Forecast'!Y31 -> 1260000 | U7: ='Sales Forecast'!Z31 -> 1290000 | V7: ='Sales Forecast'!AA31 -> 1320000 | W7: ='Sales Forecast'!AB31 -> 1350000 | ... Z7: ='Sales Forecast'!AE31 -> 1500000 | AA7: =SUM(O7:Z7) -> 13890000 | AB7: ='Sales Forecast'!AF31 -> 1700000 | AC7: ='Sales Forecast'!AG31 -> 1820000 | AD7: ='Sales Forecast'!AH31 -> 1850000 | AE7: ='Sales Forecast'!AI31 -> 1850000 | AF7: ='Sales Forecast'!AJ31 -> 1850000 | AG7: ='Sales Forecast'!AK31 -> 1850000 | AH7: ='Sales Forecast'!AL31 -> 1850000 | AI7: ='Sales Forecast'!AM31 -> 1850000 | ... AM7: ='Sales Forecast'!AQ31 -> 1850000 | AN7: =SUM(AB7:AM7) -> 22020000 | AO7: ='Sales Forecast'!AR31 -> 2050000 | AP7: ='Sales Forecast'!AS31 -> 2230000 | AQ7: ='Sales Forecast'!AT31 -> 2420000 | AR7: ='Sales Forecast'!AU31 -> 2610000 | AS7: ='Sales Forecast'!AV31 -> 2740000 | AT7: ='Sales Forecast'!AW31 -> 2740000 | AU7: ='Sales Forecast'!AX31 -> 2810000 | AV7: ='Sales Forecast'!AY31 -> 2810000 | ... AZ7: ='Sales Forecast'!BC31 -> 2810000 | BA7: =SUM(AO7:AZ7) -> 31650000 | BB7: ='Sales Forecast'!BD31 -> 2910000 | BC7: ='Sales Forecast'!BE31 -> 3100000 | BD7: ='Sales Forecast'!BF31 -> 3170000 | BE7: ='Sales Forecast'!BG31 -> 3360000 | BF7: ='Sales Forecast'!BH31 -> 3460000 | BG7: ='Sales Forecast'!BI31 -> 3620000 | BH7: ='Sales Forecast'!BJ31 -> 3720000 | BI7: ='Sales Forecast'!BK31 -> 3910000 | ... BM7: ='Sales Forecast'!BO31 -> 4610000 | BN7: =SUM(BB7:BM7) -> 44460000
A8: Channel Sales | B8: ='Sales Forecast'!H33 -> 0 | C8: ='Sales Forecast'!I33 -> 0 | D8: ='Sales Forecast'!J33 -> 0 | E8: ='Sales Forecast'!K33 -> 0 | F8: ='Sales Forecast'!L33 -> 0 | G8: ='Sales Forecast'!M33 -> 0 | H8: ='Sales Forecast'!N33 -> 0 | I8: ='Sales Forecast'!O33 -> 0 | ... M8: ='Sales Forecast'!S33 -> 0 | N8: =SUM(B8:M8) -> 0 | O8: ='Sales Forecast'!T33 -> 0 | P8: ='Sales Forecast'!U33 -> 0 | Q8: ='Sales Forecast'!V33 -> 0 | R8: ='Sales Forecast'!W33 -> 0 | S8: ='Sales Forecast'!X33 -> 0 | T8: ='Sales Forecast'!Y33 -> 0 | U8: ='Sales Forecast'!Z33 -> 0 | V8: ='Sales Forecast'!AA33 -> 0 | ... Z8: ='Sales Forecast'!AE33 -> 0 | AA8: =SUM(O8:Z8) -> 0 | AB8: ='Sales Forecast'!AF33 -> 0 | AC8: ='Sales Forecast'!AG33 -> 0 | AD8: ='Sales Forecast'!AH33 -> 0 | AE8: ='Sales Forecast'!AI33 -> 0 | AF8: ='Sales Forecast'!AJ33 -> 0 | AG8: ='Sales Forecast'!AK33 -> 0 | AH8: ='Sales Forecast'!AL33 -> 0 | AI8: ='Sales Forecast'!AM33 -> 0 | ... AM8: ='Sales Forecast'!AQ33 -> 0 | AN8: =SUM(AB8:AM8) -> 0 | AO8: ='Sales Forecast'!AR33 -> 0 | AP8: ='Sales Forecast'!AS33 -> 0 | AQ8: ='Sales Forecast'!AT33 -> 0 | AR8: ='Sales Forecast'!AU33 -> 0 | AS8: ='Sales Forecast'!AV33 -> 0 | AT8: ='Sales Forecast'!AW33 -> 0 | AU8: ='Sales Forecast'!AX33 -> 0 | AV8: ='Sales Forecast'!AY33 -> 0 | ... AZ8: ='Sales Forecast'!BC33 -> 0 | BA8: =SUM(AO8:AZ8) -> 0 | BB8: ='Sales Forecast'!BD33 -> 0 | BC8: ='Sales Forecast'!BE33 -> 0 | BD8: ='Sales Forecast'!BF33 -> 0 | BE8: ='Sales Forecast'!BG33 -> 0 | BF8: ='Sales Forecast'!BH33 -> 0 | BG8: ='Sales Forecast'!BI33 -> 0 | BH8: ='Sales Forecast'!BJ33 -> 0 | BI8: ='Sales Forecast'!BK33 -> 0 | ... BM8: ='Sales Forecast'!BO33 -> 0 | BN8: =SUM(BB8:BM8) -> 0
A9: Data and Digital Services | B9: ='Sales Forecast'!H34 -> 0 | C9: ='Sales Forecast'!I34 -> 0 | D9: ='Sales Forecast'!J34 -> 0 | E9: ='Sales Forecast'!K34 -> 0 | F9: ='Sales Forecast'!L34 -> 0 | G9: ='Sales Forecast'!M34 -> 0 | H9: ='Sales Forecast'!N34 -> 0 | I9: ='Sales Forecast'!O34 -> 0 | ... M9: ='Sales Forecast'!S34 -> 0 | N9: =SUM(B9:M9) -> 0 | O9: ='Sales Forecast'!T34 -> 0 | P9: ='Sales Forecast'!U34 -> 0 | Q9: ='Sales Forecast'!V34 -> 0 | R9: ='Sales Forecast'!W34 -> 0 | S9: ='Sales Forecast'!X34 -> 0 | T9: ='Sales Forecast'!Y34 -> 0 | U9: ='Sales Forecast'!Z34 -> 0 | V9: ='Sales Forecast'!AA34 -> 0 | ... Z9: ='Sales Forecast'!AE34 -> 0 | AA9: =SUM(O9:Z9) -> 0 | AB9: ='Sales Forecast'!AF34 -> 0 | AC9: ='Sales Forecast'!AG34 -> 0 | AD9: ='Sales Forecast'!AH34 -> 0 | AE9: ='Sales Forecast'!AI34 -> 0 | AF9: ='Sales Forecast'!AJ34 -> 0 | AG9: ='Sales Forecast'!AK34 -> 0 | AH9: ='Sales Forecast'!AL34 -> 0 | AI9: ='Sales Forecast'!AM34 -> 0 | ... AM9: ='Sales Forecast'!AQ34 -> 0 | AN9: =SUM(AB9:AM9) -> 0 | AO9: ='Sales Forecast'!AR34 -> 0 | AP9: ='Sales Forecast'!AS34 -> 0 | AQ9: ='Sales Forecast'!AT34 -> 0 | AR9: ='Sales Forecast'!AU34 -> 0 | AS9: ='Sales Forecast'!AV34 -> 0 | AT9: ='Sales Forecast'!AW34 -> 0 | AU9: ='Sales Forecast'!AX34 -> 0 | AV9: ='Sales Forecast'!AY34 -> 0 | ... AZ9: ='Sales Forecast'!BC34 -> 0 | BA9: =SUM(AO9:AZ9) -> 0 | BB9: ='Sales Forecast'!BD34 -> 0 | BC9: ='Sales Forecast'!BE34 -> 0 | BD9: ='Sales Forecast'!BF34 -> 0 | BE9: ='Sales Forecast'!BG34 -> 0 | BF9: ='Sales Forecast'!BH34 -> 0 | BG9: ='Sales Forecast'!BI34 -> 0 | BH9: ='Sales Forecast'!BJ34 -> 0 | BI9: ='Sales Forecast'!BK34 -> 0 | ... BM9: ='Sales Forecast'!BO34 -> 0 | BN9: =SUM(BB9:BM9) -> 0
N10: =SUM(B10:M10) -> 0 | O10: =SUM(C10:N10) -> 0 | P10: =SUM(D10:O10) -> 0 | Q10: =SUM(E10:P10) -> 0 | R10: =SUM(F10:Q10) -> 0 | S10: =SUM(G10:R10) -> 0 | T10: =SUM(H10:S10) -> 0 | U10: =SUM(I10:T10) -> 0 | ... BN10: =SUM(BB10:BM10) -> 0
N11: =SUM(B11:M11) -> 0 | O11: =SUM(C11:N11) -> 0 | P11: =SUM(D11:O11) -> 0 | Q11: =SUM(E11:P11) -> 0 | R11: =SUM(F11:Q11) -> 0 | S11: =SUM(G11:R11) -> 0 | T11: =SUM(H11:S11) -> 0 | U11: =SUM(I11:T11) -> 0 | ... BN11: =SUM(BB11:BM11) -> 0
N12: =SUM(B12:M12) -> 0 | O12: =SUM(C12:N12) -> 0 | P12: =SUM(D12:O12) -> 0 | Q12: =SUM(E12:P12) -> 0 | R12: =SUM(F12:Q12) -> 0 | S12: =SUM(G12:R12) -> 0 | T12: =SUM(H12:S12) -> 0 | U12: =SUM(I12:T12) -> 0 | ... BN12: =SUM(BB12:BM12) -> 0
N13: =SUM(B13:M13) -> 0 | O13: =SUM(C13:N13) -> 0 | P13: =SUM(D13:O13) -> 0 | Q13: =SUM(E13:P13) -> 0 | R13: =SUM(F13:Q13) -> 0 | S13: =SUM(G13:R13) -> 0 | T13: =SUM(H13:S13) -> 0 | U13: =SUM(I13:T13) -> 0 | ... BN13: =SUM(BB13:BM13) -> 0
N14: =+N10+N11+N12+N13 -> 0 | O14: =+O10+O11+O12+O13 -> 0 | P14: =+P10+P11+P12+P13 -> 0 | Q14: =+Q10+Q11+Q12+Q13 -> 0 | R14: =+R10+R11+R12+R13 -> 0 | S14: =+S10+S11+S12+S13 -> 0 | T14: =+T10+T11+T12+T13 -> 0 | U14: =+U10+U11+U12+U13 -> 0 | ... BN14: =+BN10+BN11+BN12+BN13 -> 0 | BO14: 50% in y 4 and 50% y5
A15: Total Sales | B15: =SUM(B7:B13) -> 40000 | C15: =SUM(C7:C13) -> 230000 | D15: =SUM(D7:D13) -> 480000 | E15: =SUM(E7:E13) -> 620000 | F15: =SUM(F7:F13) -> 820000 | G15: =SUM(G7:G13) -> 840000 | H15: =SUM(H7:H13) -> 860000 | I15: =SUM(I7:I13) -> 880000 | ... M15: =SUM(M7:M13) -> 960000 | N15: =SUM(N6:N14) -> 8511495 | O15: =SUM(O7:O13) -> 0 | P15: =SUM(P7:P13) -> 1050000 | Q15: =SUM(Q7:Q13) -> 1080000 | R15: =SUM(R7:R13) -> 1110000 | S15: =SUM(S7:S13) -> 1140000 | T15: =SUM(T7:T13) -> 1260000 | U15: =SUM(U7:U13) -> 1290000 | V15: =SUM(V7:V13) -> 1320000 | ... Z15: =SUM(Z7:Z13) -> 1500000 | AA15: =SUM(AA6:AA13) -> 13992375 | AB15: =SUM(AB7:AB13) -> 1700000 | AC15: =SUM(AC7:AC13) -> 1820000 | AD15: =SUM(AD7:AD13) -> 1850000 | AE15: =SUM(AE7:AE13) -> 1850000 | AF15: =SUM(AF7:AF13) -> 1850000 | AG15: =SUM(AG7:AG13) -> 1850000 | AH15: =SUM(AH7:AH13) -> 1850000 | AI15: =SUM(AI7:AI13) -> 1850000 | ... AM15: =SUM(AM7:AM13) -> 1850000 | AN15: =SUM(AN6:AN13) -> 22239075 | AO15: =SUM(AO7:AO13) -> 2050000 | AP15: =SUM(AP7:AP13) -> 2230000 | AQ15: =SUM(AQ7:AQ13) -> 2420000 | AR15: =SUM(AR7:AR13) -> 2610000 | AS15: =SUM(AS7:AS13) -> 2740000 | AT15: =SUM(AT7:AT13) -> 2740000 | AU15: =SUM(AU7:AU13) -> 2810000 | AV15: =SUM(AV7:AV13) -> 2810000 | ... AZ15: =SUM(AZ7:AZ13) -> 2810000 | BA15: =SUM(BA6:BA13) -> 32015730 | BB15: =SUM(BB7:BB13) -> 2910000 | BC15: =SUM(BC7:BC13) -> 3100000 | BD15: =SUM(BD7:BD13) -> 3170000 | BE15: =SUM(BE7:BE13) -> 3360000 | BF15: =SUM(BF7:BF13) -> 3460000 | BG15: =SUM(BG7:BG13) -> 3620000 | BH15: =SUM(BH7:BH13) -> 3720000 | BI15: =SUM(BI7:BI13) -> 3910000 | ... BM15: =SUM(BM7:BM13) -> 4610000 | BN15: =SUM(BN6:BN13) -> 45017205
A16: Growth | B16: n/a | C16: =IF(B15=0,"n/a",+(C15-B15)/B15) -> 4.75 | D16: =IF(C15=0,"n/a",+(D15-C15)/C15) -> 1.0869565 | E16: =IF(D15=0,"n/a",+(E15-D15)/D15) -> 0.29166667 | F16: =IF(E15=0,"n/a",+(F15-E15)/E15) -> 0.32258065 | G16: =IF(F15=0,"n/a",+(G15-F15)/F15) -> 0.024390244 | H16: =IF(G15=0,"n/a",+(H15-G15)/G15) -> 0.023809524 | I16: =IF(H15=0,"n/a",+(I15-H15)/H15) -> 0.023255814 | J16: =IF(I15=0,"n/a",+(J15-I15)/I15) -> 0.022727273 | ... M16: =IF(L15=0,"n/a",+(M15-L15)/L15) -> 0.021276596 | N16: n/a | O16: =IF(M15=0,"n/a",+(O15-M15)/M15) -> -1 | P16: =IF(O15=0,"n/a",+(P15-O15)/O15) -> n/a | Q16: =IF(P15=0,"n/a",+(Q15-P15)/P15) -> 0.028571429 | R16: =IF(Q15=0,"n/a",+(R15-Q15)/Q15) -> 0.027777778 | S16: =IF(R15=0,"n/a",+(S15-R15)/R15) -> 0.027027027 | T16: =IF(S15=0,"n/a",+(T15-S15)/S15) -> 0.10526316 | U16: =IF(T15=0,"n/a",+(U15-T15)/T15) -> 0.023809524 | V16: =IF(U15=0,"n/a",+(V15-U15)/U15) -> 0.023255814 | W16: =IF(V15=0,"n/a",+(W15-V15)/V15) -> 0.022727273 | ... Z16: =IF(Y15=0,"n/a",+(Z15-Y15)/Y15) -> 0.063829787 | AA16: =IF(N15=0,"n/a",+(AA15-N15)/N15) -> 0.64393858 | AB16: =IF(Z15=0,"n/a",+(AB15-Z15)/Z15) -> 0.13333333 | AC16: =IF(AB15=0,"n/a",+(AC15-AB15)/AB15) -> 0.070588235 | AD16: =IF(AC15=0,"n/a",+(AD15-AC15)/AC15) -> 0.016483516 | AE16: =IF(AD15=0,"n/a",+(AE15-AD15)/AD15) -> 0 | AF16: =IF(AE15=0,"n/a",+(AF15-AE15)/AE15) -> 0 | AG16: =IF(AF15=0,"n/a",+(AG15-AF15)/AF15) -> 0 | AH16: =IF(AG15=0,"n/a",+(AH15-AG15)/AG15) -> 0 | AI16: =IF(AH15=0,"n/a",+(AI15-AH15)/AH15) -> 0 | AJ16: =IF(AI15=0,"n/a",+(AJ15-AI15)/AI15) -> 0 | ... AM16: =IF(AL15=0,"n/a",+(AM15-AL15)/AL15) -> 0 | AN16: =IF(AA15=0,"n/a",+(AN15-AA15)/AA15) -> 0.589371 | AO16: =IF(AM15=0,"n/a",+(AO15-AM15)/AM15) -> 0.10810811 | AP16: =IF(AO15=0,"n/a",+(AP15-AO15)/AO15) -> 0.087804878 | AQ16: =IF(AP15=0,"n/a",+(AQ15-AP15)/AP15) -> 0.085201794 | AR16: =IF(AQ15=0,"n/a",+(AR15-AQ15)/AQ15) -> 0.078512397 | AS16: =IF(AR15=0,"n/a",+(AS15-AR15)/AR15) -> 0.049808429 | AT16: =IF(AS15=0,"n/a",+(AT15-AS15)/AS15) -> 0 | AU16: =IF(AT15=0,"n/a",+(AU15-AT15)/AT15) -> 0.025547445 | AV16: =IF(AU15=0,"n/a",+(AV15-AU15)/AU15) -> 0 | AW16: =IF(AV15=0,"n/a",+(AW15-AV15)/AV15) -> 0 | ... AZ16: =IF(AY15=0,"n/a",+(AZ15-AY15)/AY15) -> 0 | BA16: =IF(AN15=0,"n/a",+(BA15-AN15)/AN15) -> 0.43961608 | BB16: =IF(AZ15=0,"n/a",+(BB15-AZ15)/AZ15) -> 0.035587189 | BC16: =IF(BB15=0,"n/a",+(BC15-BB15)/BB15) -> 0.065292096 | BD16: =IF(BC15=0,"n/a",+(BD15-BC15)/BC15) -> 0.022580645 | BE16: =IF(BD15=0,"n/a",+(BE15-BD15)/BD15) -> 0.059936909 | BF16: =IF(BE15=0,"n/a",+(BF15-BE15)/BE15) -> 0.029761905 | BG16: =IF(BF15=0,"n/a",+(BG15-BF15)/BF15) -> 0.046242775 | BH16: =IF(BG15=0,"n/a",+(BH15-BG15)/BG15) -> 0.027624309 | BI16: =IF(BH15=0,"n/a",+(BI15-BH15)/BH15) -> 0.051075269 | BJ16: =IF(BI15=0,"n/a",+(BJ15-BI15)/BI15) -> 0.017902813 | ... BM16: =IF(BL15=0,"n/a",+(BM15-BL15)/BL15) -> 0.035955056 | BN16: =IF(BA15=0,"n/a",+(BN15-BA15)/BA15) -> 0.40609647
A17: COGS | B17: ='Monthly Income'!C8 -> 28021 | C17: ='Monthly Income'!D8 -> 161084 | D17: ='Monthly Income'!E8 -> 336231 | E17: ='Monthly Income'!F8 -> 434430.5 | F17: ='Monthly Income'!G8 -> 574682.5 | G17: ='Monthly Income'!H8 -> 588955.5 | H17: ='Monthly Income'!I8 -> 603249.5 | I17: ='Monthly Income'!J8 -> 617564.5 | ... M17: ='Monthly Income'!N8 -> 675034.5 | N17: =SUM(B17:M17) -> 5958046.5 | O17: ='Monthly Income'!O8 -> 686696.4 | P17: ='Monthly Income'!P8 -> 707198.4 | Q17: ='Monthly Income'!Q8 -> 727710.45 | R17: ='Monthly Income'!R8 -> 748232.55 | S17: ='Monthly Income'!S8 -> 768764.7 | T17: ='Monthly Income'!T8 -> 849616.95 | U17: ='Monthly Income'!U8 -> 870179.25 | V17: ='Monthly Income'!V8 -> 890751.6 | ... Z17: ='Monthly Income'!Z8 -> 1013351.6 | AA17: =SUM(O17:Z17) -> 10058291 | AB17: ='Monthly Income'!AA8 -> 1100808.1 | AC17: ='Monthly Income'!AB8 -> 1178476.7 | AD17: ='Monthly Income'!AC8 -> 1198330 | AE17: ='Monthly Income'!AD8 -> 1198908.2 | AF17: ='Monthly Income'!AE8 -> 1199486.5 | AG17: ='Monthly Income'!AF8 -> 1200064.7 | AH17: ='Monthly Income'!AG8 -> 1200643 | AI17: ='Monthly Income'!AH8 -> 1201221.2 | ... AM17: ='Monthly Income'!AL8 -> 1203534.2 | AN17: =SUM(AB17:AM17) -> 14288606 | AO17: ='Monthly Income'!AM8 -> 1327475.2 | AP17: ='Monthly Income'!AN8 -> 1443328 | AQ17: ='Monthly Income'!AO8 -> 1565619.2 | AR17: ='Monthly Income'!AP8 -> 1687948.8 | AS17: ='Monthly Income'!AQ8 -> 1771907.2 | AT17: ='Monthly Income'!AR8 -> 1772665.6 | AU17: ='Monthly Income'!AS8 -> 1818243.2 | AV17: ='Monthly Income'!AT8 -> 1819020.8 | ... AZ17: ='Monthly Income'!AX8 -> 1822131.2 | BA17: =SUM(AO17:AZ17) -> 20490067 | BB17: ='Monthly Income'!AY8 -> 1857454.2 | BC17: ='Monthly Income'!AZ8 -> 1977985.8 | BD17: ='Monthly Income'!BA8 -> 2022936.3 | BE17: ='Monthly Income'!BB8 -> 2143524.6 | BF17: ='Monthly Income'!BC8 -> 2207441.2 | BG17: ='Monthly Income'!BD8 -> 2309186.2 | BH17: ='Monthly Income'!BE8 -> 2373159.6 | BI17: ='Monthly Income'!BF8 -> 2493870.8 | ... BM17: ='Monthly Income'!BJ8 -> 2939227.2 | BN17: =SUM(BB17:BM17) -> 28360839
A18: Gross Profit | B18: =B15-B17 -> 11979 | C18: =C15-C17 -> 68916 | D18: =D15-D17 -> 143769 | E18: =E15-E17 -> 185569.5 | F18: =F15-F17 -> 245317.5 | G18: =G15-G17 -> 251044.5 | H18: =H15-H17 -> 256750.5 | I18: =I15-I17 -> 262435.5 | ... BN18: =BN15-BN17 -> 16656366
A19: Margin | B19: =IF(B15=0,"n/a",B18/B15) -> 0.299475 | C19: =IF(C15=0,"n/a",C18/C15) -> 0.29963478 | D19: =IF(D15=0,"n/a",D18/D15) -> 0.29951875 | E19: =IF(E15=0,"n/a",E18/E15) -> 0.29930565 | F19: =IF(F15=0,"n/a",F18/F15) -> 0.29916768 | G19: =IF(G15=0,"n/a",G18/G15) -> 0.2988625 | H19: =IF(H15=0,"n/a",H18/H15) -> 0.29854709 | I19: =IF(I15=0,"n/a",I18/I15) -> 0.29822216 | ... BN19: =IF(BN15=0,"n/a",BN18/BN15) -> 0.37
A20: Salary & Wages | B20: ='Monthly Income'!C12 -> 58333.333 | C20: ='Monthly Income'!D12 -> 58333.333 | D20: ='Monthly Income'!E12 -> 58333.333 | E20: ='Monthly Income'!F12 -> 73333.333 | F20: ='Monthly Income'!G12 -> 73333.333 | G20: ='Monthly Income'!H12 -> 73333.333 | H20: ='Monthly Income'!I12 -> 73333.333 | I20: ='Monthly Income'!J12 -> 87916.667 | ... M20: ='Monthly Income'!N12 -> 195000 | N20: =SUM(B20:M20) -> 1237916.7 | O20: ='Monthly Income'!O12 -> 201666.67 | P20: ='Monthly Income'!P12 -> 208333.33 | Q20: ='Monthly Income'!Q12 -> 208333.33 | R20: ='Monthly Income'!R12 -> 208333.33 | S20: ='Monthly Income'!S12 -> 208333.33 | T20: ='Monthly Income'!T12 -> 208333.33 | U20: ='Monthly Income'!U12 -> 208333.33 | V20: ='Monthly Income'!V12 -> 329166.67 | ... Z20: ='Monthly Income'!Z12 -> 361250 | AA20: =SUM(O20:Z20) -> 3178333.3 | AB20: ='Monthly Income'!AA12 -> 368750 | AC20: ='Monthly Income'!AB12 -> 368750 | AD20: ='Monthly Income'!AC12 -> 375833.33 | AE20: ='Monthly Income'!AD12 -> 382916.67 | AF20: ='Monthly Income'!AE12 -> 382916.67 | AG20: ='Monthly Income'!AF12 -> 382916.67 | AH20: ='Monthly Income'!AG12 -> 382916.67 | AI20: ='Monthly Income'!AH12 -> 382916.67 | ... AM20: ='Monthly Income'!AL12 -> 382916.67 | AN20: =SUM(AB20:AM20) -> 4559583.3 | AO20: ='Monthly Income'!AM12 -> 382916.67 | AP20: ='Monthly Income'!AN12 -> 382916.67 | AQ20: ='Monthly Income'!AO12 -> 382916.67 | AR20: ='Monthly Income'!AP12 -> 382916.67 | AS20: ='Monthly Income'!AQ12 -> 382916.67 | AT20: ='Monthly Income'!AR12 -> 382916.67 | AU20: ='Monthly Income'!AS12 -> 382916.67 | AV20: ='Monthly Income'!AT12 -> 382916.67 | ... AZ20: ='Monthly Income'!AX12 -> 382916.67 | BA20: =SUM(AO20:AZ20) -> 4595000 | BB20: ='Monthly Income'!AY12 -> 449583.33 | BC20: ='Monthly Income'!AZ12 -> 449583.33 | BD20: ='Monthly Income'!BA12 -> 449583.33 | BE20: ='Monthly Income'!BB12 -> 449583.33 | BF20: ='Monthly Income'!BC12 -> 449583.33 | BG20: ='Monthly Income'!BD12 -> 449583.33 | BH20: ='Monthly Income'!BE12 -> 449583.33 | BI20: ='Monthly Income'!BF12 -> 449583.33 | ... BM20: ='Monthly Income'!BJ12 -> 449583.33 | BN20: =SUM(BB20:BM20) -> 5395000
A21: Employee Related Expenses | B21: ='Monthly Income'!C13 -> 10354.167 | C21: ='Monthly Income'!D13 -> 10354.167 | D21: ='Monthly Income'!E13 -> 10354.167 | E21: ='Monthly Income'!F13 -> 13176.667 | F21: ='Monthly Income'!G13 -> 13176.667 | G21: ='Monthly Income'!H13 -> 13176.667 | H21: ='Monthly Income'!I13 -> 13176.667 | I21: ='Monthly Income'!J13 -> 15940.208 | ... M21: ='Monthly Income'!N13 -> 37392.5 | N21: =SUM(B21:M21) -> 229765.21 | O21: ='Monthly Income'!O13 -> 38685.833 | P21: ='Monthly Income'!P13 -> 39979.167 | Q21: ='Monthly Income'!Q13 -> 39979.167 | R21: ='Monthly Income'!R13 -> 39979.167 | S21: ='Monthly Income'!S13 -> 39979.167 | T21: ='Monthly Income'!T13 -> 39979.167 | U21: ='Monthly Income'!U13 -> 39979.167 | V21: ='Monthly Income'!V13 -> 66877.083 | ... Z21: ='Monthly Income'!Z13 -> 83316.875 | AA21: =SUM(O21:Z21) -> 661484.17 | AB21: ='Monthly Income'!AA13 -> 85078.125 | AC21: ='Monthly Income'!AB13 -> 83678.125 | AD21: ='Monthly Income'!AC13 -> 86080.417 | AE21: ='Monthly Income'!AD13 -> 87782.708 | AF21: ='Monthly Income'!AE13 -> 88482.708 | AG21: ='Monthly Income'!AF13 -> 88482.708 | AH21: ='Monthly Income'!AG13 -> 88482.708 | AI21: ='Monthly Income'!AH13 -> 88482.708 | ... AM21: ='Monthly Income'!AL13 -> 88482.708 | AN21: =SUM(AB21:AM21) -> 1050481 | AO21: ='Monthly Income'!AM13 -> 88482.708 | AP21: ='Monthly Income'!AN13 -> 88482.708 | AQ21: ='Monthly Income'!AO13 -> 88482.708 | AR21: ='Monthly Income'!AP13 -> 88482.708 | AS21: ='Monthly Income'!AQ13 -> 88482.708 | AT21: ='Monthly Income'!AR13 -> 88482.708 | AU21: ='Monthly Income'!AS13 -> 88482.708 | AV21: ='Monthly Income'!AT13 -> 88482.708 | ... AZ21: ='Monthly Income'!AX13 -> 88482.708 | BA21: =SUM(AO21:AZ21) -> 1061792.5 | BB21: ='Monthly Income'!AY13 -> 97916.042 | BC21: ='Monthly Income'!AZ13 -> 97916.042 | BD21: ='Monthly Income'!BA13 -> 97916.042 | BE21: ='Monthly Income'!BB13 -> 97916.042 | BF21: ='Monthly Income'!BC13 -> 97916.042 | BG21: ='Monthly Income'!BD13 -> 97916.042 | BH21: ='Monthly Income'!BE13 -> 97916.042 | BI21: ='Monthly Income'!BF13 -> 97916.042 | ... BM21: ='Monthly Income'!BJ13 -> 97916.042 | BN21: =SUM(BB21:BM21) -> 1174992.5
A22: Product Design & Development | B22: ='Monthly Income'!C14 -> 5300 | C22: ='Monthly Income'!D14 -> 5300 | D22: ='Monthly Income'!E14 -> 5300 | E22: ='Monthly Income'!F14 -> 5300 | F22: ='Monthly Income'!G14 -> 5300 | G22: ='Monthly Income'!H14 -> 5300 | H22: ='Monthly Income'!I14 -> 5300 | I22: ='Monthly Income'!J14 -> 5300 | ... M22: ='Monthly Income'!N14 -> 5300 | N22: =SUM(B22:M22) -> 63600 | O22: ='Monthly Income'!O14 -> 5500 | P22: ='Monthly Income'!P14 -> 5500 | Q22: ='Monthly Income'!Q14 -> 5500 | R22: ='Monthly Income'!R14 -> 5500 | S22: ='Monthly Income'!S14 -> 5500 | T22: ='Monthly Income'!T14 -> 5500 | U22: ='Monthly Income'!U14 -> 5500 | V22: ='Monthly Income'!V14 -> 5500 | ... Z22: ='Monthly Income'!Z14 -> 5500 | AA22: =SUM(O22:Z22) -> 66000 | AB22: ='Monthly Income'!AA14 -> 6050 | AC22: ='Monthly Income'!AB14 -> 6050 | AD22: ='Monthly Income'!AC14 -> 6050 | AE22: ='Monthly Income'!AD14 -> 6050 | AF22: ='Monthly Income'!AE14 -> 6050 | AG22: ='Monthly Income'!AF14 -> 6050 | AH22: ='Monthly Income'!AG14 -> 6050 | AI22: ='Monthly Income'!AH14 -> 6050 | ... AM22: ='Monthly Income'!AL14 -> 6050 | AN22: =SUM(AB22:AM22) -> 72600 | AO22: ='Monthly Income'!AM14 -> 6655 | AP22: ='Monthly Income'!AN14 -> 6655 | AQ22: ='Monthly Income'!AO14 -> 6655 | AR22: ='Monthly Income'!AP14 -> 6655 | AS22: ='Monthly Income'!AQ14 -> 6655 | AT22: ='Monthly Income'!AR14 -> 6655 | AU22: ='Monthly Income'!AS14 -> 6655 | AV22: ='Monthly Income'!AT14 -> 6655 | ... AZ22: ='Monthly Income'!AX14 -> 6655 | BA22: =SUM(AO22:AZ22) -> 79860 | BB22: ='Monthly Income'!AY14 -> 7320.5 | BC22: ='Monthly Income'!AZ14 -> 7320.5 | BD22: ='Monthly Income'!BA14 -> 7320.5 | BE22: ='Monthly Income'!BB14 -> 7320.5 | BF22: ='Monthly Income'!BC14 -> 7320.5 | BG22: ='Monthly Income'!BD14 -> 7320.5 | BH22: ='Monthly Income'!BE14 -> 7320.5 | BI22: ='Monthly Income'!BF14 -> 7320.5 | ... BM22: ='Monthly Income'!BJ14 -> 7320.5 | BN22: =SUM(BB22:BM22) -> 87846
A23: Sales & Marketing | B23: ='Monthly Income'!C15 -> 8569.0653 | C23: ='Monthly Income'!D15 -> 21875.365 | D23: ='Monthly Income'!E15 -> 39390.065 | E23: ='Monthly Income'!F15 -> 49210.015 | F23: ='Monthly Income'!G15 -> 63235.215 | G23: ='Monthly Income'!H15 -> 64662.515 | H23: ='Monthly Income'!I15 -> 66091.915 | I23: ='Monthly Income'!J15 -> 67523.415 | ... M23: ='Monthly Income'!N15 -> 73270.415 | N23: =SUM(B23:M23) -> 665008.23 | O23: ='Monthly Income'!O15 -> 77511.365 | P23: ='Monthly Income'!P15 -> 79653.365 | Q23: ='Monthly Income'!Q15 -> 81796.415 | R23: ='Monthly Income'!R15 -> 83940.515 | S23: ='Monthly Income'!S15 -> 86085.665 | T23: ='Monthly Income'!T15 -> 94532.915 | U23: ='Monthly Income'!U15 -> 96681.215 | V23: ='Monthly Income'!V15 -> 98830.565 | ... Z23: ='Monthly Income'!Z15 -> 111639.52 | AA23: =SUM(O23:Z23) -> 1120069.8 | AB23: ='Monthly Income'!AA15 -> 125699.37 | AC23: ='Monthly Income'!AB15 -> 134161.32 | AD23: ='Monthly Income'!AC15 -> 136324.32 | AE23: ='Monthly Income'!AD15 -> 136387.32 | AF23: ='Monthly Income'!AE15 -> 136450.32 | AG23: ='Monthly Income'!AF15 -> 136513.32 | AH23: ='Monthly Income'!AG15 -> 136576.32 | AI23: ='Monthly Income'!AH15 -> 136639.32 | ... AM23: ='Monthly Income'!AL15 -> 136891.32 | AN23: =SUM(AB23:AM23) -> 1625938.8 | AO23: ='Monthly Income'!AM15 -> 130217.77 | AP23: ='Monthly Income'!AN15 -> 141078.97 | AQ23: ='Monthly Income'!AO15 -> 152543.77 | AR23: ='Monthly Income'!AP15 -> 164012.17 | AS23: ='Monthly Income'!AQ15 -> 171883.27 | AT23: ='Monthly Income'!AR15 -> 171954.37 | AU23: ='Monthly Income'!AS15 -> 176227.27 | AV23: ='Monthly Income'!AT15 -> 176300.17 | ... AZ23: ='Monthly Income'!AX15 -> 176591.77 | BA23: =SUM(AO23:AZ23) -> 1990147.4 | BB23: ='Monthly Income'!AY15 -> 182667.37 | BC23: ='Monthly Income'!AZ15 -> 194146.57 | BD23: ='Monthly Income'!BA15 -> 198427.57 | BE23: ='Monthly Income'!BB15 -> 209912.17 | BF23: ='Monthly Income'!BC15 -> 215999.47 | BG23: ='Monthly Income'!BD15 -> 225689.47 | BH23: ='Monthly Income'!BE15 -> 231782.17 | BI23: ='Monthly Income'!BF15 -> 243278.47 | ... BM23: ='Monthly Income'!BJ15 -> 285693.37 | BN23: =SUM(BB23:BM23) -> 2770235.9
A24: G & A Expenses | B24: ='Monthly Income'!C16 -> 7745.9833 | C24: ='Monthly Income'!D16 -> 8696.4333 | D24: ='Monthly Income'!E16 -> 9947.4833 | E24: ='Monthly Income'!F16 -> 11823.908 | F24: ='Monthly Income'!G16 -> 12825.708 | G24: ='Monthly Income'!H16 -> 13277.658 | H24: ='Monthly Income'!I16 -> 14879.758 | I24: ='Monthly Income'!J16 -> 14657.008 | ... M24: ='Monthly Income'!N16 -> 25642.508 | N24: =SUM(B24:M24) -> 186407.48 | O24: ='Monthly Income'!O16 -> 26532.933 | P24: ='Monthly Income'!P16 -> 27273.433 | Q24: ='Monthly Income'!Q16 -> 27426.508 | R24: ='Monthly Income'!R16 -> 27579.658 | S24: ='Monthly Income'!S16 -> 27732.883 | T24: ='Monthly Income'!T16 -> 28336.258 | U24: ='Monthly Income'!U16 -> 28489.708 | V24: ='Monthly Income'!V16 -> 45093.233 | ... Z24: ='Monthly Income'!Z16 -> 65983.158 | AA24: =SUM(O24:Z24) -> 482949.38 | AB24: ='Monthly Income'!AA16 -> 68162.433 | AC24: ='Monthly Income'!AB16 -> 66416.858 | AD24: ='Monthly Income'!AC16 -> 68921.358 | AE24: ='Monthly Income'!AD16 -> 70100.858 | AF24: ='Monthly Income'!AE16 -> 71280.358 | AG24: ='Monthly Income'!AF16 -> 71284.858 | AH24: ='Monthly Income'!AG16 -> 71289.358 | AI24: ='Monthly Income'!AH16 -> 71293.858 | ... AM24: ='Monthly Income'!AL16 -> 71311.858 | AN24: =SUM(AB24:AM24) -> 843970.38 | AO24: ='Monthly Income'!AM16 -> 72316.733 | AP24: ='Monthly Income'!AN16 -> 73221.833 | AQ24: ='Monthly Income'!AO16 -> 74177.233 | AR24: ='Monthly Income'!AP16 -> 75132.933 | AS24: ='Monthly Income'!AQ16 -> 75788.858 | AT24: ='Monthly Income'!AR16 -> 75794.783 | AU24: ='Monthly Income'!AS16 -> 76150.858 | AV24: ='Monthly Income'!AT16 -> 76156.933 | ... AZ24: ='Monthly Income'!AX16 -> 76181.233 | BA24: =SUM(AO24:AZ24) -> 903428.65 | BB24: ='Monthly Income'!AY16 -> 76687.533 | BC24: ='Monthly Income'!AZ16 -> 77644.133 | BD24: ='Monthly Income'!BA16 -> 78000.883 | BE24: ='Monthly Income'!BB16 -> 78957.933 | BF24: ='Monthly Income'!BC16 -> 79465.208 | BG24: ='Monthly Income'!BD16 -> 80272.708 | BH24: ='Monthly Income'!BE16 -> 80780.433 | BI24: ='Monthly Income'!BF16 -> 81738.458 | ... BM24: ='Monthly Income'!BJ16 -> 85273.033 | BN24: =SUM(BB24:BM24) -> 968436.03
A25: Total Operating Expenses | B25: =SUM(B20:B24) -> 90302.549 | C25: =SUM(C20:C24) -> 104559.3 | D25: =SUM(D20:D24) -> 123325.05 | E25: =SUM(E20:E24) -> 152843.92 | F25: =SUM(F20:F24) -> 167870.92 | G25: =SUM(G20:G24) -> 169750.17 | H25: =SUM(H20:H24) -> 172781.67 | I25: =SUM(I20:I24) -> 191337.3 | ... BN25: =SUM(BN20:BN24) -> 10396510
A27: % of sales | B27: =IF(B15=0,"n/a",B25/B15) -> 2.2575637 | C27: =IF(C15=0,"n/a",C25/C15) -> 0.45460565 | D27: =IF(D15=0,"n/a",D25/D15) -> 0.25692718 | E27: =IF(E15=0,"n/a",E25/E15) -> 0.24652246 | F27: =IF(F15=0,"n/a",F25/F15) -> 0.20472064 | G27: =IF(G15=0,"n/a",G25/G15) -> 0.20208354 | H27: =IF(H15=0,"n/a",H25/H15) -> 0.20090892 | I27: =IF(I15=0,"n/a",I25/I15) -> 0.21742875 | ... BN27: =IF(BN15=0,"n/a",BN25/BN15) -> 0.23094527
A28: EBITDA | B28: =B18-B25 -> -78323.549 | C28: =C18-C25 -> -35643.299 | D28: =D18-D25 -> 20443.951 | E28: =E18-E25 -> 32725.576 | F28: =F18-F25 -> 77446.576 | G28: =G18-G25 -> 81294.326 | H28: =H18-H25 -> 83968.826 | I28: =I18-I25 -> 71098.201 | ... BN28: =BN18-BN25 -> 6259855.4
A29: % of sales | B29: =IF(B15=0,"n/a",B28/B15) -> -1.9580887 | C29: =IF(C15=0,"n/a",C28/C15) -> -0.15497086 | D29: =IF(D15=0,"n/a",D28/D15) -> 0.042591565 | E29: =IF(E15=0,"n/a",E28/E15) -> 0.052783188 | F29: =IF(F15=0,"n/a",F28/F15) -> 0.094447044 | G29: =IF(G15=0,"n/a",G28/G15) -> 0.09677896 | H29: =IF(H15=0,"n/a",H28/H15) -> 0.09763817 | I29: =IF(I15=0,"n/a",I28/I15) -> 0.080793411 | ... BN29: =IF(BN15=0,"n/a",BN28/BN15) -> 0.13905473
A30: EBIT | B30: ='Monthly Income'!C24 -> -78343.549 | C30: ='Monthly Income'!D24 -> -35573.299 | D30: ='Monthly Income'!E24 -> 20723.951 | E30: ='Monthly Income'!F24 -> 33273.91 | F30: ='Monthly Income'!G24 -> 78354.91 | G30: ='Monthly Income'!H24 -> 82592.66 | H30: ='Monthly Income'!I24 -> 85687.16 | I30: ='Monthly Income'!J24 -> 73249.868 | ... M30: ='Monthly Income'!N24 -> -47538.257 | N30: =SUM(B30:M30) -> 169450.92 | O30: ='Monthly Income'!O24 -> -11914.865 | P30: ='Monthly Income'!P24 -> -12667.699 | Q30: ='Monthly Income'!Q24 -> -4860.8736 | R30: ='Monthly Income'!R24 -> 2949.7764 | S30: ='Monthly Income'!S24 -> 10764.251 | T30: ='Monthly Income'!T24 -> 41536.376 | U30: ='Monthly Income'!U24 -> 49362.326 | V30: ='Monthly Income'!V24 -> -107222.48 | ... Z30: ='Monthly Income'!Z24 -> -129342.77 | AA30: =SUM(O30:Z30) -> -559794.62 | AB30: ='Monthly Income'!AA24 -> -42011.357 | AC30: ='Monthly Income'!AB24 -> -4078.0111 | AD30: ='Monthly Income'!AC24 -> -7217.7194 | AE30: ='Monthly Income'!AD24 -> -16940.761 | AF30: ='Monthly Income'!AE24 -> -18578.178 | AG30: ='Monthly Income'!AF24 -> -18323.928 | AH30: ='Monthly Income'!AG24 -> -18069.678 | AI30: ='Monthly Income'!AH24 -> -17815.428 | ... AM30: ='Monthly Income'!AL24 -> -16798.428 | AN30: =SUM(AB30:AM30) -> -211754.27 | AO30: ='Monthly Income'!AM24 -> 65299.26 | AP30: ='Monthly Income'!AN24 -> 118700.16 | AQ30: ='Monthly Income'!AO24 -> 175068.76 | AR30: ='Monthly Income'!AP24 -> 231455.06 | AS30: ='Monthly Income'!AQ24 -> 270154.63 | AT30: ='Monthly Income'!AR24 -> 270504.21 | AU30: ='Monthly Income'!AS24 -> 291512.63 | AV30: ='Monthly Income'!AT24 -> 291871.06 | ... AZ30: ='Monthly Income'!AX24 -> 293304.76 | BA30: =SUM(AO30:AZ30) -> 2885634.3 | BB30: ='Monthly Income'!AY24 -> 275894.36 | BC30: ='Monthly Income'!AZ24 -> 334246.96 | BD30: ='Monthly Income'!BA24 -> 356008.71 | BE30: ='Monthly Income'!BB24 -> 414388.76 | BF30: ='Monthly Income'!BC24 -> 445332.53 | BG30: ='Monthly Income'!BD24 -> 494590.03 | BH30: ='Monthly Income'!BE24 -> 525561.26 | BI30: ='Monthly Income'!BF24 -> 584000.78 | ... BM30: ='Monthly Income'!BJ24 -> 799609.86 | BN30: =SUM(BB30:BM30) -> 6250055.4
A31: % of sales | B31: =IF(B15=0,"n/a",B30/B15) -> -1.9585887 | C31: =IF(C15=0,"n/a",C30/C15) -> -0.15466652 | D31: =IF(D15=0,"n/a",D30/D15) -> 0.043174899 | E31: =IF(E15=0,"n/a",E30/E15) -> 0.053667596 | F31: =IF(F15=0,"n/a",F30/F15) -> 0.095554768 | G31: =IF(G15=0,"n/a",G30/G15) -> 0.098324595 | H31: =IF(H15=0,"n/a",H30/H15) -> 0.099636232 | I31: =IF(I15=0,"n/a",I30/I15) -> 0.083238486 | ... BN31: =IF(BN15=0,"n/a",BN30/BN15) -> 0.13883704
A32: NI | B32: ='Monthly Income'!C28 -> -51706.742 | C32: ='Monthly Income'!D28 -> -23478.377 | D32: ='Monthly Income'!E28 -> 13677.808 | E32: ='Monthly Income'!F28 -> 21960.78 | F32: ='Monthly Income'!G28 -> 51714.24 | G32: ='Monthly Income'!H28 -> 54511.155 | H32: ='Monthly Income'!I28 -> 56553.525 | I32: ='Monthly Income'!J28 -> 48344.913 | ... M32: ='Monthly Income'!N28 -> -31375.25 | N32: =SUM(B32:M32) -> 111837.61 | O32: ='Monthly Income'!O28 -> -7863.8111 | P32: ='Monthly Income'!P28 -> -8360.6811 | Q32: ='Monthly Income'!Q28 -> -3208.1766 | R32: ='Monthly Income'!R28 -> 1946.8524 | S32: ='Monthly Income'!S28 -> 7104.4059 | T32: ='Monthly Income'!T28 -> 27414.008 | U32: ='Monthly Income'!U28 -> 32579.135 | V32: ='Monthly Income'!V28 -> -70766.838 | ... Z32: ='Monthly Income'!Z28 -> -85366.225 | AA32: =SUM(O32:Z32) -> -369464.45 | AB32: ='Monthly Income'!AA28 -> -27727.496 | AC32: ='Monthly Income'!AB28 -> -2691.4873 | AD32: ='Monthly Income'!AC28 -> -4763.6948 | AE32: ='Monthly Income'!AD28 -> -11180.902 | AF32: ='Monthly Income'!AE28 -> -12261.597 | AG32: ='Monthly Income'!AF28 -> -12093.792 | AH32: ='Monthly Income'!AG28 -> -11925.987 | AI32: ='Monthly Income'!AH28 -> -11758.182 | ... AM32: ='Monthly Income'!AL28 -> -11086.962 | AN32: =SUM(AB32:AM32) -> -139757.82 | AO32: ='Monthly Income'!AM28 -> 43097.511 | AP32: ='Monthly Income'!AN28 -> 78342.105 | AQ32: ='Monthly Income'!AO28 -> 115545.38 | AR32: ='Monthly Income'!AP28 -> 152760.34 | AS32: ='Monthly Income'!AQ28 -> 178302.06 | AT32: ='Monthly Income'!AR28 -> 178532.78 | AU32: ='Monthly Income'!AS28 -> 192398.34 | AV32: ='Monthly Income'!AT28 -> 192634.9 | ... AZ32: ='Monthly Income'!AX28 -> 193581.14 | BA32: =SUM(AO32:AZ32) -> 1904518.6 | BB32: ='Monthly Income'!AY28 -> 182090.28 | BC32: ='Monthly Income'!AZ28 -> 220602.99 | BD32: ='Monthly Income'!BA28 -> 234965.75 | BE32: ='Monthly Income'!BB28 -> 273496.58 | BF32: ='Monthly Income'!BC28 -> 293919.47 | BG32: ='Monthly Income'!BD28 -> 326429.42 | BH32: ='Monthly Income'!BE28 -> 346870.43 | BI32: ='Monthly Income'!BF28 -> 385440.52 | ... BM32: ='Monthly Income'!BJ28 -> 527742.51 | BN32: =SUM(BB32:BM32) -> 4125036.6
A33: % of sales | B33: =IF(B15=0,"n/a",B32/B15) -> -1.2926686 | C33: =IF(C15=0,"n/a",C32/C15) -> -0.1020799 | D33: =IF(D15=0,"n/a",D32/D15) -> 0.028495433 | E33: =IF(E15=0,"n/a",E32/E15) -> 0.035420614 | F33: =IF(F15=0,"n/a",F32/F15) -> 0.063066147 | G33: =IF(G15=0,"n/a",G32/G15) -> 0.064894233 | H33: =IF(H15=0,"n/a",H32/H15) -> 0.065759913 | I33: =IF(I15=0,"n/a",I32/I15) -> 0.054937401 | ... BN33: =IF(BN15=0,"n/a",BN32/BN15) -> 0.091632446
A34: Cash
A35: Cash, Beginning Balance | B35: =Cashflow!G24 -> 155313.26 | C35: =Cashflow!H24 -> 155313.26 | D35: =Cashflow!I24 -> 220308.38 | E35: =Cashflow!J24 -> 242844.19 | F35: =Cashflow!K24 -> 107097.89 | G35: =Cashflow!L24 -> 217530.04 | H35: =Cashflow!M24 -> 224722.37 | I35: =Cashflow!N24 -> 260927.06 | ... M35: =Cashflow!R24 -> 190595.52 | N35: =B35 -> 155313.26 | O35: =Cashflow!S24 -> 137888.11 | P35: =Cashflow!T24 -> 90557.011 | Q35: =Cashflow!U24 -> 31933.78 | R35: =Cashflow!V24 -> 9998363.1 | S35: =Cashflow!W24 -> 9969932.4 | T35: =Cashflow!X24 -> 9946644.3 | U35: =Cashflow!Y24 -> 9868488.2 | V35: =Cashflow!Z24 -> 9855779.9 | ... Z35: =Cashflow!AD24 -> 9373703.1 | AA35: =N38 -> 293201.36 | AB35: =Cashflow!AE24 -> 9205228.5 | AC35: =Cashflow!AF24 -> 9018149.9 | AD35: =Cashflow!AG24 -> 8862232.4 | AE35: =Cashflow!AH24 -> 8809267.2 | AF35: =Cashflow!AI24 -> 8791623.8 | AG35: =Cashflow!AJ24 -> 8778278.9 | AH35: =Cashflow!AK24 -> 8766101.7 | AI35: =Cashflow!AL24 -> 8754092.4 | ... AM35: =Cashflow!AP24 -> 8707733.2 | AN35: =AA38 -> 9360541.8 | AO35: =Cashflow!AQ24 -> 8696562.9 | AP35: =Cashflow!AR24 -> 8577858.2 | AQ35: =Cashflow!AS24 -> 8470063.6 | AR35: =Cashflow!AT24 -> 8397156.4 | AS35: =Cashflow!AU24 -> 8359604.2 | AT35: =Cashflow!AV24 -> 8396746 | AU35: =Cashflow!AW24 -> 8551510.5 | AV35: =Cashflow!AX24 -> 8686115.9 | ... AZ35: =Cashflow!BB24 -> 9443881.5 | BA35: =AN38 -> 8851876.1 | BB35: =Cashflow!BC24 -> 9637064.3 | BC35: =Cashflow!BD24 -> 9751461.1 | BD35: =Cashflow!BE24 -> 9783986.4 | BE35: =Cashflow!BF24 -> 9926224.4 | BF35: =Cashflow!BG24 -> 10031339 | BG35: =Cashflow!BH24 -> 10207978 | BH35: =Cashflow!BI24 -> 10384833 | BI35: =Cashflow!BJ24 -> 10619883 | ... BM35: =Cashflow!BN24 -> 11638705 | BN35: =BA38 -> 9792377.6
A36: Change in Cash from Operations | B36: =Cashflow!G27 -> -94686.742 | C36: =Cashflow!H27 -> -185004.88 | D36: =Cashflow!I27 -> -227464.19 | E36: =Cashflow!J27 -> -135746.3 | F36: =Cashflow!K27 -> -139567.84 | G36: =Cashflow!L27 -> 7192.3221 | H36: =Cashflow!M27 -> 36204.692 | I36: =Cashflow!N27 -> 26982.746 | ... M36: =Cashflow!R27 -> -52707.416 | N36: =SUM(B36:M36) -> -862111.89 | O36: =Cashflow!S27 -> -47331.094 | P36: =Cashflow!T27 -> -58623.231 | Q36: =Cashflow!U27 -> -33570.702 | R36: =Cashflow!V27 -> -28430.673 | S36: =Cashflow!W27 -> -23288.119 | T36: =Cashflow!X27 -> -78156.042 | U36: =Cashflow!Y27 -> -12708.39 | V36: =Cashflow!Z27 -> -114986.03 | ... Z36: =Cashflow!AD27 -> -168474.61 | AA36: =SUM(O36:Z36) -> -932659.59 | AB36: =Cashflow!AE27 -> -187078.64 | AC36: =Cashflow!AF27 -> -155917.52 | AD36: =Cashflow!AG27 -> -52965.18 | AE36: =Cashflow!AH27 -> -17643.402 | AF36: =Cashflow!AI27 -> -13344.931 | AG36: =Cashflow!AJ27 -> -12177.126 | AH36: =Cashflow!AK27 -> -12009.321 | AI36: =Cashflow!AL27 -> -11841.516 | ... AM36: =Cashflow!AP27 -> -11170.296 | AN36: =SUM(AB36:AM36) -> -508665.64 | AO36: =Cashflow!AQ27 -> -118704.69 | AP36: =Cashflow!AR27 -> -107794.63 | AQ36: =Cashflow!AS27 -> -72907.152 | AR36: =Cashflow!AT27 -> -37552.194 | AS36: =Cashflow!AU27 -> 37141.826 | AT36: =Cashflow!AV27 -> 154764.45 | AU36: =Cashflow!AW27 -> 134605.41 | AV36: =Cashflow!AX27 -> 179636.57 | ... AZ36: =Cashflow!BB27 -> 193182.81 | BA36: =SUM(AO36:AZ36) -> 940501.44 | BB36: =Cashflow!BC27 -> 114396.74 | BC36: =Cashflow!BD27 -> 32525.36 | BD36: =Cashflow!BE27 -> 142237.97 | BE36: =Cashflow!BF27 -> 105114.35 | BF36: =Cashflow!BG27 -> 176639.46 | BG36: =Cashflow!BH27 -> 176854.41 | BH36: =Cashflow!BI27 -> 235050.42 | BI36: =Cashflow!BJ27 -> 211313.28 | ... BM36: =Cashflow!BN27 -> 344552.5 | BN36: =SUM(BB36:BM36) -> 2346193.7
A37: Change in Cash from Financing | B37: =Cashflow!G20 -> 250000 | C37: =Cashflow!H20 -> 250000 | D37: =Cashflow!I20 -> 250000 | E37: =Cashflow!J20 -> 0 | F37: =Cashflow!K20 -> 250000 | G37: =Cashflow!L20 -> 0 | H37: =Cashflow!M20 -> 0 | I37: =Cashflow!N20 -> 0 | ... M37: =Cashflow!R20 -> 0 | N37: =SUM(B37:M37) -> 1000000 | O37: =Cashflow!S20 -> 0 | P37: =Cashflow!T20 -> 0 | Q37: =Cashflow!U20 -> 10000000 | R37: =Cashflow!V20 -> 0 | S37: =Cashflow!W20 -> 0 | T37: =Cashflow!X20 -> 0 | U37: =Cashflow!Y20 -> 0 | V37: =Cashflow!Z20 -> 0 | ... Z37: =Cashflow!AD20 -> 0 | AA37: =SUM(O37:Z37) -> 10000000 | AB37: =Cashflow!AE20 -> 0 | AC37: =Cashflow!AF20 -> 0 | AD37: =Cashflow!AG20 -> 0 | AE37: =Cashflow!AH20 -> 0 | AF37: =Cashflow!AI20 -> 0 | AG37: =Cashflow!AJ20 -> 0 | AH37: =Cashflow!AK20 -> 0 | AI37: =Cashflow!AL20 -> 0 | ... AM37: =Cashflow!AP20 -> 0 | AN37: =SUM(AB37:AM37) -> 0 | AO37: =Cashflow!AQ20 -> 0 | AP37: =Cashflow!AR20 -> 0 | AQ37: =Cashflow!AS20 -> 0 | AR37: =Cashflow!AT20 -> 0 | AS37: =Cashflow!AU20 -> 0 | AT37: =Cashflow!AV20 -> 0 | AU37: =Cashflow!AW20 -> 0 | AV37: =Cashflow!AX20 -> 0 | ... AZ37: =Cashflow!BB20 -> 0 | BA37: =SUM(AO37:AZ37) -> 0 | BB37: =Cashflow!BC20 -> 0 | BC37: =Cashflow!BD20 -> 0 | BD37: =Cashflow!BE20 -> 0 | BE37: =Cashflow!BF20 -> 0 | BF37: =Cashflow!BG20 -> 0 | BG37: =Cashflow!BH20 -> 0 | BH37: =Cashflow!BI20 -> 0 | BI37: =Cashflow!BJ20 -> 0 | ... BM37: =Cashflow!BN20 -> 0 | BN37: =SUM(BB37:BM37) -> 0
A38: Cash, Ending Balance | B38: =SUM(B35:B37) -> 310626.52 | C38: =SUM(C35:C37) -> 220308.38 | D38: =SUM(D35:D37) -> 242844.19 | E38: =SUM(E35:E37) -> 107097.89 | F38: =SUM(F35:F37) -> 217530.04 | G38: =SUM(G35:G37) -> 224722.37 | H38: =SUM(H35:H37) -> 260927.06 | I38: =SUM(I35:I37) -> 287909.8 | ... BN38: =SUM(BN35:BN37) -> 12138571
A39: Headcount
A40: FTE & Contract | B40: ='People Costs'!H20+Contractors!H20 -> 5.25 | C40: ='People Costs'!I20+Contractors!I20 -> 8.25 | D40: ='People Costs'!J20+Contractors!J20 -> 8.25 | E40: ='People Costs'!K20+Contractors!K20 -> 11.5 | F40: ='People Costs'!L20+Contractors!L20 -> 13.5 | G40: ='People Costs'!M20+Contractors!M20 -> 17 | H40: ='People Costs'!N20+Contractors!N20 -> 4 | I40: ='People Costs'!O20+Contractors!O20 -> 5 | ... M40: ='People Costs'!S20+Contractors!S20 -> 14 | N40: =M40 -> 14 | O40: ='People Costs'!T20+Contractors!T20 -> 14.5 | P40: ='People Costs'!U20 -> 15 | Q40: ='People Costs'!V20 -> 15 | R40: ='People Costs'!W20 -> 15 | S40: ='People Costs'!X20 -> 15 | T40: ='People Costs'!Y20 -> 15 | U40: ='People Costs'!Z20 -> 15 | V40: ='People Costs'!AA20 -> 29 | W40: ='People Costs'!AB20 -> 39 | ... Z40: ='People Costs'!AE20 -> 46 | AA40: =Z40 -> 46 | AB40: ='People Costs'!AF20+Contractors!AF20 -> 47 | AC40: ='People Costs'!AG20+Contractors!AG20 -> 45 | AD40: ='People Costs'!AH20+Contractors!AH20 -> 47 | AE40: ='People Costs'!AI20+Contractors!AI20 -> 48 | AF40: ='People Costs'!AJ20+Contractors!AJ20 -> 49 | AG40: ='People Costs'!AK20+Contractors!AK20 -> 49 | AH40: ='People Costs'!AL20+Contractors!AL20 -> 49 | AI40: ='People Costs'!AM20+Contractors!AM20 -> 49 | ... AM40: ='People Costs'!AQ20+Contractors!AQ20 -> 49 | AN40: =AM40 -> 49 | AO40: ='People Costs'!AR20+Contractors!AR20 -> 49 | AP40: ='People Costs'!AS20+Contractors!AS20 -> 49 | AQ40: ='People Costs'!AT20+Contractors!AT20 -> 49 | AR40: ='People Costs'!AU20+Contractors!AU20 -> 49 | AS40: ='People Costs'!AV20+Contractors!AV20 -> 49 | AT40: ='People Costs'!AW20+Contractors!AW20 -> 49 | AU40: ='People Costs'!AX20+Contractors!AX20 -> 49 | AV40: ='People Costs'!AY20+Contractors!AY20 -> 49 | ... AZ40: ='People Costs'!BC20+Contractors!BC20 -> 49 | BA40: =AZ40 -> 49 | BB40: ='People Costs'!BD20+Contractors!BD20 -> 49 | BC40: ='People Costs'!BE20+Contractors!BE20 -> 49 | BD40: ='People Costs'!BF20+Contractors!BF20 -> 49 | BE40: ='People Costs'!BG20+Contractors!BG20 -> 49 | BF40: ='People Costs'!BH20+Contractors!BH20 -> 49 | BG40: ='People Costs'!BI20+Contractors!BI20 -> 49 | BH40: ='People Costs'!BJ20+Contractors!BJ20 -> 49 | BI40: ='People Costs'!BK20+Contractors!BK20 -> 49 | ... BM40: ='People Costs'!BO20+Contractors!BO20 -> 49 | BN40: =BM40 -> 49
A42: Rev Per FTE | N42: =+N15/N40 -> 607963.93 | O42: =+O15/O40 -> 0 | P42: =+P15/P40 -> 70000 | Q42: =+Q15/Q40 -> 72000 | R42: =+R15/R40 -> 74000 | S42: =+S15/S40 -> 76000 | T42: =+T15/T40 -> 84000 | U42: =+U15/U40 -> 86000 | ... BN42: =+BN15/BN40 -> 918718.47
A43: Marketing % of Rev | N43: =N23/N15 -> 0.078130603 | O43: =O23/O15 -> #DIV/0! | P43: =P23/P15 -> 0.075860348 | Q43: =Q23/Q15 -> 0.075737422 | R43: =R23/R15 -> 0.075622086 | S43: =S23/S15 -> 0.075513741 | T43: =T23/T15 -> 0.075026123 | U43: =U23/U15 -> 0.074946678 | ... BN43: =BN23/BN15 -> 0.06153727
A44: Investment | B44: =Cashflow!G19 -> 250000 | C44: =Cashflow!H19 -> 250000 | D44: =Cashflow!I19 -> 250000 | E44: =Cashflow!J19 | F44: =Cashflow!K19 -> 250000 | G44: =Cashflow!L19 -> 0 | H44: =Cashflow!M19 -> 0 | I44: =Cashflow!N19 -> 0 | ... M44: =Cashflow!R19 -> 0 | N44: =SUM(B44:M44) -> 1000000 | O44: =Cashflow!S19 -> 0 | P44: =Cashflow!T19 -> 0 | Q44: =Cashflow!U19 -> 10000000 | R44: =Cashflow!V19 -> 0 | S44: =Cashflow!W19 -> 0 | T44: =Cashflow!X19 -> 0 | U44: =Cashflow!Y19 | V44: =Cashflow!Z19 -> 0 | ... Z44: =Cashflow!AD19 -> 0 | AA44: =SUM(O44:Z44) -> 10000000 | AB44: =Cashflow!AE19 -> 0 | AC44: =Cashflow!AF19 -> 0 | AD44: =Cashflow!AG19 -> 0 | AE44: =Cashflow!AH19 -> 0 | AF44: =Cashflow!AI19 -> 0 | AG44: =Cashflow!AJ19 -> 0 | AH44: =Cashflow!AK19 -> 0 | AI44: =Cashflow!AL19 -> 0 | ... AM44: =Cashflow!AP19 -> 0 | AN44: =SUM(AB44:AM44) -> 0 | AO44: =Cashflow!AR19 -> 0 | AP44: =Cashflow!AS19 -> 0 | AQ44: =Cashflow!AT19 -> 0 | AR44: =Cashflow!AU19 -> 0 | AS44: =Cashflow!AV19 -> 0 | AT44: =Cashflow!AW19 -> 0 | AU44: =Cashflow!AX19 -> 0 | AV44: =Cashflow!AY19 -> 0 | ... AZ44: =Cashflow!BC19 -> 0 | BA44: =SUM(AO44:AZ44) -> 0 | BB44: =Cashflow!BD19 -> 0 | BC44: =Cashflow!BE19 -> 0 | BD44: =Cashflow!BF19 -> 0 | BE44: =Cashflow!BG19 -> 0 | BF44: =Cashflow!BH19 -> 0 | BG44: =Cashflow!BI19 -> 0 | BH44: =Cashflow!BJ19 -> 0 | BI44: =Cashflow!BK19 -> 0 | ... BM44: =Cashflow!BO19 | BN44: =SUM(BB44:BM44) -> 0
A45: Ending Cash | B45: =Cashflow!G25 -> 155313.26 | C45: =Cashflow!H25 -> 220308.38 | D45: =Cashflow!I25 -> 242844.19 | E45: =Cashflow!J25 -> 107097.89 | F45: =Cashflow!K25 -> 217530.04 | G45: =Cashflow!L25 -> 224722.37 | H45: =Cashflow!M25 -> 260927.06 | I45: =Cashflow!N25 -> 287909.8 | ... M45: =Cashflow!R25 -> 137888.11 | N45: =M45 -> 137888.11 | O45: =Cashflow!S25 -> 90557.011 | P45: =Cashflow!T25 -> 31933.78 | Q45: =Cashflow!U25 -> 9998363.1 | R45: =Cashflow!V25 -> 9969932.4 | S45: =Cashflow!W25 -> 9946644.3 | T45: =Cashflow!X25 -> 9868488.2 | U45: =Cashflow!Y25 -> 9855779.9 | V45: =Cashflow!Z25 -> 9740793.8 | ... Z45: =Cashflow!AD25 -> 9205228.5 | AA45: =Z45 -> 9205228.5 | AB45: =Cashflow!AE25 -> 9018149.9 | AC45: =Cashflow!AF25 -> 8862232.4 | AD45: =Cashflow!AG25 -> 8809267.2 | AE45: =Cashflow!AH25 -> 8791623.8 | AF45: =Cashflow!AI25 -> 8778278.9 | AG45: =Cashflow!AJ25 -> 8766101.7 | AH45: =Cashflow!AK25 -> 8754092.4 | AI45: =Cashflow!AL25 -> 8742250.9 | ... AM45: =Cashflow!AP25 -> 8696562.9 | AN45: =AM45 -> 8696562.9 | AO45: =Cashflow!AQ25 -> 8577858.2 | AP45: =Cashflow!AR25 -> 8470063.6 | AQ45: =Cashflow!AS25 -> 8397156.4 | AR45: =Cashflow!AT25 -> 8359604.2 | AS45: =Cashflow!AU25 -> 8396746 | AT45: =Cashflow!AV25 -> 8551510.5 | AU45: =Cashflow!AW25 -> 8686115.9 | AV45: =Cashflow!AX25 -> 8865752.4 | ... AZ45: =Cashflow!BB25 -> 9637064.3 | BA45: =AZ45 -> 9637064.3 | BB45: =Cashflow!BC25 -> 9751461.1 | BC45: =Cashflow!BD25 -> 9783986.4 | BD45: =Cashflow!BE25 -> 9926224.4 | BE45: =Cashflow!BF25 -> 10031339 | BF45: =Cashflow!BG25 -> 10207978 | BG45: =Cashflow!BH25 -> 10384833 | BH45: =Cashflow!BI25 -> 10619883 | BI45: =Cashflow!BJ25 -> 10831196 | ... BM45: =Cashflow!BN25 -> 11983258 | BN45: =BM45 -> 11983258
O48: =O15/O40 -> 0 | P48: =P15/P40 -> 70000 | Q48: =Q15/Q40 -> 72000 | R48: =R15/R40 -> 74000 | S48: =S15/S40 -> 76000 | T48: =T15/T40 -> 84000 | U48: =U15/U40 -> 86000 | V48: =V15/V40 -> 45517.241 | ... Z48: =Z15/Z40 -> 32608.696 | AB48: =AB15/AB40 -> 36170.213 | AC48: =AC15/AC40 -> 40444.444 | AD48: =AD15/AD40 -> 39361.702 | AE48: =AE15/AE40 -> 38541.667 | AF48: =AF15/AF40 -> 37755.102 | AG48: =AG15/AG40 -> 37755.102 | AH48: =AH15/AH40 -> 37755.102 | AI48: =AI15/AI40 -> 37755.102 | ... AM48: =AM15/AM40 -> 37755.102 | AO48: =AO15/AO40 -> 41836.735 | AP48: =AP15/AP40 -> 45510.204 | AQ48: =AQ15/AQ40 -> 49387.755 | AR48: =AR15/AR40 -> 53265.306 | AS48: =AS15/AS40 -> 55918.367 | AT48: =AT15/AT40 -> 55918.367 | AU48: =AU15/AU40 -> 57346.939 | AV48: =AV15/AV40 -> 57346.939 | ... AZ48: =AZ15/AZ40 -> 57346.939 | BB48: =BB15/BB40 -> 59387.755 | BC48: =BC15/BC40 -> 63265.306 | BD48: =BD15/BD40 -> 64693.878 | BE48: =BE15/BE40 -> 68571.429 | BF48: =BF15/BF40 -> 70612.245 | BG48: =BG15/BG40 -> 73877.551 | BH48: =BH15/BH40 -> 75918.367 | BI48: =BI15/BI40 -> 79795.918 | ... BM48: =BM15/BM40 -> 94081.633

Sheet Graphs
B5: Year 1 | C5: Year 2 | D5: Year 3 | E5: Year 4 | F5: Year 5
A6: Total Sales | B6: ='5-Yr Summary'!N15 -> 8511495 | C6: ='5-Yr Summary'!AA15 -> 13992375 | D6: ='5-Yr Summary'!AN15 -> 22239075 | E6: ='5-Yr Summary'!BA15 -> 32015730 | F6: ='5-Yr Summary'!BN15 -> 45017205
A7: Gross Profit | B7: ='5-Yr Summary'!N18 -> 2553448.5 | C7: =+'5-Yr Summary'!AA18 -> 3934083.8 | D7: =+'5-Yr Summary'!AN18 -> 7950469.3 | E7: =+'5-Yr Summary'!BA18 -> 11525663 | F7: =+'5-Yr Summary'!BN18 -> 16656366
A8: Total Operating Expenses | B8: =+'5-Yr Summary'!N25 -> 2382697.6 | C8: =+'5-Yr Summary'!AA25 -> 5508836.7 | D8: =+'5-Yr Summary'!AN25 -> 8152573.6 | E8: =+'5-Yr Summary'!BA25 -> 8630228.5 | F8: =+'5-Yr Summary'!BN25 -> 10396510
A9: EBITDA | B9: =+'5-Yr Summary'!N28 -> 170750.92 | C9: =+'5-Yr Summary'!AA28 -> -1574753 | D9: =+'5-Yr Summary'!AN28 -> -202104.27 | E9: =+'5-Yr Summary'!BA28 -> 2895434.3 | F9: =+'5-Yr Summary'!BN28 -> 6259855.4
A22: Total Sales | B22: =+B6 -> 8511495 | C22: =+C6 -> 13992375 | D22: =+D6 -> 22239075 | E22: =+E6 -> 32015730 | F22: =+F6 -> 45017205
A23: EBITDA | B23: =+B9 -> 170750.92 | C23: =+C9 -> -1574753 | D23: =+D9 -> -202104.27 | E23: =+E9 -> 2895434.3 | F23: =+F9 -> 6259855.4

Sheet Monthly Income
A1: UrbanWind
A2: Monthly Income Statements
C5: 44562 | D5: 44593 | E5: 44621 | F5: 44652 | G5: 44682 | H5: 44713 | I5: 44743 | J5: 44774 | K5: 44805 | L5: 44835 | M5: 44866 | N5: 44896 | O5: 44927 | P5: 44958 | Q5: 44986 | R5: 45017 | S5: 45047 | T5: 45078 | U5: 45108 | V5: 45139 | W5: 45170 | X5: 45200 | Y5: 45231 | Z5: 45261 | AA5: 45292 | AB5: 45323 | AC5: 45352 | AD5: 45383 | AE5: 45413 | AF5: 45444 | AG5: 45474 | AH5: 45505 | AI5: 45536 | AJ5: 45566 | AK5: 45597 | AL5: 45627 | AM5: 45658 | AN5: 45689 | AO5: 45717 | AP5: 45748 | AQ5: 45778 | AR5: 45809 | AS5: 45839 | AT5: 45870 | AU5: 45901 | AV5: 45931 | AW5: 45962 | AX5: 45992 | AY5: 46023 | AZ5: 46054 | BA5: 46082 | BB5: 46113 | BC5: 46143 | BD5: 46174 | BE5: 46204 | BF5: 46235 | BG5: 46266 | BH5: 46296 | BI5: 46327 | BJ5: 46357
A7: Sales | C7: ='Sales Forecast'!H37 -> 40030 | D7: ='Sales Forecast'!I37 -> 230120 | E7: ='Sales Forecast'!J37 -> 480330 | F7: ='Sales Forecast'!K37 -> 620615 | G7: ='Sales Forecast'!L37 -> 820975 | H7: ='Sales Forecast'!M37 -> 841365 | I7: ='Sales Forecast'!N37 -> 861785 | J7: ='Sales Forecast'!O37 -> 882235 | ... BJ7: ='Sales Forecast'!BO37 -> 4665440
A8: Cost of Goods Sold | C8: =COGS!G14 -> 28021 | D8: =COGS!H14 -> 161084 | E8: =COGS!I14 -> 336231 | F8: =COGS!J14 -> 434430.5 | G8: =COGS!K14 -> 574682.5 | H8: =COGS!L14 -> 588955.5 | I8: =COGS!M14 -> 603249.5 | J8: =COGS!N14 -> 617564.5 | ... BJ8: =COGS!BN14 -> 2939227.2
A9: Gross Profit | C9: =C7-C8 -> 12009 | D9: =D7-D8 -> 69036 | E9: =E7-E8 -> 144099 | F9: =F7-F8 -> 186184.5 | G9: =G7-G8 -> 246292.5 | H9: =H7-H8 -> 252409.5 | I9: =I7-I8 -> 258535.5 | J9: =J7-J8 -> 264670.5 | ... BJ9: =BJ7-BJ8 -> 1726212.8
A10: Gross Margin | C10: =+IF(C9>0,C9/C7,"n/a") -> 0.3 | D10: =+IF(D9>0,D9/D7,"n/a") -> 0.3 | E10: =+IF(E9>0,E9/E7,"n/a") -> 0.3 | F10: =+IF(F9>0,F9/F7,"n/a") -> 0.3 | G10: =+IF(G9>0,G9/G7,"n/a") -> 0.3 | H10: =+IF(H9>0,H9/H7,"n/a") -> 0.3 | I10: =+IF(I9>0,I9/I7,"n/a") -> 0.3 | J10: =+IF(J9>0,J9/J7,"n/a") -> 0.3 | ... BJ10: =+IF(BJ9>0,BJ9/BJ7,"n/a") -> 0.37
A11: Operating Expenses
A12: Salary & Wages | C12: ='People Costs'!H13 -> 58333.333 | D12: ='People Costs'!I13 -> 58333.333 | E12: ='People Costs'!J13 -> 58333.333 | F12: ='People Costs'!K13 -> 73333.333 | G12: ='People Costs'!L13 -> 73333.333 | H12: ='People Costs'!M13 -> 73333.333 | I12: ='People Costs'!N13 -> 73333.333 | J12: ='People Costs'!O13 -> 87916.667 | ... BJ12: ='People Costs'!BO13 -> 449583.33
A13: Employee Related Expenses | C13: ='People Costs'!H17 -> 10354.167 | D13: ='People Costs'!I17 -> 10354.167 | E13: ='People Costs'!J17 -> 10354.167 | F13: ='People Costs'!K17 -> 13176.667 | G13: ='People Costs'!L17 -> 13176.667 | H13: ='People Costs'!M17 -> 13176.667 | I13: ='People Costs'!N17 -> 13176.667 | J13: ='People Costs'!O17 -> 15940.208 | ... BJ13: ='People Costs'!BO17 -> 97916.042
A14: Product Design & Development | C14: =OpEx!G18 -> 5300 | D14: =OpEx!H18 -> 5300 | E14: =OpEx!I18 -> 5300 | F14: =OpEx!J18 -> 5300 | G14: =OpEx!K18 -> 5300 | H14: =OpEx!L18 -> 5300 | I14: =OpEx!M18 -> 5300 | J14: =OpEx!N18 -> 5300 | ... BJ14: =OpEx!BN18 -> 7320.5
A15: Sales & Marketing | C15: =OpEx!G27 -> 8569.0653 | D15: =OpEx!H27 -> 21875.365 | E15: =OpEx!I27 -> 39390.065 | F15: =OpEx!J27 -> 49210.015 | G15: =OpEx!K27 -> 63235.215 | H15: =OpEx!L27 -> 64662.515 | I15: =OpEx!M27 -> 66091.915 | J15: =OpEx!N27 -> 67523.415 | ... BJ15: =OpEx!BN27 -> 285693.37
A16: G & A Expenses | C16: =OpEx!G46 -> 7745.9833 | D16: =OpEx!H46 -> 8696.4333 | E16: =OpEx!I46 -> 9947.4833 | F16: =OpEx!J46 -> 11823.908 | G16: =OpEx!K46 -> 12825.708 | H16: =OpEx!L46 -> 13277.658 | I16: =OpEx!M46 -> 14879.758 | J16: =OpEx!N46 -> 14657.008 | ... BJ16: =OpEx!BN46 -> 85273.033
A17: Total Operating Expenses | C17: =SUM(C12:C16) -> 90302.549 | D17: =SUM(D12:D16) -> 104559.3 | E17: =SUM(E12:E16) -> 123325.05 | F17: =SUM(F12:F16) -> 152843.92 | G17: =SUM(G12:G16) -> 167870.92 | H17: =SUM(H12:H16) -> 169750.17 | I17: =SUM(I12:I16) -> 172781.67 | J17: =SUM(J12:J16) -> 191337.3 | ... BJ17: =SUM(BJ12:BJ16) -> 925786.27
A19: EBITDA | C19: =C9-C17 -> -78293.549 | D19: =D9-D17 -> -35523.299 | E19: =E9-E17 -> 20773.951 | F19: =F9-F17 -> 33340.576 | G19: =G9-G17 -> 78421.576 | H19: =H9-H17 -> 82659.326 | I19: =I9-I17 -> 85753.826 | J19: =J9-J17 -> 73333.201 | ... BJ19: =BJ9-BJ17 -> 800426.53
A20: % of Sales | C20: =+IF(C7>0,C19/C7,"n/a") -> -1.9558718 | D20: =+IF(D7>0,D19/D7,"n/a") -> -0.15436858 | E20: =+IF(E7>0,E19/E7,"n/a") -> 0.043249332 | F20: =+IF(F7>0,F19/F7,"n/a") -> 0.053721835 | G20: =+IF(G7>0,G19/G7,"n/a") -> 0.09552249 | H20: =+IF(H7>0,H19/H7,"n/a") -> 0.098244313 | I20: =+IF(I7>0,I19/I7,"n/a") -> 0.099507216 | J20: =+IF(J7>0,J19/J7,"n/a") -> 0.083122072 | ... BJ20: =+IF(BJ7>0,BJ19/BJ7,"n/a") -> 0.17156507
A22: Depreciation & Amortization | C22: =CapX!G14 -> 50 | D22: =CapX!H14 -> 50 | E22: =CapX!I14 -> 50 | F22: =CapX!J14 -> 66.666667 | G22: =CapX!K14 -> 66.666667 | H22: =CapX!L14 -> 66.666667 | I22: =CapX!M14 -> 66.666667 | J22: =CapX!N14 -> 83.333333 | ... BJ22: =CapX!BN14 -> 816.66667
A24: Net Income Before Taxes | C24: =+C19-C22 -> -78343.549 | D24: =+D19-D22 -> -35573.299 | E24: =+E19-E22 -> 20723.951 | F24: =+F19-F22 -> 33273.91 | G24: =+G19-G22 -> 78354.91 | H24: =+H19-H22 -> 82592.66 | I24: =+I19-I22 -> 85687.16 | J24: =+J19-J22 -> 73249.868 | ... BJ24: =+BJ19-BJ22 -> 799609.86
A26: Income Taxes | B26: =Assumptions!B12 -> 0.34 | C26: =C24*$B$26 -> -26636.807 | D26: =D24*$B$26 -> -12094.922 | E26: =E24*$B$26 -> 7046.1435 | F26: =F24*$B$26 -> 11313.129 | G26: =G24*$B$26 -> 26640.669 | H26: =H24*$B$26 -> 28081.504 | I26: =I24*$B$26 -> 29133.634 | J26: =J24*$B$26 -> 24904.955 | ... BJ26: =BJ24*$B$26 -> 271867.35
A28: Net Income | C28: =+C24-C26 -> -51706.742 | D28: =+D24-D26 -> -23478.377 | E28: =+E24-E26 -> 13677.808 | F28: =+F24-F26 -> 21960.78 | G28: =+G24-G26 -> 51714.24 | H28: =+H24-H26 -> 54511.155 | I28: =+I24-I26 -> 56553.525 | J28: =+J24-J26 -> 48344.913 | ... BJ28: =+BJ24-BJ26 -> 527742.51
A29: % of Sales | C29: =+IF(C7>0,C28/C7,"n/a") -> -1.2916998 | D29: =+IF(D7>0,D28/D7,"n/a") -> -0.10202667 | E29: =+IF(E7>0,E28/E7,"n/a") -> 0.028475856 | F29: =+IF(F7>0,F28/F7,"n/a") -> 0.035385513 | G29: =+IF(G7>0,G28/G7,"n/a") -> 0.062991249 | H29: =+IF(H7>0,H28/H7,"n/a") -> 0.064788951 | I29: =+IF(I7>0,I28/I7,"n/a") -> 0.065623706 | J29: =+IF(J7>0,J28/J7,"n/a") -> 0.054798226 | ... BJ29: =+IF(BJ7>0,BJ28/BJ7,"n/a") -> 0.11311741
A30: Annual Net Income | N30: =SUM(C28:N28) -> 111837.61 | Z30: =SUM(O28:Z28) -> -369464.45 | AL30: =SUM(AA28:AL28) -> -139757.82 | AX30: =SUM(AM28:AX28) -> 1904518.6 | BJ30: =SUM(AY28:BJ28) -> 4125036.6

Sheet Bal Sheet
A1: UrbanWind
A2: Projected Balance Sheets
A3: Assumption Inputs
A5: Note: Must must manually link below "Equity" to investment $ of Preferred Capital Raise from "Equity" worksheet in month of estimated close; Total raised to date
B7: Assumptions (Turns in Days by Year)
B8: 1 | C8: 2 | D8: 3 | E8: 4 | F8: 5 | G8: 44562 | H8: 44593 | I8: 44621 | J8: 44652 | K8: 44682 | L8: 44713 | M8: 44743 | N8: 44774 | O8: 44805 | P8: 44835 | Q8: 44866 | R8: 44896 | S8: 44927 | T8: 44958 | U8: 44986 | V8: 45017 | W8: 45047 | X8: 45078 | Y8: 45108 | Z8: 45139 | AA8: 45170 | AB8: 45200 | AC8: 45231 | AD8: 45261 | AE8: 45292 | AF8: 45323 | AG8: 45352 | AH8: 45383 | AI8: 45413 | AJ8: 45444 | AK8: 45474 | AL8: 45505 | AM8: 45536 | AN8: 45566 | AO8: 45597 | AP8: 45627 | AQ8: 45658 | AR8: 45689 | AS8: 45717 | AT8: 45748 | AU8: 45778 | AV8: 45809 | AW8: 45839 | AX8: 45870 | AY8: 45901 | AZ8: 45931 | BA8: 45962 | BB8: 45992 | BC8: 46023 | BD8: 46054 | BE8: 46082 | BF8: 46113 | BG8: 46143 | BH8: 46174 | BI8: 46204 | BJ8: 46235 | BK8: 46266 | BL8: 46296 | BM8: 46327 | BN8: 46357
A9: Assets
A10: Cash & Equivalents | G10: =Cashflow!G22 -> 155313.26 | H10: =G10+Cashflow!H22 -> 220308.38 | I10: =H10+Cashflow!I22 -> 242844.19 | J10: =I10+Cashflow!J22 -> 107097.89 | K10: =J10+Cashflow!K22 -> 217530.04 | L10: =K10+Cashflow!L22 -> 224722.37 | M10: =L10+Cashflow!M22 -> 260927.06 | N10: =M10+Cashflow!N22 -> 287909.8 | O10: =N10+Cashflow!O22 -> 286781.42 | ... BN10: =BM10+Cashflow!BN22 -> 11983258
A11: Accounts Receivables | B11: =Assumptions!B10 -> 30 | C11: =B11 -> 30 | D11: =C11 -> 30 | E11: =D11 -> 30 | F11: =E11 -> 30 | G11: =IF(B11/(30)>1,'Sales Forecast'!H37,'Sales Forecast'!H37*(B11/30)) -> 40030 | H11: =(('Sales Forecast'!H37+'Sales Forecast'!I37)/2)*('Bal Sheet'!$B$11/30) -> 135075 | I11: =(('Sales Forecast'!I37+'Sales Forecast'!J37)/2)*('Bal Sheet'!$B$11/30) -> 355225 | J11: =(('Sales Forecast'!J37+'Sales Forecast'!K37)/2)*('Bal Sheet'!$B$11/30) -> 550472.5 | K11: =(('Sales Forecast'!K37+'Sales Forecast'!L37)/2)*('Bal Sheet'!$B$11/30) -> 720795 | L11: =(('Sales Forecast'!L37+'Sales Forecast'!M37)/2)*('Bal Sheet'!$B$11/30) -> 831170 | M11: =(('Sales Forecast'!M37+'Sales Forecast'!N37)/2)*('Bal Sheet'!$B$11/30) -> 851575 | N11: =(('Sales Forecast'!N37+'Sales Forecast'!O37)/2)*('Bal Sheet'!$B$11/30) -> 872010 | O11: =(('Sales Forecast'!O37+'Sales Forecast'!P37)/2)*('Bal Sheet'!$B$11/30) -> 892475 | ... R11: =(('Sales Forecast'!R37+'Sales Forecast'!S37)/2)*('Bal Sheet'!$B$11/30) -> 954050 | S11: =(('Sales Forecast'!S37+'Sales Forecast'!T37)/2)*('Bal Sheet'!$C$11/30) -> 994627.5 | T11: =(('Sales Forecast'!T37+'Sales Forecast'!U37)/2)*('Bal Sheet'!$C$11/30) -> 1040220 | U11: =(('Sales Forecast'!U37+'Sales Forecast'!V37)/2)*('Bal Sheet'!$C$11/30) -> 1070827.5 | V11: =(('Sales Forecast'!V37+'Sales Forecast'!W37)/2)*('Bal Sheet'!$C$11/30) -> 1101450 | W11: =(('Sales Forecast'!W37+'Sales Forecast'!X37)/2)*('Bal Sheet'!$C$11/30) -> 1132087.5 | X11: =(('Sales Forecast'!X37+'Sales Forecast'!Y37)/2)*('Bal Sheet'!$C$11/30) -> 1207747.5 | Y11: =(('Sales Forecast'!Y37+'Sales Forecast'!Z37)/2)*('Bal Sheet'!$C$11/30) -> 1283430 | Z11: =(('Sales Forecast'!Z37+'Sales Forecast'!AA37)/2)*('Bal Sheet'!$C$11/30) -> 1314127.5 | ... AD11: =(('Sales Forecast'!AD37+'Sales Forecast'!AE37)/2)*('Bal Sheet'!$C$11/30) -> 1467075 | AE11: =(('Sales Forecast'!AE37+'Sales Forecast'!AF37)/2)*('Bal Sheet'!$D$11/30) -> 1612892.5 | AF11: =(('Sales Forecast'!AF37+'Sales Forecast'!AG37)/2)*('Bal Sheet'!$D$11/30) -> 1773762.5 | AG11: =(('Sales Forecast'!AG37+'Sales Forecast'!AH37)/2)*('Bal Sheet'!$D$11/30) -> 1849655 | AH11: =(('Sales Forecast'!AH37+'Sales Forecast'!AI37)/2)*('Bal Sheet'!$D$11/30) -> 1865555 | AI11: =(('Sales Forecast'!AI37+'Sales Forecast'!AJ37)/2)*('Bal Sheet'!$D$11/30) -> 1866455 | AJ11: =(('Sales Forecast'!AJ37+'Sales Forecast'!AK37)/2)*('Bal Sheet'!$D$11/30) -> 1867355 | AK11: =(('Sales Forecast'!AK37+'Sales Forecast'!AL37)/2)*('Bal Sheet'!$D$11/30) -> 1868255 | AL11: =(('Sales Forecast'!AL37+'Sales Forecast'!AM37)/2)*('Bal Sheet'!$D$11/30) -> 1869155 | ... AP11: =(('Sales Forecast'!AP37+'Sales Forecast'!AQ37)/2)*('Bal Sheet'!$D$11/30) -> 1872755 | AQ11: =(('Sales Forecast'!AQ37+'Sales Forecast'!AR37)/2)*('Bal Sheet'!$E$11/30) -> 1973692.5 | AR11: =(('Sales Forecast'!AR37+'Sales Forecast'!AS37)/2)*('Bal Sheet'!$E$11/30) -> 2164690 | AS11: =(('Sales Forecast'!AS37+'Sales Forecast'!AT37)/2)*('Bal Sheet'!$E$11/30) -> 2350740 | AT11: =(('Sales Forecast'!AT37+'Sales Forecast'!AU37)/2)*('Bal Sheet'!$E$11/30) -> 2541850 | AU11: =(('Sales Forecast'!AU37+'Sales Forecast'!AV37)/2)*('Bal Sheet'!$E$11/30) -> 2703012.5 | AV11: =(('Sales Forecast'!AV37+'Sales Forecast'!AW37)/2)*('Bal Sheet'!$E$11/30) -> 2769197.5 | AW11: =(('Sales Forecast'!AW37+'Sales Forecast'!AX37)/2)*('Bal Sheet'!$E$11/30) -> 2805397.5 | AX11: =(('Sales Forecast'!AX37+'Sales Forecast'!AY37)/2)*('Bal Sheet'!$E$11/30) -> 2841612.5 | ... BB11: =(('Sales Forecast'!BB37+'Sales Forecast'!BC37)/2)*('Bal Sheet'!$E$11/30) -> 2846472.5 | BC11: =(('Sales Forecast'!BC37+'Sales Forecast'!BD37)/2)*('Bal Sheet'!$F$11/30) -> 2897710 | BD11: =(('Sales Forecast'!BD37+'Sales Forecast'!BE37)/2)*('Bal Sheet'!$F$11/30) -> 3044000 | BE11: =(('Sales Forecast'!BE37+'Sales Forecast'!BF37)/2)*('Bal Sheet'!$F$11/30) -> 3175335 | BF11: =(('Sales Forecast'!BF37+'Sales Forecast'!BG37)/2)*('Bal Sheet'!$F$11/30) -> 3306715 | BG11: =(('Sales Forecast'!BG37+'Sales Forecast'!BH37)/2)*('Bal Sheet'!$F$11/30) -> 3453147.5 | BH11: =(('Sales Forecast'!BH37+'Sales Forecast'!BI37)/2)*('Bal Sheet'!$F$11/30) -> 3584625 | BI11: =(('Sales Forecast'!BI37+'Sales Forecast'!BJ37)/2)*('Bal Sheet'!$F$11/30) -> 3716147.5 | BJ11: =(('Sales Forecast'!BJ37+'Sales Forecast'!BK37)/2)*('Bal Sheet'!$F$11/30) -> 3862722.5 | ... BN11: =(('Sales Forecast'!BN37+'Sales Forecast'!BO37)/2)*('Bal Sheet'!$F$11/30) -> 4584532.5
A12: Inventories | G12: =COGS!G21 -> 28021 | H12: =COGS!H21 -> 161084 | I12: =COGS!I21 -> 336231 | J12: =COGS!J21 -> 434430.5 | K12: =COGS!K21 -> 574682.5 | L12: =COGS!L21 -> 588955.5 | M12: =COGS!M21 -> 603249.5 | N12: =COGS!N21 -> 617564.5 | ... BN12: =COGS!BN21 -> 2939227.2
A13: Fixed Assets, net | G13: =CapX!G22-CapX!G14 -> 2950 | H13: =G13+CapX!H22-CapX!H14 -> 2900 | I13: =H13+CapX!I22-CapX!I14 -> 2850 | J13: =I13+CapX!J22-CapX!J14 -> 3783.3333 | K13: =J13+CapX!K22-CapX!K14 -> 3716.6667 | L13: =K13+CapX!L22-CapX!L14 -> 3650 | M13: =L13+CapX!M22-CapX!M14 -> 3583.3333 | N13: =M13+CapX!N22-CapX!N14 -> 4500 | O13: =N13+CapX!O22-CapX!O14 -> 7366.6667 | ... BN13: =BM13+CapX!BN22-CapX!BN14 -> 13408.333
A14: Total Assets | G14: =SUM(G10:G13) -> 226314.26 | H14: =SUM(H10:H13) -> 519367.38 | I14: =SUM(I10:I13) -> 937150.19 | J14: =SUM(J10:J13) -> 1095784.2 | K14: =SUM(K10:K13) -> 1516724.2 | L14: =SUM(L10:L13) -> 1648497.9 | M14: =SUM(M10:M13) -> 1719334.9 | N14: =SUM(N10:N13) -> 1781984.3 | ... BN14: =SUM(BN10:BN13) -> 19520426
A15: Liabilities & Stockholders' Equity
A16: Liabilities
A17: Accounts Payable | B17: =Assumptions!B11 -> 30 | C17: =B17 -> 30 | D17: =C17 -> 30 | E17: =D17 -> 30 | F17: =E17 -> 30 | G17: =IF(B17/(30)>1,COGS!G14,COGS!G14*($B$17/30)) -> 28021 | H17: =((COGS!G14+COGS!H14)/2)*('Bal Sheet'!$B$17/30) -> 94552.5 | I17: =((COGS!H14+COGS!I14)/2)*('Bal Sheet'!$B$17/30) -> 248657.5 | J17: =((COGS!I14+COGS!J14)/2)*('Bal Sheet'!$B$17/30) -> 385330.75 | K17: =((COGS!J14+COGS!K14)/2)*('Bal Sheet'!$B$17/30) -> 504556.5 | L17: =((COGS!K14+COGS!L14)/2)*('Bal Sheet'!$B$17/30) -> 581819 | M17: =((COGS!L14+COGS!M14)/2)*('Bal Sheet'!$B$17/30) -> 596102.5 | N17: =((COGS!M14+COGS!N14)/2)*('Bal Sheet'!$B$17/30) -> 610407 | O17: =((COGS!N14+COGS!O14)/2)*('Bal Sheet'!$B$17/30) -> 624732.5 | ... R17: =((COGS!Q14+COGS!R14)/2)*('Bal Sheet'!$B$17/30) -> 667835 | S17: =((COGS!R14+COGS!S14)/2)*('Bal Sheet'!$C$17/30) -> 680865.45 | T17: =((COGS!S14+COGS!T14)/2)*('Bal Sheet'!$C$17/30) -> 696947.4 | U17: =((COGS!T14+COGS!U14)/2)*('Bal Sheet'!$C$17/30) -> 717454.43 | V17: =((COGS!U14+COGS!V14)/2)*('Bal Sheet'!$C$17/30) -> 737971.5 | W17: =((COGS!V14+COGS!W14)/2)*('Bal Sheet'!$C$17/30) -> 758498.62 | X17: =((COGS!W14+COGS!X14)/2)*('Bal Sheet'!$C$17/30) -> 809190.82 | Y17: =((COGS!X14+COGS!Y14)/2)*('Bal Sheet'!$C$17/30) -> 859898.1 | Z17: =((COGS!Y14+COGS!Z14)/2)*('Bal Sheet'!$C$17/30) -> 880465.43 | ... AD17: =((COGS!AC14+COGS!AD14)/2)*('Bal Sheet'!$C$17/30) -> 982940.25 | AE17: =((COGS!AD14+COGS!AE14)/2)*('Bal Sheet'!$D$17/30) -> 1057079.8 | AF17: =((COGS!AE14+COGS!AF14)/2)*('Bal Sheet'!$D$17/30) -> 1139642.4 | AG17: =((COGS!AF14+COGS!AG14)/2)*('Bal Sheet'!$D$17/30) -> 1188403.3 | AH17: =((COGS!AG14+COGS!AH14)/2)*('Bal Sheet'!$D$17/30) -> 1198619.1 | AI17: =((COGS!AH14+COGS!AI14)/2)*('Bal Sheet'!$D$17/30) -> 1199197.3 | AJ17: =((COGS!AI14+COGS!AJ14)/2)*('Bal Sheet'!$D$17/30) -> 1199775.6 | AK17: =((COGS!AJ14+COGS!AK14)/2)*('Bal Sheet'!$D$17/30) -> 1200353.8 | AL17: =((COGS!AK14+COGS!AL14)/2)*('Bal Sheet'!$D$17/30) -> 1200932.1 | ... AP17: =((COGS!AO14+COGS!AP14)/2)*('Bal Sheet'!$D$17/30) -> 1203245.1 | AQ17: =((COGS!AP14+COGS!AQ14)/2)*('Bal Sheet'!$E$17/30) -> 1265504.7 | AR17: =((COGS!AQ14+COGS!AR14)/2)*('Bal Sheet'!$E$17/30) -> 1385401.6 | AS17: =((COGS!AR14+COGS!AS14)/2)*('Bal Sheet'!$E$17/30) -> 1504473.6 | AT17: =((COGS!AS14+COGS!AT14)/2)*('Bal Sheet'!$E$17/30) -> 1626784 | AU17: =((COGS!AT14+COGS!AU14)/2)*('Bal Sheet'!$E$17/30) -> 1729928 | AV17: =((COGS!AU14+COGS!AV14)/2)*('Bal Sheet'!$E$17/30) -> 1772286.4 | AW17: =((COGS!AV14+COGS!AW14)/2)*('Bal Sheet'!$E$17/30) -> 1795454.4 | AX17: =((COGS!AW14+COGS!AX14)/2)*('Bal Sheet'!$E$17/30) -> 1818632 | ... BB17: =((COGS!BA14+COGS!BB14)/2)*('Bal Sheet'!$E$17/30) -> 1821742.4 | BC17: =((COGS!BB14+COGS!BC14)/2)*('Bal Sheet'!$F$17/30) -> 1839792.7 | BD17: =((COGS!BC14+COGS!BD14)/2)*('Bal Sheet'!$F$17/30) -> 1917720 | BE17: =((COGS!BD14+COGS!BE14)/2)*('Bal Sheet'!$F$17/30) -> 2000461.1 | BF17: =((COGS!BE14+COGS!BF14)/2)*('Bal Sheet'!$F$17/30) -> 2083230.4 | BG17: =((COGS!BF14+COGS!BG14)/2)*('Bal Sheet'!$F$17/30) -> 2175482.9 | BH17: =((COGS!BG14+COGS!BH14)/2)*('Bal Sheet'!$F$17/30) -> 2258313.8 | BI17: =((COGS!BH14+COGS!BI14)/2)*('Bal Sheet'!$F$17/30) -> 2341172.9 | BJ17: =((COGS!BI14+COGS!BJ14)/2)*('Bal Sheet'!$F$17/30) -> 2433515.2 | ... BN17: =((COGS!BM14+COGS!BN14)/2)*('Bal Sheet'!$F$17/30) -> 2888255.5
A18: Total Liabilities | G18: =SUM(G17) -> 28021 | H18: =SUM(H17) -> 94552.5 | I18: =SUM(I17) -> 248657.5 | J18: =SUM(J17) -> 385330.75 | K18: =SUM(K17) -> 504556.5 | L18: =SUM(L17) -> 581819 | M18: =SUM(M17) -> 596102.5 | N18: =SUM(N17) -> 610407 | ... BN18: =SUM(BN17) -> 2888255.5
A19: Equity
A20: Common Stock | G20: =Equity!C18 -> 0 | H20: =G20 -> 0 | I20: =H20 -> 0 | J20: =I20 -> 0 | K20: =J20 -> 0 | L20: =K20 -> 0 | M20: =L20 -> 0 | N20: =M20 -> 0 | O20: =N20 -> 0 | ... BN20: =BM20 -> 0
A21: Preferred Stock - Series A (Balance = cumulative raised) | G21: 250000 | H21: 500000 | I21: 750000 | J21: 750000 | K21: 1000000 | L21: =K21 -> 1000000 | M21: =L21 -> 1000000 | N21: =M21 -> 1000000 | O21: =N21 -> 1000000 | P21: =O21 -> 1000000 | Q21: =P21 -> 1000000 | R21: =Q21 -> 1000000 | S21: =R21 -> 1000000 | T21: =S21 -> 1000000 | U21: 11000000 | V21: =U21 -> 11000000 | W21: =V21 -> 11000000 | X21: =W21 -> 11000000 | Y21: =X21 -> 11000000 | Z21: =Y21 -> 11000000 | AA21: =Z21 -> 11000000 | AB21: =AA21 -> 11000000 | AC21: =AB21 -> 11000000 | ... BN21: =BM21 -> 11000000
A22: Preferred Stock - Series B (Balance = cumulative raised) | G22: 0 | H22: =G22 -> 0 | I22: =H22 -> 0 | J22: =I22 -> 0 | K22: =J22 -> 0 | L22: =K22 -> 0 | M22: =L22 -> 0 | N22: =M22 -> 0 | O22: =N22 -> 0 | ... BN22: =BM22 -> 0
A23: Retained Earnings (Deficits) - Net Income | G23: ='Monthly Income'!C28 -> -51706.742 | H23: =G23+'Monthly Income'!D28 -> -75185.119 | I23: =H23+'Monthly Income'!E28 -> -61507.311 | J23: =I23+'Monthly Income'!F28 -> -39546.531 | K23: =J23+'Monthly Income'!G28 -> 12167.71 | L23: =K23+'Monthly Income'!H28 -> 66678.865 | M23: =L23+'Monthly Income'!I28 -> 123232.39 | N23: =M23+'Monthly Income'!J28 -> 171577.3 | O23: =N23+'Monthly Income'!K28 -> 193791.08 | ... BN23: =BM23+'Monthly Income'!BJ28 -> 5632170.5
A24: Total Equity | G24: =SUM(G20:G23) -> 198293.26 | H24: =SUM(H20:H23) -> 424814.88 | I24: =SUM(I20:I23) -> 688492.69 | J24: =SUM(J20:J23) -> 710453.47 | K24: =SUM(K20:K23) -> 1012167.7 | L24: =SUM(L20:L23) -> 1066678.9 | M24: =SUM(M20:M23) -> 1123232.4 | N24: =SUM(N20:N23) -> 1171577.3 | ... BN24: =SUM(BN20:BN23) -> 16632171
A25: Total Liabilities & Stockholders' Equity | G25: =G18+G24 -> 226314.26 | H25: =H18+H24 -> 519367.38 | I25: =I18+I24 -> 937150.19 | J25: =J18+J24 -> 1095784.2 | K25: =K18+K24 -> 1516724.2 | L25: =L18+L24 -> 1648497.9 | M25: =M18+M24 -> 1719334.9 | N25: =N18+N24 -> 1781984.3 | ... BN25: =BN18+BN24 -> 19520426
F26: check | G26: =G14-G25 -> 0 | H26: =H14-H25 -> 0 | I26: =I14-I25 -> -1.1641532e-10 | J26: =J14-J25 -> -2.3283064e-10 | K26: =K14-K25 -> 0 | L26: =L14-L25 -> 0 | M26: =M14-M25 -> 0 | N26: =N14-N25 -> 0 | ... BN26: =BN14-BN25 -> -3.7252903e-09

Sheet Cashflow
A1: UrbanWind
A2: Projected Cash Flow Statements
B5: Assumptions (Years)
B6: 1 | C6: 2 | D6: 3 | E6: 4 | F6: 5 | G6: 44562 | H6: 44593 | I6: 44621 | J6: 44652 | K6: 44682 | L6: 44713 | M6: 44743 | N6: 44774 | O6: 44805 | P6: 44835 | Q6: 44866 | R6: 44896 | S6: 44927 | T6: 44958 | U6: 44986 | V6: 45017 | W6: 45047 | X6: 45078 | Y6: 45108 | Z6: 45139 | AA6: 45170 | AB6: 45200 | AC6: 45231 | AD6: 45261 | AE6: 45292 | AF6: 45323 | AG6: 45352 | AH6: 45383 | AI6: 45413 | AJ6: 45444 | AK6: 45474 | AL6: 45505 | AM6: 45536 | AN6: 45566 | AO6: 45597 | AP6: 45627 | AQ6: 45658 | AR6: 45689 | AS6: 45717 | AT6: 45748 | AU6: 45778 | AV6: 45809 | AW6: 45839 | AX6: 45870 | AY6: 45901 | AZ6: 45931 | BA6: 45962 | BB6: 45992 | BC6: 46023 | BD6: 46054 | BE6: 46082 | BF6: 46113 | BG6: 46143 | BH6: 46174 | BI6: 46204 | BJ6: 46235 | BK6: 46266 | BL6: 46296 | BM6: 46327 | BN6: 46357
A7: Operating Activities
A8: Net Income | G8: ='Monthly Income'!C28 -> -51706.742 | H8: ='Monthly Income'!D28 -> -23478.377 | I8: ='Monthly Income'!E28 -> 13677.808 | J8: ='Monthly Income'!F28 -> 21960.78 | K8: ='Monthly Income'!G28 -> 51714.24 | L8: ='Monthly Income'!H28 -> 54511.155 | M8: ='Monthly Income'!I28 -> 56553.525 | N8: ='Monthly Income'!J28 -> 48344.913 | ... BN8: ='Monthly Income'!BJ28 -> 527742.51
A9: Depreciation | G9: ='Monthly Income'!C22 -> 50 | H9: ='Monthly Income'!D22 -> 50 | I9: ='Monthly Income'!E22 -> 50 | J9: ='Monthly Income'!F22 -> 66.666667 | K9: ='Monthly Income'!G22 -> 66.666667 | L9: ='Monthly Income'!H22 -> 66.666667 | M9: ='Monthly Income'!I22 -> 66.666667 | N9: ='Monthly Income'!J22 -> 83.333333 | ... BN9: ='Monthly Income'!BJ22 -> 816.66667
A10: Changes in Assets and Liabilities
A11: Accounts Receivable | G11: =-'Bal Sheet'!G11 -> -40030 | H11: ='Bal Sheet'!G11-'Bal Sheet'!H11 -> -95045 | I11: ='Bal Sheet'!H11-'Bal Sheet'!I11 -> -220150 | J11: ='Bal Sheet'!I11-'Bal Sheet'!J11 -> -195247.5 | K11: ='Bal Sheet'!J11-'Bal Sheet'!K11 -> -170322.5 | L11: ='Bal Sheet'!K11-'Bal Sheet'!L11 -> -110375 | M11: ='Bal Sheet'!L11-'Bal Sheet'!M11 -> -20405 | N11: ='Bal Sheet'!M11-'Bal Sheet'!N11 -> -20435 | O11: ='Bal Sheet'!N11-'Bal Sheet'!O11 -> -20465 | ... BN11: ='Bal Sheet'!BM11-'Bal Sheet'!BN11 -> -221792.5
A12: Inventories | G12: =-'Bal Sheet'!G12 -> -28021 | H12: ='Bal Sheet'!G12-'Bal Sheet'!H12 -> -133063 | I12: ='Bal Sheet'!H12-'Bal Sheet'!I12 -> -175147 | J12: ='Bal Sheet'!I12-'Bal Sheet'!J12 -> -98199.5 | K12: ='Bal Sheet'!J12-'Bal Sheet'!K12 -> -140252 | L12: ='Bal Sheet'!K12-'Bal Sheet'!L12 -> -14273 | M12: ='Bal Sheet'!L12-'Bal Sheet'!M12 -> -14294 | N12: ='Bal Sheet'!M12-'Bal Sheet'!N12 -> -14315 | O12: ='Bal Sheet'!N12-'Bal Sheet'!O12 -> -14336 | ... BN12: ='Bal Sheet'!BM12-'Bal Sheet'!BN12 -> -101943.45
A13: Accounts Payable | G13: =+'Bal Sheet'!G17 -> 28021 | H13: =-'Bal Sheet'!G17+'Bal Sheet'!H17 -> 66531.5 | I13: =-'Bal Sheet'!H17+'Bal Sheet'!I17 -> 154105 | J13: =-'Bal Sheet'!I17+'Bal Sheet'!J17 -> 136673.25 | K13: =-'Bal Sheet'!J17+'Bal Sheet'!K17 -> 119225.75 | L13: =-'Bal Sheet'!K17+'Bal Sheet'!L17 -> 77262.5 | M13: =-'Bal Sheet'!L17+'Bal Sheet'!M17 -> 14283.5 | N13: =-'Bal Sheet'!M17+'Bal Sheet'!N17 -> 14304.5 | O13: =-'Bal Sheet'!N17+'Bal Sheet'!O17 -> 14325.5 | ... BN13: =-'Bal Sheet'!BM17+'Bal Sheet'!BN17 -> 139729.27
A14: Cash from Operating Activities | G14: =SUM(G8:G13) -> -91686.742 | H14: =SUM(H8:H13) -> -185004.88 | I14: =SUM(I8:I13) -> -227464.19 | J14: =SUM(J8:J13) -> -134746.3 | K14: =SUM(K8:K13) -> -139567.84 | L14: =SUM(L8:L13) -> 7192.3221 | M14: =SUM(M8:M13) -> 36204.692 | N14: =SUM(N8:N13) -> 27982.746 | ... BN14: =SUM(BN8:BN13) -> 344552.5
A15: Investing Activities
A16: Purchases - CapX | G16: =-CapX!G22 -> -3000 | H16: =-CapX!H22 -> 0 | I16: =-CapX!I22 -> 0 | J16: =-CapX!J22 -> -1000 | K16: =-CapX!K22 -> 0 | L16: =-CapX!L22 -> 0 | M16: =-CapX!M22 -> 0 | N16: =-CapX!N22 -> -1000 | ... BN16: =-CapX!BN22 -> 0
A17: Cash from Investing Activities | G17: =SUM(G16) -> -3000 | H17: =SUM(H16) -> 0 | I17: =SUM(I16) -> 0 | J17: =SUM(J16) -> -1000 | K17: =SUM(K16) -> 0 | L17: =SUM(L16) -> 0 | M17: =SUM(M16) -> 0 | N17: =SUM(N16) -> -1000 | ... BN17: =SUM(BN16) -> 0
A18: Financing Activities
A19: Equity Raises | G19: 250000 | H19: 250000 | I19: 250000 | K19: 250000 | L19: =IF(SUM('Bal Sheet'!L20:L22)=0,0,SUM('Bal Sheet'!L20:L22)-SUM('Bal Sheet'!K20:K22)) -> 0 | M19: =IF(SUM('Bal Sheet'!M20:M22)=0,0,SUM('Bal Sheet'!M20:M22)-SUM('Bal Sheet'!L20:L22)) -> 0 | N19: 0 | O19: =IF(SUM('Bal Sheet'!O20:O22)=0,0,SUM('Bal Sheet'!O20:O22)-SUM('Bal Sheet'!N20:N22)) -> 0 | P19: =IF(SUM('Bal Sheet'!P20:P22)=0,0,SUM('Bal Sheet'!P20:P22)-SUM('Bal Sheet'!O20:O22)) -> 0 | Q19: =IF(SUM('Bal Sheet'!Q20:Q22)=0,0,SUM('Bal Sheet'!Q20:Q22)-SUM('Bal Sheet'!P20:P22)) -> 0 | R19: =IF(SUM('Bal Sheet'!R20:R22)=0,0,SUM('Bal Sheet'!R20:R22)-SUM('Bal Sheet'!Q20:Q22)) -> 0 | S19: =IF(SUM('Bal Sheet'!S20:S22)=0,0,SUM('Bal Sheet'!S20:S22)-SUM('Bal Sheet'!R20:R22)) -> 0 | T19: =IF(SUM('Bal Sheet'!T20:T22)=0,0,SUM('Bal Sheet'!T20:T22)-SUM('Bal Sheet'!S20:S22)) -> 0 | U19: 10000000 | V19: =IF(SUM('Bal Sheet'!V20:V22)=0,0,SUM('Bal Sheet'!V20:V22)-SUM('Bal Sheet'!U20:U22)) -> 0 | W19: =IF(SUM('Bal Sheet'!W20:W22)=0,0,SUM('Bal Sheet'!W20:W22)-SUM('Bal Sheet'!V20:V22)) -> 0 | X19: 0 | Z19: =IF(SUM('Bal Sheet'!Z20:Z22)=0,0,SUM('Bal Sheet'!Z20:Z22)-SUM('Bal Sheet'!Y20:Y22)) -> 0 | AA19: =IF(SUM('Bal Sheet'!AA20:AA22)=0,0,SUM('Bal Sheet'!AA20:AA22)-SUM('Bal Sheet'!Z20:Z22)) -> 0 | AB19: =IF(SUM('Bal Sheet'!AB20:AB22)=0,0,SUM('Bal Sheet'!AB20:AB22)-SUM('Bal Sheet'!AA20:AA22)) -> 0 | AC19: =IF(SUM('Bal Sheet'!AC20:AC22)=0,0,SUM('Bal Sheet'!AC20:AC22)-SUM('Bal Sheet'!AB20:AB22)) -> 0 | AD19: =IF(SUM('Bal Sheet'!AD20:AD22)=0,0,SUM('Bal Sheet'!AD20:AD22)-SUM('Bal Sheet'!AC20:AC22)) -> 0 | AE19: 0 | AF19: =IF(SUM('Bal Sheet'!AF20:AF22)=0,0,SUM('Bal Sheet'!AF20:AF22)-SUM('Bal Sheet'!AE20:AE22)) -> 0 | AG19: 0 | AH19: =IF(SUM('Bal Sheet'!AH20:AH22)=0,0,SUM('Bal Sheet'!AH20:AH22)-SUM('Bal Sheet'!AG20:AG22)) -> 0 | AI19: =IF(SUM('Bal Sheet'!AI20:AI22)=0,0,SUM('Bal Sheet'!AI20:AI22)-SUM('Bal Sheet'!AH20:AH22)) -> 0 | AJ19: =IF(SUM('Bal Sheet'!AJ20:AJ22)=0,0,SUM('Bal Sheet'!AJ20:AJ22)-SUM('Bal Sheet'!AI20:AI22)) -> 0 | AK19: =IF(SUM('Bal Sheet'!AK20:AK22)=0,0,SUM('Bal Sheet'!AK20:AK22)-SUM('Bal Sheet'!AJ20:AJ22)) -> 0 | AL19: =IF(SUM('Bal Sheet'!AL20:AL22)=0,0,SUM('Bal Sheet'!AL20:AL22)-SUM('Bal Sheet'!AK20:AK22)) -> 0 | AM19: =IF(SUM('Bal Sheet'!AM20:AM22)=0,0,SUM('Bal Sheet'!AM20:AM22)-SUM('Bal Sheet'!AL20:AL22)) -> 0 | AN19: =IF(SUM('Bal Sheet'!AN20:AN22)=0,0,SUM('Bal Sheet'!AN20:AN22)-SUM('Bal Sheet'!AM20:AM22)) -> 0 | AO19: =IF(SUM('Bal Sheet'!AO20:AO22)=0,0,SUM('Bal Sheet'!AO20:AO22)-SUM('Bal Sheet'!AN20:AN22)) -> 0 | ... BN19: =IF(SUM('Bal Sheet'!BN20:BN22)=0,0,SUM('Bal Sheet'!BN20:BN22)-SUM('Bal Sheet'!BM20:BM22)) -> 0
A20: Cash from Financing Activities | G20: =SUM(G19) -> 250000 | H20: =SUM(H19) -> 250000 | I20: =SUM(I19) -> 250000 | J20: =SUM(J19) -> 0 | K20: =SUM(K19) -> 250000 | L20: =SUM(L19) -> 0 | M20: =SUM(M19) -> 0 | N20: =SUM(N19) -> 0 | ... BN20: =SUM(BN19) -> 0
A21: Change in Cash
G22: =G14+G17+G20 -> 155313.26 | H22: =H14+H17+H20 -> 64995.123 | I22: =I14+I17+I20 -> 22535.808 | J22: =J14+J17+J20 -> -135746.3 | K22: =K14+K17+K20 -> 110432.16 | L22: =L14+L17+L20 -> 7192.3221 | M22: =M14+M17+M20 -> 36204.692 | N22: =N14+N17+N20 -> 26982.746 | ... BN22: =BN14+BN17+BN20 -> 344552.5
A23: Cash Balances
A24: Cash, Beginning Balances | G24: ='Bal Sheet'!G10 -> 155313.26 | H24: =G25 -> 155313.26 | I24: =H25 -> 220308.38 | J24: =I25 -> 242844.19 | K24: =J25 -> 107097.89 | L24: =K25 -> 217530.04 | M24: =L25 -> 224722.37 | N24: =M25 -> 260927.06 | O24: =N25 -> 287909.8 | ... BN24: =BM25 -> 11638705
A25: Cash, Ending Balances | G25: =G24 -> 155313.26 | H25: =H24+H22 -> 220308.38 | I25: =I24+I22 -> 242844.19 | J25: =J24+J22 -> 107097.89 | K25: =K24+K22 -> 217530.04 | L25: =L24+L22 -> 224722.37 | M25: =M24+M22 -> 260927.06 | N25: =N24+N22 -> 287909.8 | O25: =O24+O22 -> 286781.42 | ... BN25: =BN24+BN22 -> 11983258
A26: Operating Cash Return (Burn) excludes financing activities
G27: =G14+G17 -> -94686.742 | H27: =H14+H17 -> -185004.88 | I27: =I14+I17 -> -227464.19 | J27: =J14+J17 -> -135746.3 | K27: =K14+K17 -> -139567.84 | L27: =L14+L17 -> 7192.3221 | M27: =M14+M17 -> 36204.692 | N27: =N14+N17 -> 26982.746 | ... BN27: =BN14+BN17 -> 344552.5
A28: Quarterly | I28: =SUM(G22:I22) -> 242844.19 | L28: =SUM(J22:L22) -> -18121.824 | O28: =SUM(M22:O22) -> 62059.052 | R28: =SUM(P22:R22) -> -148893.31 | U28: =SUM(S22:U22) -> 9860475 | X28: =SUM(V22:X22) -> -129874.83 | AA28: =SUM(Y22:AA22) -> -245843.61 | AD28: =SUM(AB22:AD22) -> -417416.12 | AG28: =SUM(AE22:AG22) -> -395961.34 | AJ28: =SUM(AH22:AJ22) -> -43165.459 | AM28: =SUM(AK22:AM22) -> -35524.547 | AP28: =SUM(AN22:AP22) -> -34014.302 | AS28: =SUM(AQ22:AS22) -> -299406.48 | AV28: =SUM(AT22:AV22) -> 154354.08 | AY28: =SUM(AW22:AY22) -> 506715.1 | BB28: =SUM(AZ22:BB22) -> 578838.74 | BE28: =SUM(BC22:BE22) -> 289160.07 | BH28: =SUM(BF22:BH22) -> 458608.23 | BK28: =SUM(BI22:BK22) -> 753211.57 | BN28: =SUM(BL22:BN22) -> 845213.8

Sheet Sales Forecast
A1: UrbanWind
A2: Sales Forecast
A3: Assumption Inputs | H3: =8500000/12 -> 708333.33
C5: Assumptions (Years)
A6: Key Sales Metrics | C6: 2022A | D6: 2023A | E6: 2024 | F6: 2025 | G6: 2026 | H6: 44562 | I6: 44593 | J6: 44621 | K6: 44652 | L6: 44682 | M6: 44713 | N6: 44743 | O6: 44774 | P6: 44805 | Q6: 44835 | R6: 44866 | S6: 44896 | T6: 44927 | U6: 44958 | V6: 44986 | W6: 45017 | X6: 45047 | Y6: 45078 | Z6: 45108 | AA6: 45139 | AB6: 45170 | AC6: 45200 | AD6: 45231 | AE6: 45261 | AF6: 45292 | AG6: 45323 | AH6: 45352 | AI6: 45383 | AJ6: 45413 | AK6: 45444 | AL6: 45474 | AM6: 45505 | AN6: 45536 | AO6: 45566 | AP6: 45597 | AQ6: 45627 | AR6: 45658 | AS6: 45689 | AT6: 45717 | AU6: 45748 | AV6: 45778 | AW6: 45809 | AX6: 45839 | AY6: 45870 | AZ6: 45901 | BA6: 45931 | BB6: 45962 | BC6: 45992 | BD6: 46023 | BE6: 46054 | BF6: 46082 | BG6: 46113 | BH6: 46143 | BI6: 46174 | BJ6: 46204 | BK6: 46235 | BL6: 46266 | BM6: 46296 | BN6: 46327 | BO6: 46357
A7: Qualified Leads | C7: =SUM(I7:S7) -> 0 | D7: =SUM(T7:AE7) -> 880 | E7: =SUM(AF7:AQ7) -> 2880 | F7: =SUM(AR7:BC7) -> 3024 | G7: =SUM(BD7:BO7) -> 3168 | H7: =+Assumptions!$A$30*'People Costs'!H108 -> 0 | I7: =+Assumptions!$A$30*'People Costs'!I108 -> 0 | J7: =+Assumptions!$A$30*('People Costs'!J108+'People Costs'!J111+'People Costs'!J112) -> 0 | K7: =+Assumptions!$A$30*('People Costs'!K108+'People Costs'!K111+'People Costs'!K112) -> 0 | L7: =+Assumptions!$A$30*('People Costs'!L108+'People Costs'!L111+'People Costs'!L112) -> 0 | M7: =+Assumptions!$A$30*('People Costs'!M108+'People Costs'!M111+'People Costs'!M112) -> 0 | N7: =+Assumptions!$A$30*('People Costs'!N108+'People Costs'!N111+'People Costs'!N112) -> 0 | O7: =+Assumptions!$A$30*('People Costs'!O108+'People Costs'!O111+'People Costs'!O112) -> 0 | P7: =+Assumptions!$A$30*('People Costs'!P108+'People Costs'!P111+'People Costs'!P112) -> 0 | Q7: =+Assumptions!$A$30*('People Costs'!Q108+'People Costs'!Q111+'People Costs'!Q112) -> 0 | ... AE7: =+Assumptions!$A$30*('People Costs'!AE108+'People Costs'!AE111+'People Costs'!AE112) -> 240 | AF7: =+Assumptions!$A$31*('People Costs'!AF108+'People Costs'!AF111+'People Costs'!AF112) -> 240 | AG7: =+Assumptions!$A$31*('People Costs'!AG108+'People Costs'!AG111+'People Costs'!AG112) -> 240 | AH7: =+Assumptions!$A$31*('People Costs'!AH108+'People Costs'!AH111+'People Costs'!AH112) -> 240 | AI7: =+Assumptions!$A$31*('People Costs'!AI108+'People Costs'!AI111+'People Costs'!AI112) -> 240 | AJ7: =+Assumptions!$A$31*('People Costs'!AJ108+'People Costs'!AJ111+'People Costs'!AJ112) -> 240 | AK7: =+Assumptions!$A$31*('People Costs'!AK108+'People Costs'!AK111+'People Costs'!AK112) -> 240 | AL7: =+Assumptions!$A$31*('People Costs'!AL108+'People Costs'!AL111+'People Costs'!AL112) -> 240 | AM7: =+Assumptions!$A$31*('People Costs'!AM108+'People Costs'!AM111+'People Costs'!AM112) -> 240 | ... AQ7: =+Assumptions!$A$31*('People Costs'!AQ108+'People Costs'!AQ111+'People Costs'!AQ112) -> 240 | AR7: =+Assumptions!$A$32*('People Costs'!AR108+'People Costs'!AR111+'People Costs'!AR112) -> 252 | AS7: =+Assumptions!$A$32*('People Costs'!AS108+'People Costs'!AS111+'People Costs'!AS112) -> 252 | AT7: =+Assumptions!$A$32*('People Costs'!AT108+'People Costs'!AT111+'People Costs'!AT112) -> 252 | AU7: =+Assumptions!$A$32*('People Costs'!AU108+'People Costs'!AU111+'People Costs'!AU112) -> 252 | AV7: =+Assumptions!$A$32*('People Costs'!AV108+'People Costs'!AV111+'People Costs'!AV112) -> 252 | AW7: =+Assumptions!$A$32*('People Costs'!AW108+'People Costs'!AW111+'People Costs'!AW112) -> 252 | AX7: =+Assumptions!$A$32*('People Costs'!AX108+'People Costs'!AX111+'People Costs'!AX112) -> 252 | AY7: =+Assumptions!$A$32*('People Costs'!AY108+'People Costs'!AY111+'People Costs'!AY112) -> 252 | ... BC7: =+Assumptions!$A$32*('People Costs'!BC108+'People Costs'!BC111+'People Costs'!BC112) -> 252 | BD7: =+Assumptions!$A$33*('People Costs'!BD108+'People Costs'!BD111+'People Costs'!BD112) -> 264 | BE7: =+Assumptions!$A$33*('People Costs'!BE108+'People Costs'!BE111+'People Costs'!BE112) -> 264 | BF7: =+Assumptions!$A$33*('People Costs'!BF108+'People Costs'!BF111+'People Costs'!BF112) -> 264 | BG7: =+Assumptions!$A$33*('People Costs'!BG108+'People Costs'!BG111+'People Costs'!BG112) -> 264 | BH7: =+Assumptions!$A$33*('People Costs'!BH108+'People Costs'!BH111+'People Costs'!BH112) -> 264 | BI7: =+Assumptions!$A$33*('People Costs'!BI108+'People Costs'!BI111+'People Costs'!BI112) -> 264 | BJ7: =+Assumptions!$A$33*('People Costs'!BJ108+'People Costs'!BJ111+'People Costs'!BJ112) -> 264 | BK7: =+Assumptions!$A$33*('People Costs'!BK108+'People Costs'!BK111+'People Costs'!BK112) -> 264 | ... BO7: =+Assumptions!$A$33*('People Costs'!BO108+'People Costs'!BO111+'People Costs'!BO112) -> 264
A8: Residential Breeze | C8: =SUM(I8:S8) -> 152 | D8: =SUM(T8:AE8) -> 288 | E8: =SUM(AF8:AQ8) -> 312 | F8: =SUM(AR8:BC8) -> 369 | G8: =SUM(BD8:BO8) -> 462 | H8: 1 | I8: 2 | J8: 6 | K8: 8 | L8: 10 | M8: 12 | N8: 14 | O8: 16 | P8: 18 | Q8: 20 | R8: 22 | S8: 24 | T8: 24 | U8: 24 | V8: 24 | W8: 24 | X8: 24 | Y8: 24 | Z8: 24 | AA8: 24 | AB8: 24 | AC8: 24 | AD8: 24 | AE8: 24 | AF8: 26 | AG8: =AF8 -> 26 | AH8: =AG8 -> 26 | AI8: =AH8 -> 26 | AJ8: =AI8 -> 26 | AK8: =AJ8 -> 26 | AL8: =AK8 -> 26 | AM8: =AL8 -> 26 | AN8: =AM8 -> 26 | ... AQ8: =AP8 -> 26 | AR8: 28 | AS8: =AR8 -> 28 | AT8: 29 | AU8: 30 | AV8: 31 | AW8: =AV8 -> 31 | AX8: 32 | AY8: 32 | AZ8: 32 | BA8: 32 | BB8: 32 | BC8: =BB8 -> 32 | BD8: 33 | BE8: 34 | BF8: 35 | BG8: 36 | BH8: 37 | BI8: 38 | BJ8: 39 | BK8: 40 | BL8: 41 | BM8: 42 | BN8: 43 | BO8: 44
A9: CommercialGust | C9: =SUM(I9:S9) -> 68 | D9: =SUM(T9:AE9) -> 150 | E9: =SUM(AF9:AQ9) -> 249 | F9: =SUM(AR9:BC9) -> 302 | G9: =SUM(BD9:BO9) -> 368 | H9: 1 | I9: 2 | J9: 4 | K9: 6 | L9: 7 | M9: 7 | N9: 7 | O9: 7 | P9: 7 | Q9: 7 | R9: 7 | S9: 7 | T9: 7 | U9: 8 | V9: 9 | W9: 10 | X9: 11 | Y9: 12 | Z9: 13 | AA9: 14 | AB9: 15 | AC9: 16 | AD9: 17 | AE9: 18 | AF9: 19 | AG9: 20 | AH9: 21 | AI9: =AH9 -> 21 | AJ9: =AI9 -> 21 | AK9: =AJ9 -> 21 | AL9: =AK9 -> 21 | AM9: =AL9 -> 21 | AN9: =AM9 -> 21 | AO9: =AN9 -> 21 | AP9: =AO9 -> 21 | AQ9: =AP9 -> 21 | AR9: 22 | AS9: 23 | AT9: 24 | AU9: 25 | AV9: 26 | AW9: 26 | AX9: =AW9 -> 26 | AY9: =AX9 -> 26 | AZ9: =AY9 -> 26 | BA9: =AZ9 -> 26 | BB9: =BA9 -> 26 | BC9: =BB9 -> 26 | BD9: 27 | BE9: 28 | BF9: =BE9 -> 28 | BG9: 29 | BH9: 30 | BI9: =BH9 -> 30 | BJ9: 31 | BK9: 32 | BL9: =BK9 -> 32 | BM9: 33 | BN9: 34 | BO9: =BN9 -> 34
A10: HybridFlow | C10: =SUM(I10:S10) -> 38 | D10: =SUM(T10:AE10) -> 61 | E10: =SUM(AF10:AQ10) -> 84 | F10: =SUM(AR10:BC10) -> 132 | G10: =SUM(BD10:BO10) -> 222 | H10: 0 | I10: 1 | J10: 2 | K10: 3 | L10: 4 | M10: 4 | N10: 4 | O10: 4 | P10: 4 | Q10: 4 | R10: 4 | S10: 4 | T10: 5 | U10: 5 | V10: 5 | W10: 5 | X10: 5 | Y10: 5 | Z10: 5 | AA10: 5 | AB10: 5 | AC10: 5 | AD10: 5 | AE10: 6 | AF10: 7 | AG10: 7 | AH10: =AG10 -> 7 | AI10: =AH10 -> 7 | AJ10: =AI10 -> 7 | AK10: =AJ10 -> 7 | AL10: =AK10 -> 7 | AM10: =AL10 -> 7 | AN10: =AM10 -> 7 | AO10: =AN10 -> 7 | ... AQ10: =AP10 -> 7 | AR10: 8 | AS10: 9 | AT10: 10 | AU10: 11 | AV10: 11 | AW10: 11 | AX10: 12 | AY10: =AX10 -> 12 | AZ10: =AY10 -> 12 | BA10: =AZ10 -> 12 | BB10: =BA10 -> 12 | BC10: =BB10 -> 12 | BD10: 13 | BE10: 14 | BF10: 15 | BG10: 16 | BH10: 17 | BI10: 18 | BJ10: 19 | BK10: 20 | BL10: 21 | BM10: 22 | BN10: 23 | BO10: 24
A11: SmartWind | C11: =SUM(I11:S11) -> 29 | D11: =SUM(T11:AE11) -> 43 | E11: =SUM(AF11:AQ11) -> 71 | F11: =SUM(AR11:BC11) -> 122 | G11: =SUM(BD11:BO11) -> 172 | H11: 0 | I11: 1 | J11: 2 | K11: 2 | L11: 3 | M11: 3 | N11: 3 | O11: 3 | P11: 3 | Q11: 3 | R11: 3 | S11: 3 | T11: 3 | U11: 3 | V11: 3 | W11: 3 | X11: 3 | Y11: 4 | Z11: 4 | AA11: 4 | AB11: 4 | AC11: 4 | AD11: 4 | AE11: 4 | AF11: 5 | AG11: 6 | AH11: =AG11 -> 6 | AI11: =AH11 -> 6 | AJ11: =AI11 -> 6 | AK11: =AJ11 -> 6 | AL11: =AK11 -> 6 | AM11: =AL11 -> 6 | AN11: =AM11 -> 6 | AO11: =AN11 -> 6 | ... AQ11: =AP11 -> 6 | AR11: 7 | AS11: 8 | AT11: 9 | AU11: 10 | AV11: 11 | AW11: =AV11 -> 11 | AX11: =AW11 -> 11 | AY11: =AX11 -> 11 | AZ11: =AY11 -> 11 | BA11: =AZ11 -> 11 | BB11: =BA11 -> 11 | BC11: =BB11 -> 11 | BD11: =BC11 -> 11 | BE11: 12 | BF11: =BE11 -> 12 | BG11: 13 | BH11: =BG11 -> 13 | BI11: 14 | BJ11: =BI11 -> 14 | BK11: 15 | BL11: 15 | BM11: 16 | BN11: 18 | BO11: 19
A12: Software Services | C12: =+S12 -> 289 | D12: =AE12 -> 831 | E12: =AQ12 -> 1547 | F12: =BC12 -> 2472 | G12: =BO12 -> 3696 | H12: =H8+H9+H10+H11 -> 2 | I12: =I8+I9+I10+I11+H12 -> 8 | J12: =J8+J9+J10+J11+I12 -> 22 | K12: =K8+K9+K10+K11+J12 -> 41 | L12: =L8+L9+L10+L11+K12 -> 65 | M12: =M8+M9+M10+M11+L12 -> 91 | N12: =N8+N9+N10+N11+M12 -> 119 | O12: =O8+O9+O10+O11+N12 -> 149 | P12: =P8+P9+P10+P11+O12 -> 181 | ... BO12: =BO8+BO9+BO10+BO11+BN12 -> 3696
C13: =+S13 -> 0 | D13: =AE13 -> 0 | E13: =AQ13 -> 0 | F13: =BC13 -> 0 | G13: =BO13 -> 0 | H13: 0 | I13: 0 | J13: 0 | K13: 0 | L13: 0 | M13: 0 | N13: 0 | O13: 0 | P13: 0 | Q13: 0 | R13: 0 | S13: 0 | T13: 0 | U13: 0 | V13: 0 | W13: 0 | X13: 0 | Y13: 0 | Z13: 0 | AA13: 0 | AB13: 0 | AC13: 0 | AD13: 0 | AE13: 0 | AF13: 0 | AG13: 0 | AH13: 0 | AI13: 0 | AJ13: 0 | AK13: 0 | AL13: 0 | AM13: 0 | AN13: 0 | AO13: 0 | AP13: 0 | AQ13: 0 | AR13: 0 | AS13: 0 | AT13: 0 | AU13: 0 | AV13: 0 | AW13: 0 | AX13: 0 | AY13: 0 | AZ13: 0 | BA13: 0 | BB13: 0 | BC13: 0 | BD13: 0 | BE13: 0 | BF13: 0 | BG13: 0 | BH13: 0 | BI13: 0 | BJ13: 0 | BK13: 0 | BL13: 0 | BM13: 0 | BN13: 0 | BO13: 0
C14: =SUM(I14:S14) -> 0 | D14: =SUM(T14:AE14) -> 0 | E14: =SUM(AF14:AQ14) -> 0 | F14: =SUM(AR14:BC14) -> 0 | G14: =SUM(BD14:BO14) -> 0 | H14: 0 | I14: 0 | J14: 0 | K14: 0 | L14: 0 | M14: 0 | N14: 0 | O14: 0 | P14: 0 | Q14: 0 | R14: 0 | S14: 0 | T14: 0 | U14: 0 | V14: 0 | W14: 0 | X14: 0 | Y14: 0 | Z14: 0 | AA14: 0 | AB14: 0 | AC14: 0 | AD14: 0 | AE14: 0 | AF14: 0 | AG14: 0 | AH14: 0 | AI14: 0 | AJ14: 0 | AK14: 0 | AL14: 0 | AM14: 0 | AN14: 0 | AO14: 0 | AP14: 0 | AQ14: 0 | AR14: 0 | AS14: 0 | AT14: 0 | AU14: 0 | AV14: 0 | AW14: 0 | AX14: 0 | AY14: 0 | AZ14: 0 | BA14: 0 | BB14: 0 | BC14: 0 | BD14: 0 | BE14: 0 | BF14: 0 | BG14: 0 | BH14: 0 | BI14: 0 | BJ14: 0 | BK14: 0 | BL14: 0 | BM14: 0 | BN14: 0 | BO14: 0
A16: Residential Breeze | C16: =SUM(H16:S16) -> 1530000 | D16: =SUM(T16:AE16) -> 2880000 | E16: =SUM(AF16:AQ16) -> 3120000 | F16: =SUM(AR16:BC16) -> 3690000 | G16: =SUM(BD16:BO16) -> 4620000 | H16: =H8*Assumptions!$A$53 -> 10000 | I16: =I8*Assumptions!$A$53 -> 20000 | J16: =J8*Assumptions!$A$53 -> 60000 | K16: =K8*Assumptions!$A$53 -> 80000 | L16: =L8*Assumptions!$A$53 -> 100000 | M16: =M8*Assumptions!$A$53 -> 120000 | N16: =N8*Assumptions!$A$53 -> 140000 | O16: =O8*Assumptions!$A$53 -> 160000 | ... BO16: =BO8*Assumptions!$A$53 -> 440000
A17: CommercialGust | C17: =SUM(I17:S17) -> 2040000 | D17: =SUM(T17:AE17) -> 4500000 | E17: =SUM(AF17:AQ17) -> 7470000 | F17: =SUM(AR17:BC17) -> 9060000 | G17: =SUM(BD17:BO17) -> 11040000 | H17: =H9*Assumptions!$A$55 -> 30000 | I17: =I9*Assumptions!$A$55 -> 60000 | J17: =J9*Assumptions!$A$55 -> 120000 | K17: =K9*Assumptions!$A$55 -> 180000 | L17: =L9*Assumptions!$A$55 -> 210000 | M17: =M9*Assumptions!$A$55 -> 210000 | N17: =N9*Assumptions!$A$55 -> 210000 | O17: =O9*Assumptions!$A$55 -> 210000 | ... BO17: =BO9*Assumptions!$A$55 -> 1020000
A18: HybridFlow | C18: =SUM(I18:S18) -> 2280000 | D18: =SUM(T18:AE18) -> 3660000 | E18: =SUM(AF18:AQ18) -> 5040000 | F18: =SUM(AR18:BC18) -> 7920000 | G18: =SUM(BD18:BO18) -> 13320000 | H18: =+H10*Assumptions!$A$57 -> 0 | I18: =+I10*Assumptions!$A$57 -> 60000 | J18: =+J10*Assumptions!$A$57 -> 120000 | K18: =+K10*Assumptions!$A$57 -> 180000 | L18: =+L10*Assumptions!$A$57 -> 240000 | M18: =+M10*Assumptions!$A$57 -> 240000 | N18: =+N10*Assumptions!$A$57 -> 240000 | O18: =+O10*Assumptions!$A$57 -> 240000 | ... BO18: =+BO10*Assumptions!$A$57 -> 1440000
A19: SmartWind | C19: =SUM(I19:S19) -> 2610000 | D19: =SUM(T19:AE19) -> 3870000 | E19: =SUM(AF19:AQ19) -> 6390000 | F19: =SUM(AR19:BC19) -> 10980000 | G19: =SUM(BD19:BO19) -> 15480000 | H19: =H11*Assumptions!$A$58 -> 0 | I19: =I11*Assumptions!$A$58 -> 90000 | J19: =J11*Assumptions!$A$58 -> 180000 | K19: =K11*Assumptions!$A$58 -> 180000 | L19: =L11*Assumptions!$A$58 -> 270000 | M19: =M11*Assumptions!$A$58 -> 270000 | N19: =N11*Assumptions!$A$58 -> 270000 | O19: =O11*Assumptions!$A$58 -> 270000 | ... BO19: =BO11*Assumptions!$A$58 -> 1710000
A20: Software Services | C20: =SUM(I20:S20) -> 21465 | D20: =SUM(T20:AE20) -> 102375 | E20: =SUM(AF20:AQ20) -> 219075 | F20: =SUM(AR20:BC20) -> 365730 | G20: =SUM(BD20:BO20) -> 557205 | H20: =H12*Assumptions!$A$59 -> 30 | I20: =I12*Assumptions!$A$59 -> 120 | J20: =J12*Assumptions!$A$59 -> 330 | K20: =K12*Assumptions!$A$59 -> 615 | L20: =L12*Assumptions!$A$59 -> 975 | M20: =M12*Assumptions!$A$59 -> 1365 | N20: =N12*Assumptions!$A$59 -> 1785 | O20: =O12*Assumptions!$A$59 -> 2235 | ... BO20: =BO12*Assumptions!$A$59 -> 55440
A21: Channel Sales
A23: Revenue By Product Class
A24: Residential Products | C24: =SUM(H24:S24) -> 1530000 | D24: =SUM(I24:T24) -> 1760000 | E24: =SUM(J24:U24) -> 1980000 | F24: =SUM(K24:V24) -> 2160000 | G24: =SUM(L24:W24) -> 2320000 | H24: =H16 -> 10000 | I24: =I16 -> 20000 | J24: =J16 -> 60000 | K24: =K16 -> 80000 | L24: =L16 -> 100000 | M24: =M16 -> 120000 | N24: =N16 -> 140000 | O24: =O16 -> 160000 | ... BO24: =BO16 -> 440000
A25: Commercial Products | C25: =(+C17+C18+C19) -> 6930000 | D25: =(+D17+D18+D19) -> 12030000 | E25: =(+E17+E18+E19) -> 18900000 | F25: =(+F17+F18+F19) -> 27960000 | G25: =(+G17+G18+G19) -> 39840000 | H25: =H17+H18+H19 -> 30000 | I25: =I17+I18+I19 -> 210000 | J25: =J17+J18+J19 -> 420000 | K25: =K17+K18+K19 -> 540000 | L25: =L17+L18+L19 -> 720000 | M25: =M17+M18+M19 -> 720000 | N25: =N17+N18+N19 -> 720000 | O25: =O17+O18+O19 -> 720000 | ... BO25: =BO17+BO18+BO19 -> 4170000
A26: Software Services | B26: Channel Sales | C26: =C20 -> 21465 | D26: =D20 -> 102375 | E26: =E20 -> 219075 | F26: =F20 -> 365730 | G26: =G20 -> 557205 | H26: =H20 -> 30 | I26: =I20 -> 120 | J26: =J20 -> 330 | ... BO26: =BO20 -> 55440
A27: Data and Digital Services | B27: Data and Digital Services | C27: =SUM(H27:S27) -> 0 | D27: =SUM(T27:AE27) -> 0 | E27: =SUM(AF27:AQ27) -> 0 | F27: =SUM(AR27:BC27) -> 0 | G27: =SUM(BD27:BO27) -> 0 | H27: =H25*Assumptions!$A$70 -> 0 | I27: =I25*Assumptions!$A$70 -> 0 | J27: =J25*Assumptions!$A$70 -> 0 | K27: =K25*Assumptions!$A$70 -> 0 | L27: =L25*Assumptions!$A$70 -> 0 | M27: =M25*Assumptions!$A$70 -> 0 | N27: =N25*Assumptions!$A$70 -> 0 | O27: =O25*Assumptions!$A$70 -> 0 | ... BO27: =BO25*Assumptions!$A$70 -> 0
A28: Channel Sales | C28: =SUM(H28:S28) -> 0 | D28: =SUM(T28:AE28) -> 0 | E28: =SUM(AF28:AQ28) -> 0 | F28: =SUM(AR28:BC28) -> 0 | G28: =SUM(BD28:BO28) -> 0 | H28: 0 | I28: 0 | J28: 0 | K28: 0 | L28: 0 | M28: 0 | N28: 0 | O28: 0 | P28: 0 | Q28: 0 | R28: 0 | S28: 0 | T28: 0 | U28: 0 | V28: 0 | W28: 0 | X28: 0 | Y28: 0 | Z28: 0 | AA28: 0 | AB28: 0 | AC28: 0 | AD28: 0 | AE28: 0 | AF28: 0 | AG28: 0 | AH28: 0 | AI28: 0 | AJ28: 0 | AK28: 0 | AL28: 0 | AM28: 0 | AN28: 0 | AO28: 0 | AP28: 0 | AQ28: 0 | AR28: 0 | AS28: 0 | AT28: 0 | AU28: 0 | AV28: 0 | AW28: 0 | AX28: 0 | AY28: 0 | AZ28: 0 | BA28: 0 | BB28: 0 | BC28: 0 | BD28: 0 | BE28: 0 | BF28: 0 | BG28: 0 | BH28: 0 | BI28: 0 | BJ28: 0 | BK28: 0 | BL28: 0 | BM28: 0 | BN28: 0 | BO28: 0
A29: Estimated Sales - Totals | C29: =SUM(C16:C21) -> 8481465 | D29: =SUM(D16:D21) -> 15012375 | E29: =SUM(E16:E21) -> 22239075 | F29: =SUM(F16:F21) -> 32015730 | G29: =SUM(G16:G21) -> 45017205 | H29: =SUM(H24:H28) -> 40030 | I29: =SUM(I24:I28) -> 230120 | J29: =SUM(J24:J28) -> 480330 | K29: =SUM(K24:K28) -> 620615 | L29: =SUM(L24:L28) -> 820975 | M29: =SUM(M24:M28) -> 841365 | N29: =SUM(N24:N28) -> 861785 | O29: =SUM(O24:O28) -> 882235 | ... BO29: =SUM(BO24:BO28) -> 4665440
A30: Gross Sales ($)
A31: Equipment Sales | C31: =SUM(H31:S31) -> 8490000 | D31: =SUM(T31:AE31) -> 14910000 | E31: =SUM(AF31:AQ31) -> 22020000 | F31: =SUM(AR31:BC31) -> 31650000 | G31: =SUM(BD31:BO31) -> 44460000 | H31: =H24+H25 -> 40000 | I31: =I24+I25 -> 230000 | J31: =J24+J25 -> 480000 | K31: =K24+K25 -> 620000 | L31: =L24+L25 -> 820000 | M31: =M24+M25 -> 840000 | N31: =N24+N25 -> 860000 | O31: =O24+O25 -> 880000 | ... BO31: =BO24+BO25 -> 4610000
A32: MMR (Services/Platform) | C32: =SUM(H32:S32) -> 21495 | D32: =SUM(T32:AE32) -> 102375 | E32: =SUM(AF32:AQ32) -> 219075 | F32: =SUM(AR32:BC32) -> 365730 | G32: =SUM(BD32:BO32) -> 557205 | H32: =H26 -> 30 | I32: =I26 -> 120 | J32: =J26 -> 330 | K32: =K26 -> 615 | L32: =L26 -> 975 | M32: =M26 -> 1365 | N32: =N26 -> 1785 | O32: =O26 -> 2235 | ... BO32: =BO26 -> 55440
A33: Channel Sales | C33: =C26 -> 21465 | D33: =D26 -> 102375 | E33: =E26 -> 219075 | F33: =F26 -> 365730 | G33: =G26 -> 557205 | H33: =H28 -> 0 | I33: =I28 -> 0 | J33: =J28 -> 0 | K33: =K28 -> 0 | L33: =L28 -> 0 | M33: =M28 -> 0 | N33: =N28 -> 0 | O33: =O28 -> 0 | ... BO33: =BO28 -> 0
H34: =H27 -> 0 | I34: =I27 -> 0 | J34: =J27 -> 0 | K34: =K27 -> 0 | L34: =L27 -> 0 | M34: =M27 -> 0 | N34: =N27 -> 0 | O34: =O27 -> 0 | ... BO34: =BO27 -> 0
A37: Total - Sales | C37: =SUM(C31:C32) -> 8511495 | D37: =SUM(D31:D32) -> 15012375 | E37: =SUM(E31:E32) -> 22239075 | F37: =SUM(F31:F32) -> 32015730 | G37: =SUM(G31:G32) -> 45017205 | H37: =SUM(H31:H36) -> 40030 | I37: =SUM(I31:I36) -> 230120 | J37: =SUM(J31:J36) -> 480330 | K37: =SUM(K31:K36) -> 620615 | L37: =SUM(L31:L36) -> 820975 | M37: =SUM(M31:M36) -> 841365 | N37: =SUM(N31:N36) -> 861785 | O37: =SUM(O31:O36) -> 882235 | ... BO37: =SUM(BO31:BO36) -> 4665440
A39: Sales Assumptions | Q39: Revenue | R39: Year 1 | S39: =SUM(H37:S37) -> 8511495 | AC39: Revenue | AD39: Year 2 | AE39: =SUM(T37:AE37) -> 15012375 | AO39: Revenue | AP39: Year 3 | AQ39: =SUM(AF37:AQ37) -> 22239075 | BA39: Revenue | BB39: Year 4 | BC39: =SUM(AR37:BC37) -> 32015730 | BM39: Revenue | BN39: Year 5 | BO39: =SUM(BD37:BO37) -> 45017205
A40: Monthy Sales Increase
A41: =#REF! -> #REF! | C41: 0.05 | D41: 0.04 | E41: 0.03 | F41: 0.02 | G41: 0.01
A42: =A24 -> Residential Products | C42: 0.05 | D42: 0.04 | E42: 0.03 | F42: 0.02 | G42: 0.01
A43: =#REF! -> #REF! | C43: 0.05 | D43: 0.04 | E43: 0.03 | F43: 0.02 | G43: 0.01
A44: =#REF! -> #REF! | C44: 0.05 | D44: 0.04 | E44: 0.03 | F44: 0.02 | G44: 0.01
A45: =#REF! -> #REF! | C45: 0.05 | D45: 0.04 | E45: 0.03 | F45: 0.02 | G45: 0.01
A47: Monthly Cost Per Acquistion Check | H47: =+OpEx!G27/H7 -> #DIV/0! | I47: =+OpEx!H27/I7 -> #DIV/0! | J47: =+OpEx!I27/J7 -> #DIV/0! | K47: =+OpEx!J27/K7 -> #DIV/0! | L47: =+OpEx!K27/L7 -> #DIV/0! | M47: =+OpEx!L27/M7 -> #DIV/0! | N47: =+OpEx!M27/N7 -> #DIV/0! | O47: =+OpEx!N27/O7 -> #DIV/0! | ... BO47: =+OpEx!BN27/BO7 -> 1082.1718
A64: % Units Sold via Channel vs Direct
A65: =#REF! -> #REF! | C65: 0.25 | D65: =C65 -> 0.25 | E65: 0.3 | F65: 0.5 | G65: 0.6
A66: =A24 -> Residential Products | C66: 0.3 | D66: =C66 -> 0.3 | E66: =D66 -> 0.3 | F66: 0.5 | G66: 0.6
A67: =#REF! -> #REF! | C67: 0.6 | D67: =C67 -> 0.6 | E67: =D67 -> 0.6 | F67: =E67 -> 0.6 | G67: =F67 -> 0.6
A68: =#REF! -> #REF! | C68: 0 | D68: =C68 -> 0 | E68: =D68 -> 0 | F68: =E68 -> 0 | G68: =F68 -> 0
A69: =#REF! -> #REF! | C69: 0 | D69: =C69 -> 0 | E69: =D69 -> 0 | F69: =E69 -> 0 | G69: =F69 -> 0

Sheet Assumptions
A1: Variable: | B1: Rate
A3: OpEx Assuptions | D3: Research
A4: Monthly Travel Expense Per FTE | B4: 1000 | D4: Inputs
A5: Meals/Ent Per Emp. | B5: 100 | D5: Key Inputs
A6: Monthly Office Cost Per Employee | B6: 75
A7: Phone Allowance per FTE
A9: Balance Sheet Assumptions
A10: AP Average Days | B10: 30
A11: AR Average Days | B11: 30
A12: Income Tax Rate | B12: 0.34
A15: Marketig Assumptions
A16: Marketing as a % of Sales | B16: 0.1
A17: Digital Ads as a % of Marketing | B17: 0.5
A18: Planning / Admin as a % of Marketing | B18: 0.2
A19: Planning / Admin as a % of Marketing after year 3 | B19: 0.1
A20: Conferences / Trade Shows as % of Marketing | B20: 0.3
A22: COGs Assumptions
A23: COGs as a % of Sales [ADJUST PER MODEL] year 1 | B23: 0.7
A24: COGs as a % of Sales [ADJUST PER MODEL] year 2 | B24: 0.67
A25: COGs as a % of Sales [ADJUST PER MODEL] year 3 | B25: 0.6425
A26: COGs as a % of Sales [ADJUST PER MODEL] year 4 | B26: 0.64
A27: COGs as a % of Sales [ADJUST PER MODEL] year 5 | B27: 0.63
A29: Sales Assumptions
A30: 80 | B30: Mo. leads per Sales Rep. Year 1
A31: 80 | B31: Mo. leads per Sales Rep. Year 2
A32: 84 | B32: Mo. leads per Sales Rep. Year 3
A33: 88 | B33: Mo. leads per Sales Rep. Year 4
A34: 90 | B34: Mo. leads per Sales Rep. Year 5
A35: 0 | B35: New Sales Reps Per Mo. Year 1
A36: 0 | B36: New Sales Reps Per Mo. Year 2
A37: 0 | B37: New Sales Reps Per Mo. Year 3
A38: 0 | B38: New Sales Reps Per Mo. Year 4
A39: 0 | B39: New Sales Reps Per Mo. Year 5
A40: 0 | B40: Analysts per New Account Year 1
A41: 0 | B41: Analysts per Account Year 2
... A59: 15 | B59: Software Services (Monthly)
A60: =+A47/12 -> 20000 | B60: Monlthy Project Fee (three months)
A61: =+A53/12 -> 833.33333 | B61: Monthly Level 1
A62: =+A55/12 -> 2500 | B62: Monthly Level 2
A63: =+A57/12 -> 5000 | B63: Monthly Level 3
A64: 0.01 | B64: Monthly Attrition Rate (after year 1)
A65: 0 | B65: Channel Sales as a % of MRR year 1
A66: 0 | B66: Channel Sales as a % of MRR year 2
A67: 0 | B67: Channel Sales as a % of MRR year 3
A68: 0 | B68: Channel Sales as a % of MRR year 4
A69: 0 | B69: Channel Sales as a % of MRR year 5
A70: 0 | B70: Data and Digital Services as a % of MRR Year 1
A71: 0 | B71: Data and Digital Services as a % of MRR Year 2
A72: 0 | B72: Data and Digital Services as a % of MRR Year 3
A73: 0 | B73: Data and Digital Services as a % of MRR Year 4
A74: 0 | B74: Data and Digital Services as a % of MRR Year 5
A76: People Cost Assumptions
A77: Monthly Healthcare Cost Per FTE | B77: 700
A78: Wage Inflation | B78: 0.05
A79: Federal 941 (SS/MC) | B79: 0.0765
A80: FUTA | B80: 0.008
A81: State UI | B81: 0.032
A82: State Work Comp | B82: 0.025
A85: CapX Assumptions
A86: Data Center/Production Equipment (deprecitation years) | B86: 5
A87: Employee Computers (deprecitation years) | B87: 5
A88: Internal IT Equipment (deprecitation years) | B88: 5
A89: Office Equipment (deprecitation years) | B89: 5
A90: Furniture & Fixtures (deprecitation years) | B90: 7
A91: Tenant Improvements (Lease Term) | B91: 5
A92: Hardware Costs per FTE | B92: 750
A93: Software Costs Per FTE | B93: 250
A97: Notes:
A98: Prof services equal 60k / mo per account until Year 3

Sheet People Costs
A1: UrbanWind
A2: People Costs
A3: Assumption Inputs
A4: Exeptions
C7: Assumptions (Years) | AF7: Year 3 | AR7: Year 4 | BD7: Year 5
C8: 2022 | D8: 2023 | E8: 2024 | F8: 2025 | G8: 2026 | H8: 44562 | I8: 44593 | J8: 44621 | K8: 44652 | L8: 44682 | M8: 44713 | N8: 44743 | O8: 44774 | P8: 44805 | Q8: 44835 | R8: 44866 | S8: 44896 | T8: 44927 | U8: 44958 | V8: 44986 | W8: 45017 | X8: 45047 | Y8: 45078 | Z8: 45108 | AA8: 45139 | AB8: 45170 | AC8: 45200 | AD8: 45231 | AE8: 45261 | AF8: 45292 | AG8: 45323 | AH8: 45352 | AI8: 45383 | AJ8: 45413 | AK8: 45444 | AL8: 45474 | AM8: 45505 | AN8: 45536 | AO8: 45566 | AP8: 45597 | AQ8: 45627 | AR8: 45658 | AS8: 45689 | AT8: 45717 | AU8: 45748 | AV8: 45778 | AW8: 45809 | AX8: 45839 | AY8: 45870 | AZ8: 45901 | BA8: 45931 | BB8: 45962 | BC8: 45992 | BD8: 46023 | BE8: 46054 | BF8: 46082 | BG8: 46113 | BH8: 46143 | BI8: 46174 | BJ8: 46204 | BK8: 46235 | BL8: 46266 | BM8: 46296 | BN8: 46327 | BO8: 46357
A9: Total Salaries ($)
A10: General and Administration | H10: =H38 -> 58333.333 | I10: =I38 -> 58333.333 | J10: =J38 -> 58333.333 | K10: =K38 -> 58333.333 | L10: =L38 -> 58333.333 | M10: =M38 -> 58333.333 | N10: =N38 -> 58333.333 | O10: =O38 -> 58333.333 | ... BO10: =BO38 -> 187500
A11: Sales and Marketing | H11: =H52 -> 0 | I11: =I52 -> 0 | J11: =J52 -> 0 | K11: =K52 -> 0 | L11: =L52 -> 0 | M11: =M52 -> 0 | N11: =N52 -> 0 | O11: =O52 -> 0 | ... BO11: =BO52 -> 77916.667
A12: Product Engineering | H12: =H82 -> 0 | I12: =I82 -> 0 | J12: =J82 -> 0 | K12: =K82 -> 15000 | L12: =L82 -> 15000 | M12: =M82 -> 15000 | N12: =N82 -> 15000 | O12: =O82 -> 29583.333 | ... BO12: =BO82 -> 184166.67
A13: Total Salaries | H13: =SUM(H10:H12) -> 58333.333 | I13: =SUM(I10:I12) -> 58333.333 | J13: =SUM(J10:J12) -> 58333.333 | K13: =SUM(K10:K12) -> 73333.333 | L13: =SUM(L10:L12) -> 73333.333 | M13: =SUM(M10:M12) -> 73333.333 | N13: =SUM(N10:N12) -> 73333.333 | O13: =SUM(O10:O12) -> 87916.667 | ... BO13: =SUM(BO10:BO12) -> 449583.33
A14: Employee Related Costs ($)
A15: Payroll Taxes (see rate proof below) | C15: =C157 -> 0.1415 | D15: =D157 -> 0.1415 | E15: =E157 -> 0.1415 | F15: =F157 -> 0.1415 | G15: =G157 -> 0.1415 | H15: =H13*$C$15 -> 8254.1667 | I15: =I13*$C$15 -> 8254.1667 | J15: =J13*$C$15 -> 8254.1667 | K15: =K13*$C$15 -> 10376.667 | L15: =L13*$C$15 -> 10376.667 | M15: =M13*$C$15 -> 10376.667 | N15: =N13*$C$15 -> 10376.667 | O15: =O13*$C$15 -> 12440.208 | ... S15: =S13*$C$15 -> 27592.5 | T15: =T13*$D$15 -> 28535.833 | U15: =U13*$D$15 -> 29479.167 | V15: =V13*$D$15 -> 29479.167 | W15: =W13*$D$15 -> 29479.167 | X15: =X13*$D$15 -> 29479.167 | Y15: =Y13*$D$15 -> 29479.167 | Z15: =Z13*$D$15 -> 29479.167 | AA15: =AA13*$D$15 -> 46577.083 | ... AE15: =AE13*$D$15 -> 51116.875 | AF15: =AF13*$E$15 -> 52178.125 | AG15: =AG13*$E$15 -> 52178.125 | AH15: =AH13*$E$15 -> 53180.417 | AI15: =AI13*$E$15 -> 54182.708 | AJ15: =AJ13*$E$15 -> 54182.708 | AK15: =AK13*$E$15 -> 54182.708 | AL15: =AL13*$E$15 -> 54182.708 | AM15: =AM13*$E$15 -> 54182.708 | ... AQ15: =AQ13*$E$15 -> 54182.708 | AR15: =AR13*$F$15 -> 54182.708 | AS15: =AS13*$F$15 -> 54182.708 | AT15: =AT13*$F$15 -> 54182.708 | AU15: =AU13*$F$15 -> 54182.708 | AV15: =AV13*$F$15 -> 54182.708 | AW15: =AW13*$F$15 -> 54182.708 | AX15: =AX13*$F$15 -> 54182.708 | AY15: =AY13*$F$15 -> 54182.708 | ... BC15: =BC13*$F$15 -> 54182.708 | BD15: =BD13*$G$15 -> 63616.042 | BE15: =BE13*$G$15 -> 63616.042 | BF15: =BF13*$G$15 -> 63616.042 | BG15: =BG13*$G$15 -> 63616.042 | BH15: =BH13*$G$15 -> 63616.042 | BI15: =BI13*$G$15 -> 63616.042 | BJ15: =BJ13*$G$15 -> 63616.042 | BK15: =BK13*$G$15 -> 63616.042 | ... BO15: =BO13*$G$15 -> 63616.042
A16: Health Benefits (per FTE) | C16: 700 | D16: 700 | E16: =D16 -> 700 | F16: =E16 -> 700 | G16: =F16 -> 700 | H16: =H20*$C$16 -> 2100 | I16: =I20*$C$16 -> 2100 | J16: =J20*$C$16 -> 2100 | K16: =K20*$C$16 -> 2800 | L16: =L20*$C$16 -> 2800 | M16: =M20*$C$16 -> 2800 | N16: =N20*$C$16 -> 2800 | O16: =O20*$C$16 -> 3500 | ... S16: =S20*$C$16 -> 9800 | T16: =T20*$D$16 -> 10150 | U16: =U20*$D$16 -> 10500 | V16: =V20*$D$16 -> 10500 | W16: =W20*$D$16 -> 10500 | X16: =X20*$D$16 -> 10500 | Y16: =Y20*$D$16 -> 10500 | Z16: =Z20*$D$16 -> 10500 | AA16: =AA20*$D$16 -> 20300 | ... AE16: =AE20*$D$16 -> 32200 | AF16: =AF20*$E$16 -> 32900 | AG16: =AG20*$E$16 -> 31500 | AH16: =AH20*$E$16 -> 32900 | AI16: =AI20*$E$16 -> 33600 | AJ16: =AJ20*$E$16 -> 34300 | AK16: =AK20*$E$16 -> 34300 | AL16: =AL20*$E$16 -> 34300 | AM16: =AM20*$E$16 -> 34300 | ... AQ16: =AQ20*$E$16 -> 34300 | AR16: =AR20*$F$16 -> 34300 | AS16: =AS20*$F$16 -> 34300 | AT16: =AT20*$F$16 -> 34300 | AU16: =AU20*$F$16 -> 34300 | AV16: =AV20*$F$16 -> 34300 | AW16: =AW20*$F$16 -> 34300 | AX16: =AX20*$F$16 -> 34300 | AY16: =AY20*$F$16 -> 34300 | ... BC16: =BC20*$F$16 -> 34300 | BD16: =BD20*$G$16 -> 34300 | BE16: =BE20*$G$16 -> 34300 | BF16: =BF20*$G$16 -> 34300 | BG16: =BG20*$G$16 -> 34300 | BH16: =BH20*$G$16 -> 34300 | BI16: =BI20*$G$16 -> 34300 | BJ16: =BJ20*$G$16 -> 34300 | BK16: =BK20*$G$16 -> 34300 | ... BO16: =BO20*$G$16 -> 34300
A17: Total Employee Related Costs | H17: =SUM(H15:H16) -> 10354.167 | I17: =SUM(I15:I16) -> 10354.167 | J17: =SUM(J15:J16) -> 10354.167 | K17: =SUM(K15:K16) -> 13176.667 | L17: =SUM(L15:L16) -> 13176.667 | M17: =SUM(M15:M16) -> 13176.667 | N17: =SUM(N15:N16) -> 13176.667 | O17: =SUM(O15:O16) -> 15940.208 | ... BO17: =SUM(BO15:BO16) -> 97916.042
A18: Total Headcounts
A19: New FTEs | H19: =H23+H24+H41+H55 -> 3 | I19: =I23+I24+I41+I55 -> 0 | J19: =J23+J24+J41+J55 -> 0 | K19: =K23+K24+K41+K55 -> 1 | L19: =L23+L24+L41+L55 -> 0 | M19: =M23+M24+M41+M55 -> 0 | N19: =N23+N24+N41+N55 -> 0 | O19: =O23+O24+O41+O55 -> 1 | ... BO19: =BO23+BO24+BO41+BO55 -> 0
A20: Total FTEs | H20: =H19 -> 3 | I20: =I19+H20 -> 3 | J20: =J19+I20 -> 3 | K20: =K19+J20 -> 4 | L20: =L19+K20 -> 4 | M20: =M19+L20 -> 4 | N20: =N19+M20 -> 4 | O20: =O19+N20 -> 5 | P20: =P19+O20 -> 8 | ... BO20: =BO19+BN20 -> 49
A21: General and Administration
A22: HEADCOUNT
A23: New Specific FTEs - G&A | H23: =H87 -> 3 | I23: =+I25-H25 -> 0 | J23: =+J25-I25 -> 0 | K23: =+K25-J25 -> 0 | L23: =+L25-K25 -> 0 | M23: =+M25-L25 -> 0 | N23: =+N25-M25 -> 0 | O23: =+O25-N25 -> 0 | P23: =+P25-O25 -> 0 | ... BO23: =+BO25-BN25 -> 0
A24: New Generic FTEs - G&A | H24: =H88 -> 0 | I24: 0 | J24: 0 | K24: 0 | L24: 0 | M24: 0 | N24: 0 | O24: 0 | P24: 0 | Q24: 0 | R24: 0 | S24: 0 | T24: 0 | U24: 0 | V24: 0 | W24: 0 | X24: 0 | Y24: 0 | Z24: 0 | AA24: 0 | AB24: 0 | AC24: 0 | AD24: 0 | AE24: 0 | AF24: 0 | AG24: 0 | AH24: 0 | AI24: 0 | AJ24: 0 | AK24: 0 | AL24: 0 | AM24: 0 | AN24: 0 | AO24: 0 | AP24: 0 | AQ24: 0 | AR24: 0 | AS24: 0 | AT24: 0 | AU24: 0 | AV24: 0 | AW24: 0 | AX24: 0 | AY24: 0 | AZ24: 0 | BA24: 0 | BB24: 0 | BC24: 0 | BD24: 0 | BE24: 0 | BF24: 0 | BG24: 0 | BH24: 0 | BI24: 0 | BJ24: 0 | BK24: 0 | BL24: 0 | BM24: 0 | BN24: 0 | BO24: 0
A25: Total FTEs, Contract - G&A | B25: inflation | H25: =H102 -> 3 | I25: =I102 -> 3 | J25: =J102 -> 3 | K25: =K102 -> 3 | L25: =L102 -> 3 | M25: =M102 -> 3 | N25: =N102 -> 3 | O25: =O102 -> 3 | ... BO25: =BO102 -> 12
A26: Elena Rodriguez, CEO | B26: 0 | C26: 250000 | D26: =+C26*(1+$B$26) -> 250000 | E26: =+D26*(1+$B$26) -> 250000 | F26: =+E26*(1+$B$26) -> 250000 | G26: =+F26*(1+$B$26) -> 250000 | H26: =(+$C$26/12)*H90 -> 20833.333 | I26: =(+$C$26/12)*I90 -> 20833.333 | J26: =(+$C$26/12)*J90 -> 20833.333 | K26: =(+$C$26/12)*K90 -> 20833.333 | L26: =(+$C$26/12)*L90 -> 20833.333 | M26: =(+$C$26/12)*M90 -> 20833.333 | N26: =(+$C$26/12)*N90 -> 20833.333 | O26: =(+$C$26/12)*O90 -> 20833.333 | ... S26: =(+$C$26/12)*S90 -> 20833.333 | T26: =(+$D$26/12)*T90 -> 20833.333 | U26: =(+$D$26/12)*U90 -> 20833.333 | V26: =(+$D$26/12)*V90 -> 20833.333 | W26: =(+$D$26/12)*W90 -> 20833.333 | X26: =(+$D$26/12)*X90 -> 20833.333 | Y26: =(+$D$26/12)*Y90 -> 20833.333 | Z26: =(+$D$26/12)*Z90 -> 20833.333 | AA26: =(+$D$26/12)*AA90 -> 20833.333 | ... AE26: =(+$D$26/12)*AE90 -> 20833.333 | AF26: =(+$E$26/12)*AF90 -> 20833.333 | AG26: =(+$E$26/12)*AG90 -> 20833.333 | AH26: =(+$E$26/12)*AH90 -> 20833.333 | AI26: =(+$E$26/12)*AI90 -> 20833.333 | AJ26: =(+$E$26/12)*AJ90 -> 20833.333 | AK26: =(+$E$26/12)*AK90 -> 20833.333 | AL26: =(+$E$26/12)*AL90 -> 20833.333 | AM26: =(+$E$26/12)*AM90 -> 20833.333 | ... AQ26: =(+$E$26/12)*AQ90 -> 20833.333 | AR26: =(+$F$26/12)*AR90 -> 20833.333 | AS26: =(+$F$26/12)*AS90 -> 20833.333 | AT26: =(+$F$26/12)*AT90 -> 20833.333 | AU26: =(+$F$26/12)*AU90 -> 20833.333 | AV26: =(+$F$26/12)*AV90 -> 20833.333 | AW26: =(+$F$26/12)*AW90 -> 20833.333 | AX26: =(+$F$26/12)*AX90 -> 20833.333 | AY26: =(+$F$26/12)*AY90 -> 20833.333 | ... BC26: =(+$F$26/12)*BC90 -> 20833.333 | BD26: =(+$G$26/12)*BD90 -> 20833.333 | BE26: =(+$G$26/12)*BE90 -> 20833.333 | BF26: =(+$G$26/12)*BF90 -> 20833.333 | BG26: =(+$G$26/12)*BG90 -> 20833.333 | BH26: =(+$G$26/12)*BH90 -> 20833.333 | BI26: =(+$G$26/12)*BI90 -> 20833.333 | BJ26: =(+$G$26/12)*BJ90 -> 20833.333 | BK26: =(+$G$26/12)*BK90 -> 20833.333 | ... BO26: =(+$G$26/12)*BO90 -> 20833.333
A27: Dr. Rachel Chen, CTO | B27: 0 | C27: 225000 | D27: =+C27*(1+$B$26) -> 225000 | E27: =+D27*(1+$B$26) -> 225000 | F27: =+E27*(1+$B$26) -> 225000 | G27: =+F27*(1+$B$26) -> 225000 | H27: =(+$C$27/12)*H91 -> 18750 | I27: =(+$C$27/12)*I91 -> 18750 | J27: =(+$C$27/12)*J91 -> 18750 | K27: =(+$C$27/12)*K91 -> 18750 | L27: =(+$C$27/12)*L91 -> 18750 | M27: =(+$C$27/12)*M91 -> 18750 | N27: =(+$C$27/12)*N91 -> 18750 | O27: =(+$C$27/12)*O91 -> 18750 | ... S27: =(+$C$27/12)*S91 -> 18750 | T27: =(+$D$27/12)*T91 -> 18750 | U27: =(+$D$27/12)*U91 -> 18750 | V27: =(+$D$27/12)*V91 -> 18750 | W27: =(+$D$27/12)*W91 -> 18750 | X27: =(+$D$27/12)*X91 -> 18750 | Y27: =(+$D$27/12)*Y91 -> 18750 | Z27: =(+$D$27/12)*Z91 -> 18750 | AA27: =(+$D$27/12)*AA91 -> 18750 | ... AE27: =(+$D$27/12)*AE91 -> 18750 | AF27: =(+$E$27/12)*AF91 -> 18750 | AG27: =(+$E$27/12)*AG91 -> 18750 | AH27: =(+$E$27/12)*AH91 -> 18750 | AI27: =(+$E$27/12)*AI91 -> 18750 | AJ27: =(+$E$27/12)*AJ91 -> 18750 | AK27: =(+$E$27/12)*AK91 -> 18750 | AL27: =(+$E$27/12)*AL91 -> 18750 | AM27: =(+$E$27/12)*AM91 -> 18750 | ... AQ27: =(+$E$27/12)*AQ91 -> 18750 | AR27: =(+$F$27/12)*AR91 -> 18750 | AS27: =(+$F$27/12)*AS91 -> 18750 | AT27: =(+$F$27/12)*AT91 -> 18750 | AU27: =(+$F$27/12)*AU91 -> 18750 | AV27: =(+$F$27/12)*AV91 -> 18750 | AW27: =(+$F$27/12)*AW91 -> 18750 | AX27: =(+$F$27/12)*AX91 -> 18750 | AY27: =(+$F$27/12)*AY91 -> 18750 | ... BC27: =(+$F$27/12)*BC91 -> 18750 | BD27: =(+$G$26/12)*BD91 -> 20833.333 | BE27: =(+$G$26/12)*BE91 -> 20833.333 | BF27: =(+$G$26/12)*BF91 -> 20833.333 | BG27: =(+$G$26/12)*BG91 -> 20833.333 | BH27: =(+$G$26/12)*BH91 -> 20833.333 | BI27: =(+$G$26/12)*BI91 -> 20833.333 | BJ27: =(+$G$26/12)*BJ91 -> 20833.333 | BK27: =(+$G$26/12)*BK91 -> 20833.333 | ... BO27: =(+$G$26/12)*BO91 -> 20833.333
A28: Marcus Blackwood, CFO | B28: 0 | C28: 225000 | D28: =+C28*(1+$B$26) -> 225000 | E28: =+D28*(1+$B$26) -> 225000 | F28: =+E28*(1+$B$26) -> 225000 | G28: =+F28*(1+$B$26) -> 225000 | H28: =(+$C$28/12)*H92 -> 18750 | I28: =(+$C$28/12)*I92 -> 18750 | J28: =(+$C$28/12)*J92 -> 18750 | K28: =(+$C$28/12)*K92 -> 18750 | L28: =(+$C$28/12)*L92 -> 18750 | M28: =(+$C$28/12)*M92 -> 18750 | N28: =(+$C$28/12)*N92 -> 18750 | O28: =(+$C$28/12)*O92 -> 18750 | ... S28: =(+$C$28/12)*S92 -> 18750 | T28: =(+$D$28/12)*T92 -> 18750 | U28: =(+$D$28/12)*U92 -> 18750 | V28: =(+$D$28/12)*V92 -> 18750 | W28: =(+$D$28/12)*W92 -> 18750 | X28: =(+$D$28/12)*X92 -> 18750 | Y28: =(+$D$28/12)*Y92 -> 18750 | Z28: =(+$D$28/12)*Z92 -> 18750 | AA28: =(+$D$28/12)*AA92 -> 18750 | ... AE28: =(+$D$28/12)*AE92 -> 18750 | AF28: =(+$E$28/12)*AF92 -> 18750 | AG28: =(+$E$28/12)*AG92 -> 18750 | AH28: =(+$E$28/12)*AH92 -> 18750 | AI28: =(+$E$28/12)*AI92 -> 18750 | AJ28: =(+$E$28/12)*AJ92 -> 18750 | AK28: =(+$E$28/12)*AK92 -> 18750 | AL28: =(+$E$28/12)*AL92 -> 18750 | AM28: =(+$E$28/12)*AM92 -> 18750 | ... AQ28: =(+$E$28/12)*AQ92 -> 18750 | AR28: =(+$F$28/12)*AR92 -> 18750 | AS28: =(+$F$28/12)*AS92 -> 18750 | AT28: =(+$F$28/12)*AT92 -> 18750 | AU28: =(+$F$28/12)*AU92 -> 18750 | AV28: =(+$F$28/12)*AV92 -> 18750 | AW28: =(+$F$28/12)*AW92 -> 18750 | AX28: =(+$F$28/12)*AX92 -> 18750 | AY28: =(+$F$28/12)*AY92 -> 18750 | ... BC28: =(+$F$28/12)*BC92 -> 18750 | BD28: =(+$G$26/12)*BD92 -> 20833.333 | BE28: =(+$G$26/12)*BE92 -> 20833.333 | BF28: =(+$G$26/12)*BF92 -> 20833.333 | BG28: =(+$G$26/12)*BG92 -> 20833.333 | BH28: =(+$G$26/12)*BH92 -> 20833.333 | BI28: =(+$G$26/12)*BI92 -> 20833.333 | BJ28: =(+$G$26/12)*BJ92 -> 20833.333 | BK28: =(+$G$26/12)*BK92 -> 20833.333 | ... BO28: =(+$G$26/12)*BO92 -> 20833.333
A29: Thomas Lee, COO | B29: 0 | C29: 220000 | D29: =+C29*(1+$B$26) -> 220000 | E29: =+D29*(1+$B$26) -> 220000 | F29: =+E29*(1+$B$26) -> 220000 | G29: =+F29*(1+$B$26) -> 220000 | H29: =(+$C$29/12)*H93 -> 0 | I29: =(+$C$29/12)*I93 -> 0 | J29: =(+$C$29/12)*J93 -> 0 | K29: =(+$C$29/12)*K93 -> 0 | L29: =(+$C$29/12)*L93 -> 0 | M29: =(+$C$29/12)*M93 -> 0 | N29: =(+$C$29/12)*N93 -> 0 | O29: =(+$C$29/12)*O93 -> 0 | ... S29: =(+$C$29/12)*S93 -> 0 | T29: =(+$D$29/12)*T93 -> 0 | U29: =(+$D$29/12)*U93 -> 0 | V29: =(+$D$29/12)*V93 -> 0 | W29: =(+$D$29/12)*W93 -> 0 | X29: =(+$D$29/12)*X93 -> 0 | Y29: =(+$D$29/12)*Y93 -> 0 | Z29: =(+$D$29/12)*Z93 -> 0 | AA29: =(+$D$29/12)*AA93 -> 18333.333 | ... AE29: =(+$D$29/12)*AE93 -> 18333.333 | AF29: =(+$E$29/12)*AF93 -> 18333.333 | AG29: =(+$E$29/12)*AG93 -> 18333.333 | AH29: =(+$E$29/12)*AH93 -> 18333.333 | AI29: =(+$E$29/12)*AI93 -> 18333.333 | AJ29: =(+$E$29/12)*AJ93 -> 18333.333 | AK29: =(+$E$29/12)*AK93 -> 18333.333 | AL29: =(+$E$29/12)*AL93 -> 18333.333 | AM29: =(+$E$29/12)*AM93 -> 18333.333 | ... AQ29: =(+$E$29/12)*AQ93 -> 18333.333 | AR29: =(+$F$29/12)*AR93 -> 18333.333 | AS29: =(+$F$29/12)*AS93 -> 18333.333 | AT29: =(+$F$29/12)*AT93 -> 18333.333 | AU29: =(+$F$29/12)*AU93 -> 18333.333 | AV29: =(+$F$29/12)*AV93 -> 18333.333 | AW29: =(+$F$29/12)*AW93 -> 18333.333 | AX29: =(+$F$29/12)*AX93 -> 18333.333 | AY29: =(+$F$29/12)*AY93 -> 18333.333 | ... BC29: =(+$F$29/12)*BC93 -> 18333.333 | BD29: =(+$G$26/12)*BD93 -> 20833.333 | BE29: =(+$G$26/12)*BE93 -> 20833.333 | BF29: =(+$G$26/12)*BF93 -> 20833.333 | BG29: =(+$G$26/12)*BG93 -> 20833.333 | BH29: =(+$G$26/12)*BH93 -> 20833.333 | BI29: =(+$G$26/12)*BI93 -> 20833.333 | BJ29: =(+$G$26/12)*BJ93 -> 20833.333 | BK29: =(+$G$26/12)*BK93 -> 20833.333 | ... BO29: =(+$G$26/12)*BO93 -> 20833.333
A30: Olivia Martinez, HR Manager | B30: 0 | C30: 130000 | D30: =+C30*(1+$B$26) -> 130000 | E30: =+D30*(1+$B$26) -> 130000 | F30: =+E30*(1+$B$26) -> 130000 | G30: =+F30*(1+$B$26) -> 130000 | H30: =(+$C$30/12)*H94 -> 0 | I30: =(+$C$30/12)*I94 -> 0 | J30: =(+$C$30/12)*J94 -> 0 | K30: =(+$C$30/12)*K94 -> 0 | L30: =(+$C$30/12)*L94 -> 0 | M30: =(+$C$30/12)*M94 -> 0 | N30: =(+$C$30/12)*N94 -> 0 | O30: =(+$C$30/12)*O94 -> 0 | ... S30: =(+$C$30/12)*S94 -> 0 | T30: =(+$D$30/12)*T94 -> 0 | U30: =(+$D$30/12)*U94 -> 0 | V30: =(+$D$30/12)*V94 -> 0 | W30: =(+$D$30/12)*W94 -> 0 | X30: =(+$D$30/12)*X94 -> 0 | Y30: =(+$D$30/12)*Y94 -> 0 | Z30: =(+$D$30/12)*Z94 -> 0 | AA30: =(+$D$30/12)*AA94 -> 10833.333 | ... AE30: =(+$D$30/12)*AE94 -> 10833.333 | AF30: =(+$E$30/12)*AF94 -> 10833.333 | AG30: =(+$E$30/12)*AG94 -> 10833.333 | AH30: =(+$E$30/12)*AH94 -> 10833.333 | AI30: =(+$E$30/12)*AI94 -> 10833.333 | AJ30: =(+$E$30/12)*AJ94 -> 10833.333 | AK30: =(+$E$30/12)*AK94 -> 10833.333 | AL30: =(+$E$30/12)*AL94 -> 10833.333 | AM30: =(+$E$30/12)*AM94 -> 10833.333 | ... AQ30: =(+$E$30/12)*AQ94 -> 10833.333 | AR30: =(+$F$30/12)*AR94 -> 10833.333 | AS30: =(+$F$30/12)*AS94 -> 10833.333 | AT30: =(+$F$30/12)*AT94 -> 10833.333 | AU30: =(+$F$30/12)*AU94 -> 10833.333 | AV30: =(+$F$30/12)*AV94 -> 10833.333 | AW30: =(+$F$30/12)*AW94 -> 10833.333 | AX30: =(+$F$30/12)*AX94 -> 10833.333 | AY30: =(+$F$30/12)*AY94 -> 10833.333 | ... BC30: =(+$F$30/12)*BC94 -> 10833.333 | BD30: =(+$G$26/12)*BD94 -> 20833.333 | BE30: =(+$G$26/12)*BE94 -> 20833.333 | BF30: =(+$G$26/12)*BF94 -> 20833.333 | BG30: =(+$G$26/12)*BG94 -> 20833.333 | BH30: =(+$G$26/12)*BH94 -> 20833.333 | BI30: =(+$G$26/12)*BI94 -> 20833.333 | BJ30: =(+$G$26/12)*BJ94 -> 20833.333 | BK30: =(+$G$26/12)*BK94 -> 20833.333 | ... BO30: =(+$G$26/12)*BO94 -> 20833.333
A31: Jason Wu, IT Manager | B31: 0 | C31: 140000 | D31: =+C31*(1+$B$26) -> 140000 | E31: =+D31*(1+$B$26) -> 140000 | F31: =+E31*(1+$B$26) -> 140000 | G31: =+F31*(1+$B$26) -> 140000 | H31: =(+$C$31/12)*H95 -> 0 | I31: =(+$C$31/12)*I95 -> 0 | J31: =(+$C$31/12)*J95 -> 0 | K31: =(+$C$31/12)*K95 -> 0 | L31: =(+$C$31/12)*L95 -> 0 | M31: =(+$C$31/12)*M95 -> 0 | N31: =(+$C$31/12)*N95 -> 0 | O31: =(+$C$31/12)*O95 -> 0 | ... S31: =(+$C$31/12)*S95 -> 0 | T31: =(+$D$31/12)*T95 -> 0 | U31: =(+$D$31/12)*U95 -> 0 | V31: =(+$D$31/12)*V95 -> 0 | W31: =(+$D$31/12)*W95 -> 0 | X31: =(+$D$31/12)*X95 -> 0 | Y31: =(+$D$31/12)*Y95 -> 0 | Z31: =(+$D$31/12)*Z95 -> 0 | AA31: =(+$D$31/12)*AA95 -> 11666.667 | ... AE31: =(+$D$31/12)*AE95 -> 11666.667 | AF31: =(+$E$31/12)*AF95 -> 11666.667 | AG31: =(+$E$31/12)*AG95 -> 11666.667 | AH31: =(+$E$31/12)*AH95 -> 11666.667 | AI31: =(+$E$31/12)*AI95 -> 11666.667 | AJ31: =(+$E$31/12)*AJ95 -> 11666.667 | AK31: =(+$E$31/12)*AK95 -> 11666.667 | AL31: =(+$E$31/12)*AL95 -> 11666.667 | AM31: =(+$E$31/12)*AM95 -> 11666.667 | ... AQ31: =(+$E$31/12)*AQ95 -> 11666.667 | AR31: =(+$F$31/12)*AR95 -> 11666.667 | AS31: =(+$F$31/12)*AS95 -> 11666.667 | AT31: =(+$F$31/12)*AT95 -> 11666.667 | AU31: =(+$F$31/12)*AU95 -> 11666.667 | AV31: =(+$F$31/12)*AV95 -> 11666.667 | AW31: =(+$F$31/12)*AW95 -> 11666.667 | AX31: =(+$F$31/12)*AX95 -> 11666.667 | AY31: =(+$F$31/12)*AY95 -> 11666.667 | ... BC31: =(+$F$31/12)*BC95 -> 11666.667 | BD31: =(+$G$26/12)*BD95 -> 20833.333 | BE31: =(+$G$26/12)*BE95 -> 20833.333 | BF31: =(+$G$26/12)*BF95 -> 20833.333 | BG31: =(+$G$26/12)*BG95 -> 20833.333 | BH31: =(+$G$26/12)*BH95 -> 20833.333 | BI31: =(+$G$26/12)*BI95 -> 20833.333 | BJ31: =(+$G$26/12)*BJ95 -> 20833.333 | BK31: =(+$G$26/12)*BK95 -> 20833.333 | ... BO31: =(+$G$26/12)*BO95 -> 20833.333
A32: Patricia Alvarez, Office Manager | B32: 0 | C32: 90000 | D32: =+C32*(1+$B$26) -> 90000 | E32: =+D32*(1+$B$26) -> 90000 | F32: =+E32*(1+$B$26) -> 90000 | G32: =+F32*(1+$B$26) -> 90000 | H32: =(+$C$32/12)*H96 -> 0 | I32: =(+$C$32/12)*I96 -> 0 | J32: =(+$C$32/12)*J96 -> 0 | K32: =(+$C$32/12)*K96 -> 0 | L32: =(+$C$32/12)*L96 -> 0 | M32: =(+$C$32/12)*M96 -> 0 | N32: =(+$C$32/12)*N96 -> 0 | O32: =(+$C$32/12)*O96 -> 0 | ... S32: =(+$C$32/12)*S96 -> 0 | T32: =(+$D$32/12)*T96 -> 0 | U32: =(+$D$32/12)*U96 -> 0 | V32: =(+$D$32/12)*V96 -> 0 | W32: =(+$D$32/12)*W96 -> 0 | X32: =(+$D$32/12)*X96 -> 0 | Y32: =(+$D$32/12)*Y96 -> 0 | Z32: =(+$D$32/12)*Z96 -> 0 | AA32: =(+$D$32/12)*AA96 -> 0 | ... AE32: =(+$D$32/12)*AE96 -> 0 | AF32: =(+$E$32/12)*AF96 -> 7500 | AG32: =(+$E$32/12)*AG96 -> 7500 | AH32: =(+$E$32/12)*AH96 -> 7500 | AI32: =(+$E$32/12)*AI96 -> 7500 | AJ32: =(+$E$32/12)*AJ96 -> 7500 | AK32: =(+$E$32/12)*AK96 -> 7500 | AL32: =(+$E$32/12)*AL96 -> 7500 | AM32: =(+$E$32/12)*AM96 -> 7500 | ... AQ32: =(+$E$32/12)*AQ96 -> 7500 | AR32: =(+$F$32/12)*AR96 -> 7500 | AS32: =(+$F$32/12)*AS96 -> 7500 | AT32: =(+$F$32/12)*AT96 -> 7500 | AU32: =(+$F$32/12)*AU96 -> 7500 | AV32: =(+$F$32/12)*AV96 -> 7500 | AW32: =(+$F$32/12)*AW96 -> 7500 | AX32: =(+$F$32/12)*AX96 -> 7500 | AY32: =(+$F$32/12)*AY96 -> 7500 | ... BC32: =(+$F$32/12)*BC96 -> 7500 | BD32: =(+$G$26/12)*BD96 -> 20833.333 | BE32: =(+$G$26/12)*BE96 -> 20833.333 | BF32: =(+$G$26/12)*BF96 -> 20833.333 | BG32: =(+$G$26/12)*BG96 -> 20833.333 | BH32: =(+$G$26/12)*BH96 -> 20833.333 | BI32: =(+$G$26/12)*BI96 -> 20833.333 | BJ32: =(+$G$26/12)*BJ96 -> 20833.333 | BK32: =(+$G$26/12)*BK96 -> 20833.333 | ... BO32: =(+$G$26/12)*BO96 -> 20833.333
A33: Chris Taylor, IT Support | B33: 0 | C33: 85000 | D33: =+C33*(1+$B$26) -> 85000 | E33: =+D33*(1+$B$26) -> 85000 | F33: =+E33*(1+$B$26) -> 85000 | G33: =+F33*(1+$B$26) -> 85000 | H33: =(+$C$33/12)*H97 -> 0 | I33: =(+$C$33/12)*I97 -> 0 | J33: =(+$C$33/12)*J97 -> 0 | K33: =(+$C$33/12)*K97 -> 0 | L33: =(+$C$33/12)*L97 -> 0 | M33: =(+$C$33/12)*M97 -> 0 | N33: =(+$C$33/12)*N97 -> 0 | O33: =(+$C$33/12)*O97 -> 0 | ... S33: =(+$C$33/12)*S97 -> 0 | T33: =(+$D$33/12)*T97 -> 0 | U33: =(+$D$33/12)*U97 -> 0 | V33: =(+$D$33/12)*V97 -> 0 | W33: =(+$D$33/12)*W97 -> 0 | X33: =(+$D$33/12)*X97 -> 0 | Y33: =(+$D$33/12)*Y97 -> 0 | Z33: =(+$D$33/12)*Z97 -> 0 | AA33: =(+$D$33/12)*AA97 -> 0 | ... AE33: =(+$D$33/12)*AE97 -> 0 | AF33: =(+$E$33/12)*AF97 -> 0 | AG33: =(+$E$33/12)*AG97 -> 0 | AH33: =(+$E$33/12)*AH97 -> 7083.3333 | AI33: =(+$E$33/12)*AI97 -> 7083.3333 | AJ33: =(+$E$33/12)*AJ97 -> 7083.3333 | AK33: =(+$E$33/12)*AK97 -> 7083.3333 | AL33: =(+$E$33/12)*AL97 -> 7083.3333 | AM33: =(+$E$33/12)*AM97 -> 7083.3333 | ... AQ33: =(+$E$33/12)*AQ97 -> 7083.3333 | AR33: =(+$F$33/12)*AR97 -> 7083.3333 | AS33: =(+$F$33/12)*AS97 -> 7083.3333 | AT33: =(+$F$33/12)*AT97 -> 7083.3333 | AU33: =(+$F$33/12)*AU97 -> 7083.3333 | AV33: =(+$F$33/12)*AV97 -> 7083.3333 | AW33: =(+$F$33/12)*AW97 -> 7083.3333 | AX33: =(+$F$33/12)*AX97 -> 7083.3333 | AY33: =(+$F$33/12)*AY97 -> 7083.3333 | ... BC33: =(+$F$33/12)*BC97 -> 7083.3333 | BD33: =(+$G$26/12)*BD97 -> 20833.333 | BE33: =(+$G$26/12)*BE97 -> 20833.333 | BF33: =(+$G$26/12)*BF97 -> 20833.333 | BG33: =(+$G$26/12)*BG97 -> 20833.333 | BH33: =(+$G$26/12)*BH97 -> 20833.333 | BI33: =(+$G$26/12)*BI97 -> 20833.333 | BJ33: =(+$G$26/12)*BJ97 -> 20833.333 | BK33: =(+$G$26/12)*BK97 -> 20833.333 | ... BO33: =(+$G$26/12)*BO97 -> 20833.333
A34: Kevin Park, Accounting Specialist | B34: 0 | C34: 85000 | D34: =+C34*(1+$B$26) -> 85000 | E34: =+D34*(1+$B$26) -> 85000 | F34: =+E34*(1+$B$26) -> 85000 | G34: =+F34*(1+$B$26) -> 85000 | H34: =(+$C$34/12)*H98 -> 0 | I34: =(+$C$34/12)*I98 -> 0 | J34: =(+$C$34/12)*J98 -> 0 | K34: =(+$C$34/12)*K98 -> 0 | L34: =(+$C$34/12)*L98 -> 0 | M34: =(+$C$34/12)*M98 -> 0 | N34: =(+$C$34/12)*N98 -> 0 | O34: =(+$C$34/12)*O98 -> 0 | ... S34: =(+$C$34/12)*S98 -> 0 | T34: =(+$D$34/12)*T98 -> 0 | U34: =(+$D$34/12)*U98 -> 0 | V34: =(+$D$34/12)*V98 -> 0 | W34: =(+$D$34/12)*W98 -> 0 | X34: =(+$D$34/12)*X98 -> 0 | Y34: =(+$D$34/12)*Y98 -> 0 | Z34: =(+$D$34/12)*Z98 -> 0 | AA34: =(+$D$34/12)*AA98 -> 0 | ... AE34: =(+$D$34/12)*AE98 -> 0 | AF34: =(+$E$34/12)*AF98 -> 0 | AG34: =(+$E$34/12)*AG98 -> 0 | AH34: =(+$E$34/12)*AH98 -> 0 | AI34: =(+$E$34/12)*AI98 -> 7083.3333 | AJ34: =(+$E$34/12)*AJ98 -> 7083.3333 | AK34: =(+$E$34/12)*AK98 -> 7083.3333 | AL34: =(+$E$34/12)*AL98 -> 7083.3333 | AM34: =(+$E$34/12)*AM98 -> 7083.3333 | ... AQ34: =(+$E$34/12)*AQ98 -> 7083.3333 | AR34: =(+$F$34/12)*AR98 -> 7083.3333 | AS34: =(+$F$34/12)*AS98 -> 7083.3333 | AT34: =(+$F$34/12)*AT98 -> 7083.3333 | AU34: =(+$F$34/12)*AU98 -> 7083.3333 | AV34: =(+$F$34/12)*AV98 -> 7083.3333 | AW34: =(+$F$34/12)*AW98 -> 7083.3333 | AX34: =(+$F$34/12)*AX98 -> 7083.3333 | AY34: =(+$F$34/12)*AY98 -> 7083.3333 | ... BC34: =(+$F$34/12)*BC98 -> 7083.3333 | BD34: =(+$G$26/12)*BD98 -> 20833.333 | BE34: =(+$G$26/12)*BE98 -> 20833.333 | BF34: =(+$G$26/12)*BF98 -> 20833.333 | BG34: =(+$G$26/12)*BG98 -> 20833.333 | BH34: =(+$G$26/12)*BH98 -> 20833.333 | BI34: =(+$G$26/12)*BI98 -> 20833.333 | BJ34: =(+$G$26/12)*BJ98 -> 20833.333 | BK34: =(+$G$26/12)*BK98 -> 20833.333 | ... BO34: =(+$G$26/12)*BO98 -> 20833.333
A35: Karen Lee, Finance Manager | B35: 0 | C35: 130000 | D35: =+C35*(1+$B$26) -> 130000 | E35: =+D35*(1+$B$26) -> 130000 | F35: =+E35*(1+$B$26) -> 130000 | G35: =+F35*(1+$B$26) -> 130000 | T35: =(+$D$34/12)*T99 -> 0 | U35: =(+$D$34/12)*U99 -> 0 | V35: =(+$D$34/12)*V99 -> 0 | W35: =(+$D$34/12)*W99 -> 0 | X35: =(+$D$34/12)*X99 -> 0 | Y35: =(+$D$34/12)*Y99 -> 0 | Z35: =(+$D$34/12)*Z99 -> 0 | AA35: =(+$D$34/12)*AA99 -> 7083.3333 | ... AE35: =(+$D$34/12)*AE99 -> 7083.3333 | AF35: =(+$E$34/12)*AF99 -> 7083.3333 | AG35: =(+$E$34/12)*AG99 -> 7083.3333 | AH35: =(+$E$34/12)*AH99 -> 7083.3333 | AI35: =(+$E$34/12)*AI99 -> 7083.3333 | AJ35: =(+$E$34/12)*AJ99 -> 7083.3333 | AK35: =(+$E$34/12)*AK99 -> 7083.3333 | AL35: =(+$E$34/12)*AL99 -> 7083.3333 | AM35: =(+$E$34/12)*AM99 -> 7083.3333 | ... AQ35: =(+$E$34/12)*AQ99 -> 7083.3333 | AR35: =(+$F$34/12)*AR99 -> 7083.3333 | AS35: =(+$F$34/12)*AS99 -> 7083.3333 | AT35: =(+$F$34/12)*AT99 -> 7083.3333 | AU35: =(+$F$34/12)*AU99 -> 7083.3333 | AV35: =(+$F$34/12)*AV99 -> 7083.3333 | AW35: =(+$F$34/12)*AW99 -> 7083.3333 | AX35: =(+$F$34/12)*AX99 -> 7083.3333 | AY35: =(+$F$34/12)*AY99 -> 7083.3333 | ... BC35: =(+$F$34/12)*BC99 -> 7083.3333 | BD35: =(+$G$26/12)*BD99 -> 20833.333 | BE35: =(+$G$26/12)*BE99 -> 20833.333 | BF35: =(+$G$26/12)*BF99 -> 20833.333 | BG35: =(+$G$26/12)*BG99 -> 20833.333 | BH35: =(+$G$26/12)*BH99 -> 20833.333 | BI35: =(+$G$26/12)*BI99 -> 20833.333 | BJ35: =(+$G$26/12)*BJ99 -> 20833.333 | BK35: =(+$G$26/12)*BK99 -> 20833.333 | ... BO35: =(+$G$26/12)*BO99 -> 20833.333
A36: Laura Sanchez, Executive Assistant | B36: 0 | C36: 75000 | D36: =+C36*(1+$B$26) -> 75000 | E36: =+D36*(1+$B$26) -> 75000 | F36: =+E36*(1+$B$26) -> 75000 | G36: =+F36*(1+$B$26) -> 75000 | H36: =(+$C$36/12)*H102 -> 18750 | T36: =(+$D$34/12)*T100 -> 0 | U36: =(+$D$34/12)*U100 -> 0 | V36: =(+$D$34/12)*V100 -> 0 | W36: =(+$D$34/12)*W100 -> 0 | X36: =(+$D$34/12)*X100 -> 0 | Y36: =(+$D$34/12)*Y100 -> 0 | Z36: =(+$D$34/12)*Z100 -> 0 | AA36: =(+$D$34/12)*AA100 -> 0 | ... AE36: =(+$D$34/12)*AE100 -> 0 | AF36: =(+$E$34/12)*AF100 -> 0 | AG36: =(+$E$34/12)*AG100 -> 0 | AH36: =(+$E$34/12)*AH100 -> 0 | AI36: =(+$E$34/12)*AI100 -> 0 | AJ36: =(+$E$34/12)*AJ100 -> 7083.3333 | AK36: =(+$E$34/12)*AK100 -> 7083.3333 | AL36: =(+$E$34/12)*AL100 -> 7083.3333 | AM36: =(+$E$34/12)*AM100 -> 7083.3333 | ... AQ36: =(+$E$34/12)*AQ100 -> 7083.3333 | AR36: =(+$F$34/12)*AR100 -> 7083.3333 | AS36: =(+$F$34/12)*AS100 -> 7083.3333 | AT36: =(+$F$34/12)*AT100 -> 7083.3333 | AU36: =(+$F$34/12)*AU100 -> 7083.3333 | AV36: =(+$F$34/12)*AV100 -> 7083.3333 | AW36: =(+$F$34/12)*AW100 -> 7083.3333 | AX36: =(+$F$34/12)*AX100 -> 7083.3333 | AY36: =(+$F$34/12)*AY100 -> 7083.3333 | ... BC36: =(+$F$34/12)*BC100 -> 7083.3333 | BD36: =(+$G$26/12)*BD100 -> 20833.333 | BE36: =(+$G$26/12)*BE100 -> 20833.333 | BF36: =(+$G$26/12)*BF100 -> 20833.333 | BG36: =(+$G$26/12)*BG100 -> 20833.333 | BH36: =(+$G$26/12)*BH100 -> 20833.333 | BI36: =(+$G$26/12)*BI100 -> 20833.333 | BJ36: =(+$G$26/12)*BJ100 -> 20833.333 | BK36: =(+$G$26/12)*BK100 -> 20833.333 | ... BO36: =(+$G$26/12)*BO100 -> 20833.333
A37: Michelle Wong, HR Specialist | B37: 0 | C37: 75000 | D37: =+C37*(1+$B$26) -> 75000 | E37: =+D37*(1+$B$26) -> 75000 | F37: =+E37*(1+$B$26) -> 75000 | G37: =+F37*(1+$B$26) -> 75000 | T37: =(+$D$34/12)*T101 -> 0 | U37: =(+$D$34/12)*U101 -> 0 | V37: =(+$D$34/12)*V101 -> 0 | W37: =(+$D$34/12)*W101 -> 0 | X37: =(+$D$34/12)*X101 -> 0 | Y37: =(+$D$34/12)*Y101 -> 0 | Z37: =(+$D$34/12)*Z101 -> 0 | AA37: =(+$D$34/12)*AA101 -> 0 | ... AE37: =(+$D$34/12)*AE101 -> 0 | AF37: =(+$E$34/12)*AF101 -> 0 | AG37: =(+$E$34/12)*AG101 -> 0 | AH37: =(+$E$34/12)*AH101 -> 7083.3333 | AI37: =(+$E$34/12)*AI101 -> 7083.3333 | AJ37: =(+$E$34/12)*AJ101 -> 7083.3333 | AK37: =(+$E$34/12)*AK101 -> 7083.3333 | AL37: =(+$E$34/12)*AL101 -> 7083.3333 | AM37: =(+$E$34/12)*AM101 -> 7083.3333 | ... AQ37: =(+$E$34/12)*AQ101 -> 7083.3333 | AR37: =(+$F$34/12)*AR101 -> 7083.3333 | AS37: =(+$F$34/12)*AS101 -> 7083.3333 | AT37: =(+$F$34/12)*AT101 -> 7083.3333 | AU37: =(+$F$34/12)*AU101 -> 7083.3333 | AV37: =(+$F$34/12)*AV101 -> 7083.3333 | AW37: =(+$F$34/12)*AW101 -> 7083.3333 | AX37: =(+$F$34/12)*AX101 -> 7083.3333 | AY37: =(+$F$34/12)*AY101 -> 7083.3333 | ... BC37: =(+$F$34/12)*BC101 -> 7083.3333 | BD37: =(+$G$26/12)*BD101 -> 20833.333 | BE37: =(+$G$26/12)*BE101 -> 20833.333 | BF37: =(+$G$26/12)*BF101 -> 20833.333 | BG37: =(+$G$26/12)*BG101 -> 20833.333 | BH37: =(+$G$26/12)*BH101 -> 20833.333 | BI37: =(+$G$26/12)*BI101 -> 20833.333 | BJ37: =(+$G$26/12)*BJ101 -> 20833.333 | BK37: =(+$G$26/12)*BK101 -> 20833.333 | ... BO37: =(+$G$26/12)*BO101 -> 20833.333
A38: Total Salaries - G&A | H38: =SUM(H26:H34) -> 58333.333 | I38: =SUM(I26:I34) -> 58333.333 | J38: =SUM(J26:J34) -> 58333.333 | K38: =SUM(K26:K34) -> 58333.333 | L38: =SUM(L26:L34) -> 58333.333 | M38: =SUM(M26:M34) -> 58333.333 | N38: =SUM(N26:N34) -> 58333.333 | O38: =SUM(O26:O34) -> 58333.333 | ... BO38: =SUM(BO26:BO34) -> 187500
A39: Sales and Marketing
A40: HEADCOUNT
A41: New FTEs - S&M | H41: =+H42 -> 0 | I41: =+I42-H42 -> 0 | J41: =+J42-I42 -> 0 | K41: =+K42-J42 -> 0 | L41: =+L42-K42 -> 0 | M41: =+M42-L42 -> 0 | N41: =+N42-M42 -> 0 | O41: =+O42-N42 -> 0 | P41: =+P42-O42 -> 0 | ... BO41: =+BO42-BN42 -> 0
A42: Total FTEs - S&M | H42: =+H116 -> 0 | I42: =+I116 -> 0 | J42: =+J116 -> 0 | K42: =+K116 -> 0 | L42: =+L116 -> 0 | M42: =+M116 -> 0 | N42: =+N116 -> 0 | O42: =+O116 -> 0 | ... BO42: =+BO116 -> 8
A43: Director of Marketing - Sarah Johnson | B43: 0.05 | C43: 160000 | D43: =+C43*(1+$B$26) -> 160000 | E43: =+D43*(1+$B$26) -> 160000 | F43: =+E43*(1+$B$26) -> 160000 | G43: =+F43*(1+$B$26) -> 160000 | H43: =($C$43/12)*H107 -> 0 | I43: =($C$43/12)*I107 -> 0 | J43: =($C$43/12)*J107 -> 0 | K43: =($C$43/12)*K107 -> 0 | L43: =($C$43/12)*L107 -> 0 | M43: =($C$43/12)*M107 -> 0 | N43: =($C$43/12)*N107 -> 0 | O43: =($C$43/12)*O107 -> 0 | ... S43: =($C$43/12)*S107 -> 0 | T43: =($D$43/12)*T107 -> 6666.6667 | U43: =($D$43/12)*U107 -> 13333.333 | V43: =($D$43/12)*V107 -> 13333.333 | W43: =($D$43/12)*W107 -> 13333.333 | X43: =($D$43/12)*X107 -> 13333.333 | Y43: =($D$43/12)*Y107 -> 13333.333 | Z43: =($D$43/12)*Z107 -> 13333.333 | AA43: =($D$43/12)*AA107 -> 13333.333 | ... AE43: =($D$43/12)*AE107 -> 13333.333 | AF43: =($E$43/12)*AF107 -> 13333.333 | AG43: =($E$43/12)*AG107 -> 13333.333 | AH43: =($E$43/12)*AH107 -> 13333.333 | AI43: =($E$43/12)*AI107 -> 13333.333 | AJ43: =($E$43/12)*AJ107 -> 13333.333 | AK43: =($E$43/12)*AK107 -> 13333.333 | AL43: =($E$43/12)*AL107 -> 13333.333 | AM43: =($E$43/12)*AM107 -> 13333.333 | ... AQ43: =($E$43/12)*AQ107 -> 13333.333 | AR43: =($F$43/12)*AR107 -> 13333.333 | AS43: =($F$43/12)*AS107 -> 13333.333 | AT43: =($F$43/12)*AT107 -> 13333.333 | AU43: =($F$43/12)*AU107 -> 13333.333 | AV43: =($F$43/12)*AV107 -> 13333.333 | AW43: =($F$43/12)*AW107 -> 13333.333 | AX43: =($F$43/12)*AX107 -> 13333.333 | AY43: =($F$43/12)*AY107 -> 13333.333 | ... BC43: =($F$43/12)*BC107 -> 13333.333 | BD43: =($G$43/12)*BD107 -> 13333.333 | BE43: =($G$43/12)*BE107 -> 13333.333 | BF43: =($G$43/12)*BF107 -> 13333.333 | BG43: =($G$43/12)*BG107 -> 13333.333 | BH43: =($G$43/12)*BH107 -> 13333.333 | BI43: =($G$43/12)*BI107 -> 13333.333 | BJ43: =($G$43/12)*BJ107 -> 13333.333 | BK43: =($G$43/12)*BK107 -> 13333.333 | ... BO43: =($G$43/12)*BO107 -> 13333.333
A44: Sr Sales Manager - James Wilson | B44: 0.05 | C44: 150000 | D44: =+C44*(1+$B$26) -> 150000 | E44: =+D44*(1+$B$26) -> 150000 | F44: =+E44*(1+$B$26) -> 150000 | G44: =+F44*(1+$B$26) -> 150000 | H44: =($C$44/12)*H108 -> 0 | I44: =($C$44/12)*I108 -> 0 | J44: =($C$44/12)*J108 -> 0 | K44: =($C$44/12)*K108 -> 0 | L44: =($C$44/12)*L108 -> 0 | M44: =($C$44/12)*M108 -> 0 | N44: =($C$44/12)*N108 -> 0 | O44: =($C$44/12)*O108 -> 0 | ... S44: =($C$44/12)*S108 -> 0 | T44: =($D$44/12)*T108 -> 0 | U44: =($D$44/12)*U108 -> 0 | V44: =($D$44/12)*V108 -> 0 | W44: =($D$44/12)*W108 -> 0 | X44: =($D$44/12)*X108 -> 0 | Y44: =($D$44/12)*Y108 -> 0 | Z44: =($D$44/12)*Z108 -> 0 | AA44: =($D$44/12)*AA108 -> 12500 | ... AE44: =($D$44/12)*AE108 -> 12500 | AF44: =($E$44/12)*AF108 -> 12500 | AG44: =($E$44/12)*AG108 -> 12500 | AH44: =($E$44/12)*AH108 -> 12500 | AI44: =($E$44/12)*AI108 -> 12500 | AJ44: =($E$44/12)*AJ108 -> 12500 | AK44: =($E$44/12)*AK108 -> 12500 | AL44: =($E$44/12)*AL108 -> 12500 | AM44: =($E$44/12)*AM108 -> 12500 | ... AQ44: =($E$44/12)*AQ108 -> 12500 | AR44: =($F$44/12)*AR108 -> 12500 | AS44: =($F$44/12)*AS108 -> 12500 | AT44: =($F$44/12)*AT108 -> 12500 | AU44: =($F$44/12)*AU108 -> 12500 | AV44: =($F$44/12)*AV108 -> 12500 | AW44: =($F$44/12)*AW108 -> 12500 | AX44: =($F$44/12)*AX108 -> 12500 | AY44: =($F$44/12)*AY108 -> 12500 | ... BC44: =($F$44/12)*BC108 -> 12500 | BD44: =($G$44/12)*BD108 -> 12500 | BE44: =($G$44/12)*BE108 -> 12500 | BF44: =($G$44/12)*BF108 -> 12500 | BG44: =($G$44/12)*BG108 -> 12500 | BH44: =($G$44/12)*BH108 -> 12500 | BI44: =($G$44/12)*BI108 -> 12500 | BJ44: =($G$44/12)*BJ108 -> 12500 | BK44: =($G$44/12)*BK108 -> 12500 | ... BO44: =($G$44/12)*BO108 -> 12500
A45: Digital Marketing Specialist - Linda Chen | B45: 0.05 | C45: 110000 | D45: =+C45*(1+$B$26) -> 110000 | E45: =+D45*(1+$B$26) -> 110000 | F45: =+E45*(1+$B$26) -> 110000 | G45: =+F45*(1+$B$26) -> 110000 | H45: =($C$45/12)*H109 -> 0 | I45: =($C$45/12)*I109 -> 0 | J45: =($C$45/12)*J109 -> 0 | K45: =($C$45/12)*K109 -> 0 | L45: =($C$45/12)*L109 -> 0 | M45: =($C$45/12)*M109 -> 0 | N45: =($C$45/12)*N109 -> 0 | O45: =($C$45/12)*O109 -> 0 | ... S45: =($C$45/12)*S109 -> 0 | T45: =($D$45/12)*T109 -> 0 | U45: =($D$45/12)*U109 -> 0 | V45: =($D$45/12)*V109 -> 0 | W45: =($D$45/12)*W109 -> 0 | X45: =($D$45/12)*X109 -> 0 | Y45: =($D$45/12)*Y109 -> 0 | Z45: =($D$45/12)*Z109 -> 0 | AA45: =($D$45/12)*AA109 -> 9166.6667 | ... AE45: =($D$45/12)*AE109 -> 9166.6667 | AF45: =($E$45/12)*AF109 -> 9166.6667 | AG45: =($E$45/12)*AG109 -> 9166.6667 | AH45: =($E$45/12)*AH109 -> 9166.6667 | AI45: =($E$45/12)*AI109 -> 9166.6667 | AJ45: =($E$45/12)*AJ109 -> 9166.6667 | AK45: =($E$45/12)*AK109 -> 9166.6667 | AL45: =($E$45/12)*AL109 -> 9166.6667 | AM45: =($E$45/12)*AM109 -> 9166.6667 | ... AQ45: =($E$45/12)*AQ109 -> 9166.6667 | AR45: =($F$45/12)*AR109 -> 9166.6667 | AS45: =($F$45/12)*AS109 -> 9166.6667 | AT45: =($F$45/12)*AT109 -> 9166.6667 | AU45: =($F$45/12)*AU109 -> 9166.6667 | AV45: =($F$45/12)*AV109 -> 9166.6667 | AW45: =($F$45/12)*AW109 -> 9166.6667 | AX45: =($F$45/12)*AX109 -> 9166.6667 | AY45: =($F$45/12)*AY109 -> 9166.6667 | ... BC45: =($F$45/12)*BC109 -> 9166.6667 | BD45: =($G$45/12)*BD109 -> 9166.6667 | BE45: =($G$45/12)*BE109 -> 9166.6667 | BF45: =($G$45/12)*BF109 -> 9166.6667 | BG45: =($G$45/12)*BG109 -> 9166.6667 | BH45: =($G$45/12)*BH109 -> 9166.6667 | BI45: =($G$45/12)*BI109 -> 9166.6667 | BJ45: =($G$45/12)*BJ109 -> 9166.6667 | BK45: =($G$45/12)*BK109 -> 9166.6667 | ... BO45: =($G$45/12)*BO109 -> 9166.6667
A46: Business Development Manager - Mark Thompson | B46: 0.05 | C46: 130000 | D46: =+C46*(1+$B$26) -> 130000 | E46: =+D46*(1+$B$26) -> 130000 | F46: =+E46*(1+$B$26) -> 130000 | G46: =+F46*(1+$B$26) -> 130000 | H46: =($C$46/12)*H110 -> 0 | I46: =($C$46/12)*I110 -> 0 | J46: =($C$46/12)*J110 -> 0 | K46: =($C$46/12)*K110 -> 0 | L46: =($C$46/12)*L110 -> 0 | M46: =($C$46/12)*M110 -> 0 | N46: =($C$46/12)*N110 -> 0 | O46: =($C$46/12)*O110 -> 0 | ... S46: =($C$46/12)*S110 -> 0 | T46: =($D$46/12)*T110 -> 0 | U46: =($D$46/12)*U110 -> 0 | V46: =($D$46/12)*V110 -> 0 | W46: =($D$46/12)*W110 -> 0 | X46: =($D$46/12)*X110 -> 0 | Y46: =($D$46/12)*Y110 -> 0 | Z46: =($D$46/12)*Z110 -> 0 | AA46: =($D$46/12)*AA110 -> 10833.333 | ... AE46: =($D$46/12)*AE110 -> 10833.333 | AF46: =($E$46/12)*AF110 -> 10833.333 | AG46: =($E$46/12)*AG110 -> 10833.333 | AH46: =($E$46/12)*AH110 -> 10833.333 | AI46: =($E$46/12)*AI110 -> 10833.333 | AJ46: =($E$46/12)*AJ110 -> 10833.333 | AK46: =($E$46/12)*AK110 -> 10833.333 | AL46: =($E$46/12)*AL110 -> 10833.333 | AM46: =($E$46/12)*AM110 -> 10833.333 | ... AQ46: =($E$46/12)*AQ110 -> 10833.333 | AR46: =($F$46/12)*AR110 -> 10833.333 | AS46: =($F$46/12)*AS110 -> 10833.333 | AT46: =($F$46/12)*AT110 -> 10833.333 | AU46: =($F$46/12)*AU110 -> 10833.333 | AV46: =($F$46/12)*AV110 -> 10833.333 | AW46: =($F$46/12)*AW110 -> 10833.333 | AX46: =($F$46/12)*AX110 -> 10833.333 | AY46: =($F$46/12)*AY110 -> 10833.333 | ... BC46: =($F$46/12)*BC110 -> 10833.333 | BD46: =($G$46/12)*BD110 -> 10833.333 | BE46: =($G$46/12)*BE110 -> 10833.333 | BF46: =($G$46/12)*BF110 -> 10833.333 | BG46: =($G$46/12)*BG110 -> 10833.333 | BH46: =($G$46/12)*BH110 -> 10833.333 | BI46: =($G$46/12)*BI110 -> 10833.333 | BJ46: =($G$46/12)*BJ110 -> 10833.333 | BK46: =($G$46/12)*BK110 -> 10833.333 | ... BO46: =($G$46/12)*BO110 -> 10833.333
A47: Sales Representative - Rachel Green | B47: 0.05 | C47: 100000 | D47: =+C47*(1+$B$26) -> 100000 | E47: =+D47*(1+$B$26) -> 100000 | F47: =+E47*(1+$B$26) -> 100000 | G47: =+F47*(1+$B$26) -> 100000 | H47: =($C$47/12)*H111 -> 0 | I47: =($C$47/12)*I111 -> 0 | J47: =($C$47/12)*J111 -> 0 | K47: =($C$47/12)*K111 -> 0 | L47: =($C$47/12)*L111 -> 0 | M47: =($C$47/12)*M111 -> 0 | N47: =($C$47/12)*N111 -> 0 | O47: =($C$47/12)*O111 -> 0 | ... S47: =($C$47/12)*S111 -> 0 | T47: =($D$47/12)*T111 -> 0 | U47: =($D$47/12)*U111 -> 0 | V47: =($D$47/12)*V111 -> 0 | W47: =($D$47/12)*W111 -> 0 | X47: =($D$47/12)*X111 -> 0 | Y47: =($D$47/12)*Y111 -> 0 | Z47: =($D$47/12)*Z111 -> 0 | AA47: =($D$47/12)*AA111 -> 0 | ... AE47: =($D$47/12)*AE111 -> 8333.3333 | AF47: =($E$47/12)*AF111 -> 8333.3333 | AG47: =($E$47/12)*AG111 -> 8333.3333 | AH47: =($E$47/12)*AH111 -> 8333.3333 | AI47: =($E$47/12)*AI111 -> 8333.3333 | AJ47: =($E$47/12)*AJ111 -> 8333.3333 | AK47: =($E$47/12)*AK111 -> 8333.3333 | AL47: =($E$47/12)*AL111 -> 8333.3333 | AM47: =($E$47/12)*AM111 -> 8333.3333 | ... AQ47: =($E$47/12)*AQ111 -> 8333.3333 | AR47: =($F$47/12)*AR111 -> 8333.3333 | AS47: =($F$47/12)*AS111 -> 8333.3333 | AT47: =($F$47/12)*AT111 -> 8333.3333 | AU47: =($F$47/12)*AU111 -> 8333.3333 | AV47: =($F$47/12)*AV111 -> 8333.3333 | AW47: =($F$47/12)*AW111 -> 8333.3333 | AX47: =($F$47/12)*AX111 -> 8333.3333 | AY47: =($F$47/12)*AY111 -> 8333.3333 | ... BC47: =($F$47/12)*BC111 -> 8333.3333 | BD47: =($G$47/12)*BD111 -> 8333.3333 | BE47: =($G$47/12)*BE111 -> 8333.3333 | BF47: =($G$47/12)*BF111 -> 8333.3333 | BG47: =($G$47/12)*BG111 -> 8333.3333 | BH47: =($G$47/12)*BH111 -> 8333.3333 | BI47: =($G$47/12)*BI111 -> 8333.3333 | BJ47: =($G$47/12)*BJ111 -> 8333.3333 | BK47: =($G$47/12)*BK111 -> 8333.3333 | ... BO47: =($G$47/12)*BO111 -> 8333.3333
A48: Sales Representative, Daniel Lee | B48: 0.05 | C48: 100000 | D48: =+C48*(1+$B$26) -> 100000 | E48: =+D48*(1+$B$26) -> 100000 | F48: =+E48*(1+$B$26) -> 100000 | G48: =+F48*(1+$B$26) -> 100000 | H48: =($C$48/12)*H112 -> 0 | I48: =($C$48/12)*I112 -> 0 | J48: =($C$48/12)*J112 -> 0 | K48: =($C$48/12)*K112 -> 0 | L48: =($C$48/12)*L112 -> 0 | M48: =($C$48/12)*M112 -> 0 | N48: =($C$48/12)*N112 -> 0 | O48: =($C$48/12)*O112 -> 0 | ... S48: =($C$48/12)*S112 -> 0 | T48: =($D$48/12)*T112 -> 0 | U48: =($D$48/12)*U112 -> 0 | V48: =($D$48/12)*V112 -> 0 | W48: =($D$48/12)*W112 -> 0 | X48: =($D$48/12)*X112 -> 0 | Y48: =($D$48/12)*Y112 -> 0 | Z48: =($D$48/12)*Z112 -> 0 | AA48: =($D$48/12)*AA112 -> 0 | ... AE48: =($D$48/12)*AE112 -> 8333.3333 | AF48: =($E$48/12)*AF112 -> 8333.3333 | AG48: =($E$48/12)*AG112 -> 8333.3333 | AH48: =($E$48/12)*AH112 -> 8333.3333 | AI48: =($E$48/12)*AI112 -> 8333.3333 | AJ48: =($E$48/12)*AJ112 -> 8333.3333 | AK48: =($E$48/12)*AK112 -> 8333.3333 | AL48: =($E$48/12)*AL112 -> 8333.3333 | AM48: =($E$48/12)*AM112 -> 8333.3333 | ... AQ48: =($E$48/12)*AQ112 -> 8333.3333 | AR48: =($F$48/12)*AR112 -> 8333.3333 | AS48: =($F$48/12)*AS112 -> 8333.3333 | AT48: =($F$48/12)*AT112 -> 8333.3333 | AU48: =($F$48/12)*AU112 -> 8333.3333 | AV48: =($F$48/12)*AV112 -> 8333.3333 | AW48: =($F$48/12)*AW112 -> 8333.3333 | AX48: =($F$48/12)*AX112 -> 8333.3333 | AY48: =($F$48/12)*AY112 -> 8333.3333 | ... BC48: =($F$48/12)*BC112 -> 8333.3333 | BD48: =($G$48/12)*BD112 -> 8333.3333 | BE48: =($G$48/12)*BE112 -> 8333.3333 | BF48: =($G$48/12)*BF112 -> 8333.3333 | BG48: =($G$48/12)*BG112 -> 8333.3333 | BH48: =($G$48/12)*BH112 -> 8333.3333 | BI48: =($G$48/12)*BI112 -> 8333.3333 | BJ48: =($G$48/12)*BJ112 -> 8333.3333 | BK48: =($G$48/12)*BK112 -> 8333.3333 | ... BO48: =($G$48/12)*BO112 -> 8333.3333
A49: Content Marketing Specialist - Emma Watson | B49: 0.05 | C49: 95000 | D49: =+C49*(1+$B$26) -> 95000 | E49: =+D49*(1+$B$26) -> 95000 | F49: =+E49*(1+$B$26) -> 95000 | G49: =+F49*(1+$B$26) -> 95000 | H49: =($C$49/12)*H113 -> 0 | I49: =($C$49/12)*I113 -> 0 | J49: =($C$49/12)*J113 -> 0 | K49: =($C$49/12)*K113 -> 0 | L49: =($C$49/12)*L113 -> 0 | M49: =($C$49/12)*M113 -> 0 | N49: =($C$49/12)*N113 -> 0 | O49: =($C$49/12)*O113 -> 0 | ... S49: =($C$49/12)*S113 -> 0 | T49: =($D$49/12)*T113 -> 0 | U49: =($D$49/12)*U113 -> 0 | V49: =($D$49/12)*V113 -> 0 | W49: =($D$49/12)*W113 -> 0 | X49: =($D$49/12)*X113 -> 0 | Y49: =($D$49/12)*Y113 -> 0 | Z49: =($D$49/12)*Z113 -> 0 | AA49: =($D$49/12)*AA113 -> 0 | ... AE49: =($D$49/12)*AE113 -> 7916.6667 | AF49: =($E$49/12)*AF113 -> 7916.6667 | AG49: =($E$49/12)*AG113 -> 7916.6667 | AH49: =($E$49/12)*AH113 -> 7916.6667 | AI49: =($E$49/12)*AI113 -> 7916.6667 | AJ49: =($E$49/12)*AJ113 -> 7916.6667 | AK49: =($E$49/12)*AK113 -> 7916.6667 | AL49: =($E$49/12)*AL113 -> 7916.6667 | AM49: =($E$49/12)*AM113 -> 7916.6667 | ... AQ49: =($E$49/12)*AQ113 -> 7916.6667 | AR49: =($F$49/12)*AR113 -> 7916.6667 | AS49: =($F$49/12)*AS113 -> 7916.6667 | AT49: =($F$49/12)*AT113 -> 7916.6667 | AU49: =($F$49/12)*AU113 -> 7916.6667 | AV49: =($F$49/12)*AV113 -> 7916.6667 | AW49: =($F$49/12)*AW113 -> 7916.6667 | AX49: =($F$49/12)*AX113 -> 7916.6667 | AY49: =($F$49/12)*AY113 -> 7916.6667 | ... BC49: =($F$49/12)*BC113 -> 7916.6667 | BD49: =($G$49/12)*BD113 -> 7916.6667 | BE49: =($G$49/12)*BE113 -> 7916.6667 | BF49: =($G$49/12)*BF113 -> 7916.6667 | BG49: =($G$49/12)*BG113 -> 7916.6667 | BH49: =($G$49/12)*BH113 -> 7916.6667 | BI49: =($G$49/12)*BI113 -> 7916.6667 | BJ49: =($G$49/12)*BJ113 -> 7916.6667 | BK49: =($G$49/12)*BK113 -> 7916.6667 | ... BO49: =($G$49/12)*BO113 -> 7916.6667
A50: Sales Operations Anyalyst - Michael Brown | B50: 0.05 | C50: 90000 | D50: =+C50*(1+$B$26) -> 90000 | E50: =+D50*(1+$B$26) -> 90000 | F50: =+E50*(1+$B$26) -> 90000 | G50: =+F50*(1+$B$26) -> 90000 | H50: =($C$50/12)*H114 -> 0 | I50: =($C$50/12)*I114 -> 0 | J50: =($C$50/12)*J114 -> 0 | K50: =($C$50/12)*K114 -> 0 | L50: =($C$50/12)*L114 -> 0 | M50: =($C$50/12)*M114 -> 0 | N50: =($C$50/12)*N114 -> 0 | O50: =($C$50/12)*O114 -> 0 | ... S50: =($C$50/12)*S114 -> 0 | T50: =($D$50/12)*T114 -> 0 | U50: =($D$50/12)*U114 -> 0 | V50: =($D$50/12)*V114 -> 0 | W50: =($D$50/12)*W114 -> 0 | X50: =($D$50/12)*X114 -> 0 | Y50: =($D$50/12)*Y114 -> 0 | Z50: =($D$50/12)*Z114 -> 0 | AA50: =($D$50/12)*AA114 -> 0 | ... AE50: =($D$50/12)*AE114 -> 7500 | AF50: =($E$50/12)*AF114 -> 7500 | AG50: =($E$50/12)*AG114 -> 7500 | AH50: =($E$50/12)*AH114 -> 7500 | AI50: =($E$50/12)*AI114 -> 7500 | AJ50: =($E$50/12)*AJ114 -> 7500 | AK50: =($E$50/12)*AK114 -> 7500 | AL50: =($E$50/12)*AL114 -> 7500 | AM50: =($E$50/12)*AM114 -> 7500 | ... AQ50: =($E$50/12)*AQ114 -> 7500 | AR50: =($F$50/12)*AR114 -> 7500 | AS50: =($F$50/12)*AS114 -> 7500 | AT50: =($F$50/12)*AT114 -> 7500 | AU50: =($F$50/12)*AU114 -> 7500 | AV50: =($F$50/12)*AV114 -> 7500 | AW50: =($F$50/12)*AW114 -> 7500 | AX50: =($F$50/12)*AX114 -> 7500 | AY50: =($F$50/12)*AY114 -> 7500 | ... BC50: =($F$50/12)*BC114 -> 7500 | BD50: =($G$50/12)*BD114 -> 7500 | BE50: =($G$50/12)*BE114 -> 7500 | BF50: =($G$50/12)*BF114 -> 7500 | BG50: =($G$50/12)*BG114 -> 7500 | BH50: =($G$50/12)*BH114 -> 7500 | BI50: =($G$50/12)*BI114 -> 7500 | BJ50: =($G$50/12)*BJ114 -> 7500 | BK50: =($G$50/12)*BK114 -> 7500 | ... BO50: =($G$50/12)*BO114 -> 7500
A51: Sales Position 9 | B51: 0.05 | C51: 0 | D51: =+C51*(1+$B$26) -> 0 | E51: =+D51*(1+$B$26) -> 0 | F51: =+E51*(1+$B$26) -> 0 | G51: =+F51*(1+$B$26) -> 0 | H51: =($C$51/12)*H115 -> 0 | I51: =($C$51/12)*I115 -> 0 | J51: =($C$51/12)*J115 -> 0 | K51: =($C$51/12)*K115 -> 0 | L51: =($C$51/12)*L115 -> 0 | M51: =($C$51/12)*M115 -> 0 | N51: =($C$51/12)*N115 -> 0 | O51: =($C$51/12)*O115 -> 0 | ... S51: =($C$51/12)*S115 -> 0 | T51: =($D$51/12)*T115 -> 0 | U51: =($D$51/12)*U115 -> 0 | V51: =($D$51/12)*V115 -> 0 | W51: =($D$51/12)*W115 -> 0 | X51: =($D$51/12)*X115 -> 0 | Y51: =($D$51/12)*Y115 -> 0 | Z51: =($D$51/12)*Z115 -> 0 | AA51: =($D$51/12)*AA115 -> 0 | ... AE51: =($D$51/12)*AE115 -> 0 | AF51: =($E$51/12)*AF115 -> 0 | AG51: =($E$51/12)*AG115 -> 0 | AH51: =($E$51/12)*AH115 -> 0 | AI51: =($E$51/12)*AI115 -> 0 | AJ51: =($E$51/12)*AJ115 -> 0 | AK51: =($E$51/12)*AK115 -> 0 | AL51: =($E$51/12)*AL115 -> 0 | AM51: =($E$51/12)*AM115 -> 0 | ... AQ51: =($E$51/12)*AQ115 -> 0 | AR51: =($F$51/12)*AR115 -> 0 | AS51: =($F$51/12)*AS115 -> 0 | AT51: =($F$51/12)*AT115 -> 0 | AU51: =($F$51/12)*AU115 -> 0 | AV51: =($F$51/12)*AV115 -> 0 | AW51: =($F$51/12)*AW115 -> 0 | AX51: =($F$51/12)*AX115 -> 0 | AY51: =($F$51/12)*AY115 -> 0 | ... BC51: =($F$51/12)*BC115 -> 0 | BD51: =($G$51/12)*BD115 -> 0 | BE51: =($G$51/12)*BE115 -> 0 | BF51: =($G$51/12)*BF115 -> 0 | BG51: =($G$51/12)*BG115 -> 0 | BH51: =($G$51/12)*BH115 -> 0 | BI51: =($G$51/12)*BI115 -> 0 | BJ51: =($G$51/12)*BJ115 -> 0 | BK51: =($G$51/12)*BK115 -> 0 | ... BO51: =($G$51/12)*BO115 -> 0
A52: Total Salaries - S&M | H52: =SUM(H43:H51) -> 0 | I52: =SUM(I43:I51) -> 0 | J52: =SUM(J43:J51) -> 0 | K52: =SUM(K43:K51) -> 0 | L52: =SUM(L43:L51) -> 0 | M52: =SUM(M43:M51) -> 0 | N52: =SUM(N43:N51) -> 0 | O52: =SUM(O43:O51) -> 0 | ... BO52: =SUM(BO43:BO51) -> 77916.667
A53: Product
A54: HEADCOUNT
A55: New Genrici FTEs - PD | H55: =+H56 -> 0 | I55: =+I56-H56 -> 0 | J55: =+J56-I56 -> 0 | K55: =+K56-J56 -> 1 | L55: =+L56-K56 -> 0 | M55: =+M56-L56 -> 0 | N55: =+N56-M56 -> 0 | O55: =+O56-N56 -> 1 | P55: =+P56-O56 -> 3 | ... BO55: =+BO56-BN56 -> 0
A56: Total FTEs - PD | H56: =+H146 -> 0 | I56: =+I146 -> 0 | J56: =+J146 -> 0 | K56: =+K146 -> 1 | L56: =+L146 -> 1 | M56: =+M146 -> 1 | N56: =+N146 -> 1 | O56: =+O146 -> 2 | ... BO56: =+BO146 -> 29
A57: Head of Engineering - Ethan Nakamura | B57: 0.05 | C57: 180000 | D57: =+C57*(1+$B$26) -> 180000 | E57: =+D57*(1+$B$26) -> 180000 | F57: =+E57*(1+$B$26) -> 180000 | G57: =+F57*(1+$B$26) -> 180000 | H57: =($C57/12)*H121 -> 0 | I57: =($C57/12)*I121 -> 0 | J57: =($C57/12)*J121 -> 0 | K57: =($C57/12)*K121 -> 15000 | L57: =($C57/12)*L121 -> 15000 | M57: =($C57/12)*M121 -> 15000 | N57: =($C57/12)*N121 -> 15000 | O57: =($C57/12)*O121 -> 15000 | ... S57: =($C57/12)*S121 -> 15000 | T57: =($D$57/12)*T121 -> 15000 | U57: =($D$57/12)*U121 -> 15000 | V57: =($D$57/12)*V121 -> 15000 | W57: =($D$57/12)*W121 -> 15000 | X57: =($D$57/12)*X121 -> 15000 | Y57: =($D$57/12)*Y121 -> 15000 | Z57: =($D$57/12)*Z121 -> 15000 | AA57: =($D$57/12)*AA121 -> 15000 | ... AE57: =($D$57/12)*AE121 -> 15000 | AF57: =($E57/12)*AF121 -> 15000 | AG57: =($E57/12)*AG121 -> 15000 | AH57: =($E57/12)*AH121 -> 15000 | AI57: =($E57/12)*AI121 -> 15000 | AJ57: =($E57/12)*AJ121 -> 15000 | AK57: =($E57/12)*AK121 -> 15000 | AL57: =($E57/12)*AL121 -> 15000 | AM57: =($E57/12)*AM121 -> 15000 | ... AQ57: =($E57/12)*AQ121 -> 15000 | AR57: =($F57/12)*AR121 -> 15000 | AS57: =($F57/12)*AS121 -> 15000 | AT57: =($F57/12)*AT121 -> 15000 | AU57: =($F57/12)*AU121 -> 15000 | AV57: =($F57/12)*AV121 -> 15000 | AW57: =($F57/12)*AW121 -> 15000 | AX57: =($F57/12)*AX121 -> 15000 | AY57: =($F57/12)*AY121 -> 15000 | ... BC57: =($F57/12)*BC121 -> 15000 | BD57: =($G57/12)*BD121 -> 15000 | BE57: =($G57/12)*BE121 -> 15000 | BF57: =($G57/12)*BF121 -> 15000 | BG57: =($G57/12)*BG121 -> 15000 | BH57: =($G57/12)*BH121 -> 15000 | BI57: =($G57/12)*BI121 -> 15000 | BJ57: =($G57/12)*BJ121 -> 15000 | BK57: =($G57/12)*BK121 -> 15000 | ... BO57: =($G57/12)*BO121 -> 15000
A58: Head of Research - Dr. Aisha Patel | B58: 0.05 | C58: 175000 | D58: =+C58*(1+$B$26) -> 175000 | E58: =+D58*(1+$B$26) -> 175000 | F58: =+E58*(1+$B$26) -> 175000 | G58: =+F58*(1+$B$26) -> 175000 | H58: =($C58/12)*H122 -> 0 | I58: =($C58/12)*I122 -> 0 | J58: =($C58/12)*J122 -> 0 | K58: =($C58/12)*K122 -> 0 | L58: =($C58/12)*L122 -> 0 | M58: =($C58/12)*M122 -> 0 | N58: =($C58/12)*N122 -> 0 | O58: =($C58/12)*O122 -> 14583.333 | ... S58: =($C58/12)*S122 -> 14583.333 | T58: =($D$58/12)*T122 -> 14583.333 | U58: =($D$58/12)*U122 -> 14583.333 | V58: =($D$58/12)*V122 -> 14583.333 | W58: =($D$58/12)*W122 -> 14583.333 | X58: =($D$58/12)*X122 -> 14583.333 | Y58: =($D$58/12)*Y122 -> 14583.333 | Z58: =($D$58/12)*Z122 -> 14583.333 | AA58: =($D$58/12)*AA122 -> 14583.333 | ... AE58: =($D$58/12)*AE122 -> 14583.333 | AF58: =($E58/12)*AF122 -> 14583.333 | AG58: =($E58/12)*AG122 -> 14583.333 | AH58: =($E58/12)*AH122 -> 14583.333 | AI58: =($E58/12)*AI122 -> 14583.333 | AJ58: =($E58/12)*AJ122 -> 14583.333 | AK58: =($E58/12)*AK122 -> 14583.333 | AL58: =($E58/12)*AL122 -> 14583.333 | AM58: =($E58/12)*AM122 -> 14583.333 | ... AQ58: =($E58/12)*AQ122 -> 14583.333 | AR58: =($F58/12)*AR122 -> 14583.333 | AS58: =($F58/12)*AS122 -> 14583.333 | AT58: =($F58/12)*AT122 -> 14583.333 | AU58: =($F58/12)*AU122 -> 14583.333 | AV58: =($F58/12)*AV122 -> 14583.333 | AW58: =($F58/12)*AW122 -> 14583.333 | AX58: =($F58/12)*AX122 -> 14583.333 | AY58: =($F58/12)*AY122 -> 14583.333 | ... BC58: =($F58/12)*BC122 -> 14583.333 | BD58: =($G58/12)*BD122 -> 14583.333 | BE58: =($G58/12)*BE122 -> 14583.333 | BF58: =($G58/12)*BF122 -> 14583.333 | BG58: =($G58/12)*BG122 -> 14583.333 | BH58: =($G58/12)*BH122 -> 14583.333 | BI58: =($G58/12)*BI122 -> 14583.333 | BJ58: =($G58/12)*BJ122 -> 14583.333 | BK58: =($G58/12)*BK122 -> 14583.333 | ... BO58: =($G58/12)*BO122 -> 14583.333
A59: Lead Software Architect - Michael Torres | B59: 0.05 | C59: 170000 | D59: =+C59*(1+$B$26) -> 170000 | E59: =+D59*(1+$B$26) -> 170000 | F59: =+E59*(1+$B$26) -> 170000 | G59: =+F59*(1+$B$26) -> 170000 | H59: =($C59/12)*H123 -> 0 | I59: =($C59/12)*I123 -> 0 | J59: =($C59/12)*J123 -> 0 | K59: =($C59/12)*K123 -> 0 | L59: =($C59/12)*L123 -> 0 | M59: =($C59/12)*M123 -> 0 | N59: =($C59/12)*N123 -> 0 | O59: =($C59/12)*O123 -> 0 | ... S59: =($C59/12)*S123 -> 14166.667 | T59: =($D$59/12)*T123 -> 14166.667 | U59: =($D$59/12)*U123 -> 14166.667 | V59: =($D$59/12)*V123 -> 14166.667 | W59: =($D$59/12)*W123 -> 14166.667 | X59: =($D$59/12)*X123 -> 14166.667 | Y59: =($D$59/12)*Y123 -> 14166.667 | Z59: =($D$59/12)*Z123 -> 14166.667 | AA59: =($D$59/12)*AA123 -> 14166.667 | ... AE59: =($D$59/12)*AE123 -> 14166.667 | AF59: =($E59/12)*AF123 -> 14166.667 | AG59: =($E59/12)*AG123 -> 14166.667 | AH59: =($E59/12)*AH123 -> 14166.667 | AI59: =($E59/12)*AI123 -> 14166.667 | AJ59: =($E59/12)*AJ123 -> 14166.667 | AK59: =($E59/12)*AK123 -> 14166.667 | AL59: =($E59/12)*AL123 -> 14166.667 | AM59: =($E59/12)*AM123 -> 14166.667 | ... AQ59: =($E59/12)*AQ123 -> 14166.667 | AR59: =($F59/12)*AR123 -> 14166.667 | AS59: =($F59/12)*AS123 -> 14166.667 | AT59: =($F59/12)*AT123 -> 14166.667 | AU59: =($F59/12)*AU123 -> 14166.667 | AV59: =($F59/12)*AV123 -> 14166.667 | AW59: =($F59/12)*AW123 -> 14166.667 | AX59: =($F59/12)*AX123 -> 14166.667 | AY59: =($F59/12)*AY123 -> 14166.667 | ... BC59: =($F59/12)*BC123 -> 14166.667 | BD59: =($G59/12)*BD123 -> 14166.667 | BE59: =($G59/12)*BE123 -> 14166.667 | BF59: =($G59/12)*BF123 -> 14166.667 | BG59: =($G59/12)*BG123 -> 14166.667 | BH59: =($G59/12)*BH123 -> 14166.667 | BI59: =($G59/12)*BI123 -> 14166.667 | BJ59: =($G59/12)*BJ123 -> 14166.667 | BK59: =($G59/12)*BK123 -> 14166.667 | ... BO59: =($G59/12)*BO123 -> 14166.667
A60: Sr. Electrical Engineer - Carlos Mendoza | B60: 0.05 | C60: 150000 | D60: =+C60*(1+$B$26) -> 150000 | E60: =+D60*(1+$B$26) -> 150000 | F60: =+E60*(1+$B$26) -> 150000 | G60: =+F60*(1+$B$26) -> 150000 | H60: =($C60/12)*H124 -> 0 | I60: =($C60/12)*I124 -> 0 | J60: =($C60/12)*J124 -> 0 | K60: =($C60/12)*K124 -> 0 | L60: =($C60/12)*L124 -> 0 | M60: =($C60/12)*M124 -> 0 | N60: =($C60/12)*N124 -> 0 | O60: =($C60/12)*O124 -> 0 | ... S60: =($C60/12)*S124 -> 12500 | T60: =($D$60/12)*T124 -> 12500 | U60: =($D$60/12)*U124 -> 12500 | V60: =($D$60/12)*V124 -> 12500 | W60: =($D$60/12)*W124 -> 12500 | X60: =($D$60/12)*X124 -> 12500 | Y60: =($D$60/12)*Y124 -> 12500 | Z60: =($D$60/12)*Z124 -> 12500 | AA60: =($D$60/12)*AA124 -> 12500 | ... AE60: =($D$60/12)*AE124 -> 12500 | AF60: =($E60/12)*AF124 -> 12500 | AG60: =($E60/12)*AG124 -> 12500 | AH60: =($E60/12)*AH124 -> 12500 | AI60: =($E60/12)*AI124 -> 12500 | AJ60: =($E60/12)*AJ124 -> 12500 | AK60: =($E60/12)*AK124 -> 12500 | AL60: =($E60/12)*AL124 -> 12500 | AM60: =($E60/12)*AM124 -> 12500 | ... AQ60: =($E60/12)*AQ124 -> 12500 | AR60: =($F60/12)*AR124 -> 12500 | AS60: =($F60/12)*AS124 -> 12500 | AT60: =($F60/12)*AT124 -> 12500 | AU60: =($F60/12)*AU124 -> 12500 | AV60: =($F60/12)*AV124 -> 12500 | AW60: =($F60/12)*AW124 -> 12500 | AX60: =($F60/12)*AX124 -> 12500 | AY60: =($F60/12)*AY124 -> 12500 | ... BC60: =($F60/12)*BC124 -> 12500 | BD60: =($G60/12)*BD124 -> 12500 | BE60: =($G60/12)*BE124 -> 12500 | BF60: =($G60/12)*BF124 -> 12500 | BG60: =($G60/12)*BG124 -> 12500 | BH60: =($G60/12)*BH124 -> 12500 | BI60: =($G60/12)*BI124 -> 12500 | BJ60: =($G60/12)*BJ124 -> 12500 | BK60: =($G60/12)*BK124 -> 12500 | ... BO60: =($G60/12)*BO124 -> 12500
A61: AI/ML Specialist - Samantha Lee | B61: 0.05 | C61: 160000 | D61: =+C61*(1+$B$26) -> 160000 | E61: =+D61*(1+$B$26) -> 160000 | F61: =+E61*(1+$B$26) -> 160000 | G61: =+F61*(1+$B$26) -> 160000 | H61: =($C61/12)*H125 -> 0 | I61: =($C61/12)*I125 -> 0 | J61: =($C61/12)*J125 -> 0 | K61: =($C61/12)*K125 -> 0 | L61: =($C61/12)*L125 -> 0 | M61: =($C61/12)*M125 -> 0 | N61: =($C61/12)*N125 -> 0 | O61: =($C61/12)*O125 -> 0 | ... S61: =($C61/12)*S125 -> 13333.333 | T61: =($D$61/12)*T125 -> 13333.333 | U61: =($D$61/12)*U125 -> 13333.333 | V61: =($D$61/12)*V125 -> 13333.333 | W61: =($D$61/12)*W125 -> 13333.333 | X61: =($D$61/12)*X125 -> 13333.333 | Y61: =($D$61/12)*Y125 -> 13333.333 | Z61: =($D$61/12)*Z125 -> 13333.333 | AA61: =($D$61/12)*AA125 -> 13333.333 | ... AE61: =($D$61/12)*AE125 -> 13333.333 | AF61: =($E61/12)*AF125 -> 13333.333 | AG61: =($E61/12)*AG125 -> 13333.333 | AH61: =($E61/12)*AH125 -> 13333.333 | AI61: =($E61/12)*AI125 -> 13333.333 | AJ61: =($E61/12)*AJ125 -> 13333.333 | AK61: =($E61/12)*AK125 -> 13333.333 | AL61: =($E61/12)*AL125 -> 13333.333 | AM61: =($E61/12)*AM125 -> 13333.333 | ... AQ61: =($E61/12)*AQ125 -> 13333.333 | AR61: =($F61/12)*AR125 -> 13333.333 | AS61: =($F61/12)*AS125 -> 13333.333 | AT61: =($F61/12)*AT125 -> 13333.333 | AU61: =($F61/12)*AU125 -> 13333.333 | AV61: =($F61/12)*AV125 -> 13333.333 | AW61: =($F61/12)*AW125 -> 13333.333 | AX61: =($F61/12)*AX125 -> 13333.333 | AY61: =($F61/12)*AY125 -> 13333.333 | ... BC61: =($F61/12)*BC125 -> 13333.333 | BD61: =($G61/12)*BD125 -> 13333.333 | BE61: =($G61/12)*BE125 -> 13333.333 | BF61: =($G61/12)*BF125 -> 13333.333 | BG61: =($G61/12)*BG125 -> 13333.333 | BH61: =($G61/12)*BH125 -> 13333.333 | BI61: =($G61/12)*BI125 -> 13333.333 | BJ61: =($G61/12)*BJ125 -> 13333.333 | BK61: =($G61/12)*BK125 -> 13333.333 | ... BO61: =($G61/12)*BO125 -> 13333.333
A62: Software Engineer - David Kim | B62: 0.05 | C62: 140000 | D62: =+C62*(1+$B$26) -> 140000 | E62: =+D62*(1+$B$26) -> 140000 | F62: =+E62*(1+$B$26) -> 140000 | G62: =+F62*(1+$B$26) -> 140000 | H62: =($C62/12)*H126 -> 0 | I62: =($C62/12)*I126 -> 0 | J62: =($C62/12)*J126 -> 0 | K62: =($C62/12)*K126 -> 0 | L62: =($C62/12)*L126 -> 0 | M62: =($C62/12)*M126 -> 0 | N62: =($C62/12)*N126 -> 0 | O62: =($C62/12)*O126 -> 0 | ... S62: =($C62/12)*S126 -> 11666.667 | T62: =($D$62/12)*T126 -> 11666.667 | U62: =($D$62/12)*U126 -> 11666.667 | V62: =($D$62/12)*V126 -> 11666.667 | W62: =($D$62/12)*W126 -> 11666.667 | X62: =($D$62/12)*X126 -> 11666.667 | Y62: =($D$62/12)*Y126 -> 11666.667 | Z62: =($D$62/12)*Z126 -> 11666.667 | AA62: =($D$62/12)*AA126 -> 11666.667 | ... AE62: =($D$62/12)*AE126 -> 11666.667 | AF62: =($E62/12)*AF126 -> 11666.667 | AG62: =($E62/12)*AG126 -> 11666.667 | AH62: =($E62/12)*AH126 -> 11666.667 | AI62: =($E62/12)*AI126 -> 11666.667 | AJ62: =($E62/12)*AJ126 -> 11666.667 | AK62: =($E62/12)*AK126 -> 11666.667 | AL62: =($E62/12)*AL126 -> 11666.667 | AM62: =($E62/12)*AM126 -> 11666.667 | ... AQ62: =($E62/12)*AQ126 -> 11666.667 | AR62: =($F62/12)*AR126 -> 11666.667 | AS62: =($F62/12)*AS126 -> 11666.667 | AT62: =($F62/12)*AT126 -> 11666.667 | AU62: =($F62/12)*AU126 -> 11666.667 | AV62: =($F62/12)*AV126 -> 11666.667 | AW62: =($F62/12)*AW126 -> 11666.667 | AX62: =($F62/12)*AX126 -> 11666.667 | AY62: =($F62/12)*AY126 -> 11666.667 | ... BC62: =($F62/12)*BC126 -> 11666.667 | BD62: =($G62/12)*BD126 -> 11666.667 | BE62: =($G62/12)*BE126 -> 11666.667 | BF62: =($G62/12)*BF126 -> 11666.667 | BG62: =($G62/12)*BG126 -> 11666.667 | BH62: =($G62/12)*BH126 -> 11666.667 | BI62: =($G62/12)*BI126 -> 11666.667 | BJ62: =($G62/12)*BJ126 -> 11666.667 | BK62: =($G62/12)*BK126 -> 11666.667 | ... BO62: =($G62/12)*BO126 -> 11666.667
A63: Software Engineer - Emily Chen | B63: 0.05 | C63: 135000 | D63: =+C63*(1+$B$26) -> 135000 | E63: =+D63*(1+$B$26) -> 135000 | F63: =+E63*(1+$B$26) -> 135000 | G63: =+F63*(1+$B$26) -> 135000 | H63: =($C63/12)*H127 -> 0 | I63: =($C63/12)*I127 -> 0 | J63: =($C63/12)*J127 -> 0 | K63: =($C63/12)*K127 -> 0 | L63: =($C63/12)*L127 -> 0 | M63: =($C63/12)*M127 -> 0 | N63: =($C63/12)*N127 -> 0 | O63: =($C63/12)*O127 -> 0 | ... S63: =($C63/12)*S127 -> 11250 | T63: =($D$63/12)*T127 -> 11250 | U63: =($D$63/12)*U127 -> 11250 | V63: =($D$63/12)*V127 -> 11250 | W63: =($D$63/12)*W127 -> 11250 | X63: =($D$63/12)*X127 -> 11250 | Y63: =($D$63/12)*Y127 -> 11250 | Z63: =($D$63/12)*Z127 -> 11250 | AA63: =($D$63/12)*AA127 -> 11250 | ... AE63: =($D$63/12)*AE127 -> 11250 | AF63: =($E63/12)*AF127 -> 11250 | AG63: =($E63/12)*AG127 -> 11250 | AH63: =($E63/12)*AH127 -> 11250 | AI63: =($E63/12)*AI127 -> 11250 | AJ63: =($E63/12)*AJ127 -> 11250 | AK63: =($E63/12)*AK127 -> 11250 | AL63: =($E63/12)*AL127 -> 11250 | AM63: =($E63/12)*AM127 -> 11250 | ... AQ63: =($E63/12)*AQ127 -> 11250 | AR63: =($F63/12)*AR127 -> 11250 | AS63: =($F63/12)*AS127 -> 11250 | AT63: =($F63/12)*AT127 -> 11250 | AU63: =($F63/12)*AU127 -> 11250 | AV63: =($F63/12)*AV127 -> 11250 | AW63: =($F63/12)*AW127 -> 11250 | AX63: =($F63/12)*AX127 -> 11250 | AY63: =($F63/12)*AY127 -> 11250 | ... BC63: =($F63/12)*BC127 -> 11250 | BD63: =($G63/12)*BD127 -> 11250 | BE63: =($G63/12)*BE127 -> 11250 | BF63: =($G63/12)*BF127 -> 11250 | BG63: =($G63/12)*BG127 -> 11250 | BH63: =($G63/12)*BH127 -> 11250 | BI63: =($G63/12)*BI127 -> 11250 | BJ63: =($G63/12)*BJ127 -> 11250 | BK63: =($G63/12)*BK127 -> 11250 | ... BO63: =($G63/12)*BO127 -> 11250
A64: Mechanical Engineer - Ryan Patel | B64: 0.05 | C64: 130000 | D64: =+C64*(1+$B$26) -> 130000 | E64: =+D64*(1+$B$26) -> 130000 | F64: =+E64*(1+$B$26) -> 130000 | G64: =+F64*(1+$B$26) -> 130000 | H64: =($C64/12)*H128 -> 0 | I64: =($C64/12)*I128 -> 0 | J64: =($C64/12)*J128 -> 0 | K64: =($C64/12)*K128 -> 0 | L64: =($C64/12)*L128 -> 0 | M64: =($C64/12)*M128 -> 0 | N64: =($C64/12)*N128 -> 0 | O64: =($C64/12)*O128 -> 0 | ... S64: =($C64/12)*S128 -> 10833.333 | T64: =($D$64/12)*T128 -> 10833.333 | U64: =($D$64/12)*U128 -> 10833.333 | V64: =($D$64/12)*V128 -> 10833.333 | W64: =($D$64/12)*W128 -> 10833.333 | X64: =($D$64/12)*X128 -> 10833.333 | Y64: =($D$64/12)*Y128 -> 10833.333 | Z64: =($D$64/12)*Z128 -> 10833.333 | AA64: =($D$64/12)*AA128 -> 10833.333 | ... AE64: =($D$64/12)*AE128 -> 10833.333 | AF64: =($E64/12)*AF128 -> 10833.333 | AG64: =($E64/12)*AG128 -> 10833.333 | AH64: =($E64/12)*AH128 -> 10833.333 | AI64: =($E64/12)*AI128 -> 10833.333 | AJ64: =($E64/12)*AJ128 -> 10833.333 | AK64: =($E64/12)*AK128 -> 10833.333 | AL64: =($E64/12)*AL128 -> 10833.333 | AM64: =($E64/12)*AM128 -> 10833.333 | ... AQ64: =($E64/12)*AQ128 -> 10833.333 | AR64: =($F64/12)*AR128 -> 10833.333 | AS64: =($F64/12)*AS128 -> 10833.333 | AT64: =($F64/12)*AT128 -> 10833.333 | AU64: =($F64/12)*AU128 -> 10833.333 | AV64: =($F64/12)*AV128 -> 10833.333 | AW64: =($F64/12)*AW128 -> 10833.333 | AX64: =($F64/12)*AX128 -> 10833.333 | AY64: =($F64/12)*AY128 -> 10833.333 | ... BC64: =($F64/12)*BC128 -> 10833.333 | BD64: =($G64/12)*BD128 -> 10833.333 | BE64: =($G64/12)*BE128 -> 10833.333 | BF64: =($G64/12)*BF128 -> 10833.333 | BG64: =($G64/12)*BG128 -> 10833.333 | BH64: =($G64/12)*BH128 -> 10833.333 | BI64: =($G64/12)*BI128 -> 10833.333 | BJ64: =($G64/12)*BJ128 -> 10833.333 | BK64: =($G64/12)*BK128 -> 10833.333 | ... BO64: =($G64/12)*BO128 -> 10833.333
A65: Electrical Engineer - Jessica Huang | B65: 0.05 | C65: 130000 | D65: =+C65*(1+$B$26) -> 130000 | E65: =+D65*(1+$B$26) -> 130000 | F65: =+E65*(1+$B$26) -> 130000 | G65: =+F65*(1+$B$26) -> 130000 | H65: =($C65/12)*H129 -> 0 | I65: =($C65/12)*I129 -> 0 | J65: =($C65/12)*J129 -> 0 | K65: =($C65/12)*K129 -> 0 | L65: =($C65/12)*L129 -> 0 | M65: =($C65/12)*M129 -> 0 | N65: =($C65/12)*N129 -> 0 | O65: =($C65/12)*O129 -> 0 | ... S65: =($C65/12)*S129 -> 10833.333 | T65: =($D$65/12)*T129 -> 10833.333 | U65: =($D$65/12)*U129 -> 10833.333 | V65: =($D$65/12)*V129 -> 10833.333 | W65: =($D$65/12)*W129 -> 10833.333 | X65: =($D$65/12)*X129 -> 10833.333 | Y65: =($D$65/12)*Y129 -> 10833.333 | Z65: =($D$65/12)*Z129 -> 10833.333 | AA65: =($D$65/12)*AA129 -> 10833.333 | ... AE65: =($D$65/12)*AE129 -> 10833.333 | AF65: =($E65/12)*AF129 -> 10833.333 | AG65: =($E65/12)*AG129 -> 10833.333 | AH65: =($E65/12)*AH129 -> 10833.333 | AI65: =($E65/12)*AI129 -> 10833.333 | AJ65: =($E65/12)*AJ129 -> 10833.333 | AK65: =($E65/12)*AK129 -> 10833.333 | AL65: =($E65/12)*AL129 -> 10833.333 | AM65: =($E65/12)*AM129 -> 10833.333 | ... AQ65: =($E65/12)*AQ129 -> 10833.333 | AR65: =($F65/12)*AR129 -> 10833.333 | AS65: =($F65/12)*AS129 -> 10833.333 | AT65: =($F65/12)*AT129 -> 10833.333 | AU65: =($F65/12)*AU129 -> 10833.333 | AV65: =($F65/12)*AV129 -> 10833.333 | AW65: =($F65/12)*AW129 -> 10833.333 | AX65: =($F65/12)*AX129 -> 10833.333 | AY65: =($F65/12)*AY129 -> 10833.333 | ... BC65: =($F65/12)*BC129 -> 10833.333 | BD65: =($G65/12)*BD129 -> 10833.333 | BE65: =($G65/12)*BE129 -> 10833.333 | BF65: =($G65/12)*BF129 -> 10833.333 | BG65: =($G65/12)*BG129 -> 10833.333 | BH65: =($G65/12)*BH129 -> 10833.333 | BI65: =($G65/12)*BI129 -> 10833.333 | BJ65: =($G65/12)*BJ129 -> 10833.333 | BK65: =($G65/12)*BK129 -> 10833.333 | ... BO65: =($G65/12)*BO129 -> 10833.333
A66: Research Scientist - Alex Novak | B66: 0.05 | C66: 140000 | D66: =+C66*(1+$B$26) -> 140000 | E66: =+D66*(1+$B$26) -> 140000 | F66: =+E66*(1+$B$26) -> 140000 | G66: =+F66*(1+$B$26) -> 140000 | H66: =($C66/12)*H130 -> 0 | I66: =($C66/12)*I130 -> 0 | J66: =($C66/12)*J130 -> 0 | K66: =($C66/12)*K130 -> 0 | L66: =($C66/12)*L130 -> 0 | M66: =($C66/12)*M130 -> 0 | N66: =($C66/12)*N130 -> 0 | O66: =($C66/12)*O130 -> 0 | ... S66: =($C66/12)*S130 -> 11666.667 | T66: =($D$66/12)*T130 -> 11666.667 | U66: =($D$66/12)*U130 -> 11666.667 | V66: =($D$66/12)*V130 -> 11666.667 | W66: =($D$66/12)*W130 -> 11666.667 | X66: =($D$66/12)*X130 -> 11666.667 | Y66: =($D$66/12)*Y130 -> 11666.667 | Z66: =($D$66/12)*Z130 -> 11666.667 | AA66: =($D$66/12)*AA130 -> 11666.667 | ... AE66: =($D$66/12)*AE130 -> 11666.667 | AF66: =($E66/12)*AF130 -> 11666.667 | AG66: =($E66/12)*AG130 -> 11666.667 | AH66: =($E66/12)*AH130 -> 11666.667 | AI66: =($E66/12)*AI130 -> 11666.667 | AJ66: =($E66/12)*AJ130 -> 11666.667 | AK66: =($E66/12)*AK130 -> 11666.667 | AL66: =($E66/12)*AL130 -> 11666.667 | AM66: =($E66/12)*AM130 -> 11666.667 | ... AQ66: =($E66/12)*AQ130 -> 11666.667 | AR66: =($F66/12)*AR130 -> 11666.667 | AS66: =($F66/12)*AS130 -> 11666.667 | AT66: =($F66/12)*AT130 -> 11666.667 | AU66: =($F66/12)*AU130 -> 11666.667 | AV66: =($F66/12)*AV130 -> 11666.667 | AW66: =($F66/12)*AW130 -> 11666.667 | AX66: =($F66/12)*AX130 -> 11666.667 | AY66: =($F66/12)*AY130 -> 11666.667 | ... BC66: =($F66/12)*BC130 -> 11666.667 | BD66: =($G66/12)*BD130 -> 11666.667 | BE66: =($G66/12)*BE130 -> 11666.667 | BF66: =($G66/12)*BF130 -> 11666.667 | BG66: =($G66/12)*BG130 -> 11666.667 | BH66: =($G66/12)*BH130 -> 11666.667 | BI66: =($G66/12)*BI130 -> 11666.667 | BJ66: =($G66/12)*BJ130 -> 11666.667 | BK66: =($G66/12)*BK130 -> 11666.667 | ... BO66: =($G66/12)*BO130 -> 11666.667
A67: Sr. Mechanical Engineer - Lisa Wong | B67: 0.05 | C67: 130000 | D67: =+C67*(1+$B$26) -> 130000 | E67: =+D67*(1+$B$26) -> 130000 | F67: =+E67*(1+$B$26) -> 130000 | G67: =+F67*(1+$B$26) -> 130000 | H67: =($C67/12)*H131 -> 0 | I67: =($C67/12)*I131 -> 0 | J67: =($C67/12)*J131 -> 0 | K67: =($C67/12)*K131 -> 0 | L67: =($C67/12)*L131 -> 0 | M67: =($C67/12)*M131 -> 0 | N67: =($C67/12)*N131 -> 0 | O67: =($C67/12)*O131 -> 0 | ... S67: =($C67/12)*S131 -> 10833.333 | T67: =($D$67/12)*T131 -> 10833.333 | U67: =($D$67/12)*U131 -> 10833.333 | V67: =($D$67/12)*V131 -> 10833.333 | W67: =($D$67/12)*W131 -> 10833.333 | X67: =($D$67/12)*X131 -> 10833.333 | Y67: =($D$67/12)*Y131 -> 10833.333 | Z67: =($D$67/12)*Z131 -> 10833.333 | AA67: =($D$67/12)*AA131 -> 10833.333 | ... AE67: =($D$67/12)*AE131 -> 10833.333 | AF67: =($E67/12)*AF131 -> 10833.333 | AG67: =($E67/12)*AG131 -> 10833.333 | AH67: =($E67/12)*AH131 -> 10833.333 | AI67: =($E67/12)*AI131 -> 10833.333 | AJ67: =($E67/12)*AJ131 -> 10833.333 | AK67: =($E67/12)*AK131 -> 10833.333 | AL67: =($E67/12)*AL131 -> 10833.333 | AM67: =($E67/12)*AM131 -> 10833.333 | ... AQ67: =($E67/12)*AQ131 -> 10833.333 | AR67: =($F67/12)*AR131 -> 10833.333 | AS67: =($F67/12)*AS131 -> 10833.333 | AT67: =($F67/12)*AT131 -> 10833.333 | AU67: =($F67/12)*AU131 -> 10833.333 | AV67: =($F67/12)*AV131 -> 10833.333 | AW67: =($F67/12)*AW131 -> 10833.333 | AX67: =($F67/12)*AX131 -> 10833.333 | AY67: =($F67/12)*AY131 -> 10833.333 | ... BC67: =($F67/12)*BC131 -> 10833.333 | BD67: =($G67/12)*BD131 -> 10833.333 | BE67: =($G67/12)*BE131 -> 10833.333 | BF67: =($G67/12)*BF131 -> 10833.333 | BG67: =($G67/12)*BG131 -> 10833.333 | BH67: =($G67/12)*BH131 -> 10833.333 | BI67: =($G67/12)*BI131 -> 10833.333 | BJ67: =($G67/12)*BJ131 -> 10833.333 | BK67: =($G67/12)*BK131 -> 10833.333 | ... BO67: =($G67/12)*BO131 -> 10833.333
A68: Supply Chain Manager - David Chang | B68: 0.05 | C68: 140000 | D68: =+C68*(1+$B$26) -> 140000 | E68: =+D68*(1+$B$26) -> 140000 | F68: =+E68*(1+$B$26) -> 140000 | G68: =+F68*(1+$B$26) -> 140000 | H68: =($C68/12)*H132 -> 0 | I68: =($C68/12)*I132 -> 0 | J68: =($C68/12)*J132 -> 0 | K68: =($C68/12)*K132 -> 0 | L68: =($C68/12)*L132 -> 0 | M68: =($C68/12)*M132 -> 0 | N68: =($C68/12)*N132 -> 0 | O68: =($C68/12)*O132 -> 0 | ... S68: =($C68/12)*S132 -> 0 | T68: =($D$68/12)*T132 -> 0 | U68: =($D$68/12)*U132 -> 0 | V68: =($D$68/12)*V132 -> 0 | W68: =($D$68/12)*W132 -> 0 | X68: =($D$68/12)*X132 -> 0 | Y68: =($D$68/12)*Y132 -> 0 | Z68: =($D$68/12)*Z132 -> 0 | AA68: =($D$68/12)*AA132 -> 11666.667 | ... AE68: =($D$68/12)*AE132 -> 11666.667 | AF68: =($E68/12)*AF132 -> 11666.667 | AG68: =($E68/12)*AG132 -> 11666.667 | AH68: =($E68/12)*AH132 -> 11666.667 | AI68: =($E68/12)*AI132 -> 11666.667 | AJ68: =($E68/12)*AJ132 -> 11666.667 | AK68: =($E68/12)*AK132 -> 11666.667 | AL68: =($E68/12)*AL132 -> 11666.667 | AM68: =($E68/12)*AM132 -> 11666.667 | ... AQ68: =($E68/12)*AQ132 -> 11666.667 | AR68: =($F68/12)*AR132 -> 11666.667 | AS68: =($F68/12)*AS132 -> 11666.667 | AT68: =($F68/12)*AT132 -> 11666.667 | AU68: =($F68/12)*AU132 -> 11666.667 | AV68: =($F68/12)*AV132 -> 11666.667 | AW68: =($F68/12)*AW132 -> 11666.667 | AX68: =($F68/12)*AX132 -> 11666.667 | AY68: =($F68/12)*AY132 -> 11666.667 | ... BC68: =($F68/12)*BC132 -> 11666.667 | BD68: =($G68/12)*BD132 -> 11666.667 | BE68: =($G68/12)*BE132 -> 11666.667 | BF68: =($G68/12)*BF132 -> 11666.667 | BG68: =($G68/12)*BG132 -> 11666.667 | BH68: =($G68/12)*BH132 -> 11666.667 | BI68: =($G68/12)*BI132 -> 11666.667 | BJ68: =($G68/12)*BJ132 -> 11666.667 | BK68: =($G68/12)*BK132 -> 11666.667 | ... BO68: =($G68/12)*BO132 -> 11666.667
A69: Production Manager - Maria Garcia | B69: 0.05 | C69: 130000 | D69: =+C69*(1+$B$26) -> 130000 | E69: =+D69*(1+$B$26) -> 130000 | F69: =+E69*(1+$B$26) -> 130000 | G69: =+F69*(1+$B$26) -> 130000 | H69: =($C69/12)*H133 -> 0 | I69: =($C69/12)*I133 -> 0 | J69: =($C69/12)*J133 -> 0 | K69: =($C69/12)*K133 -> 0 | L69: =($C69/12)*L133 -> 0 | M69: =($C69/12)*M133 -> 0 | N69: =($C69/12)*N133 -> 0 | O69: =($C69/12)*O133 -> 0 | ... S69: =($C69/12)*S133 -> 0 | T69: =($D$69/12)*T133 -> 0 | U69: =($D$69/12)*U133 -> 0 | V69: =($D$69/12)*V133 -> 0 | W69: =($D$69/12)*W133 -> 0 | X69: =($D$69/12)*X133 -> 0 | Y69: =($D$69/12)*Y133 -> 0 | Z69: =($D$69/12)*Z133 -> 0 | AA69: =($D$69/12)*AA133 -> 10833.333 | ... AE69: =($D$69/12)*AE133 -> 10833.333 | AF69: =($E69/12)*AF133 -> 10833.333 | AG69: =($E69/12)*AG133 -> 10833.333 | AH69: =($E69/12)*AH133 -> 10833.333 | AI69: =($E69/12)*AI133 -> 10833.333 | AJ69: =($E69/12)*AJ133 -> 10833.333 | AK69: =($E69/12)*AK133 -> 10833.333 | AL69: =($E69/12)*AL133 -> 10833.333 | AM69: =($E69/12)*AM133 -> 10833.333 | ... AQ69: =($E69/12)*AQ133 -> 10833.333 | AR69: =($F69/12)*AR133 -> 10833.333 | AS69: =($F69/12)*AS133 -> 10833.333 | AT69: =($F69/12)*AT133 -> 10833.333 | AU69: =($F69/12)*AU133 -> 10833.333 | AV69: =($F69/12)*AV133 -> 10833.333 | AW69: =($F69/12)*AW133 -> 10833.333 | AX69: =($F69/12)*AX133 -> 10833.333 | AY69: =($F69/12)*AY133 -> 10833.333 | ... BC69: =($F69/12)*BC133 -> 10833.333 | BD69: =($G69/12)*BD133 -> 10833.333 | BE69: =($G69/12)*BE133 -> 10833.333 | BF69: =($G69/12)*BF133 -> 10833.333 | BG69: =($G69/12)*BG133 -> 10833.333 | BH69: =($G69/12)*BH133 -> 10833.333 | BI69: =($G69/12)*BI133 -> 10833.333 | BJ69: =($G69/12)*BJ133 -> 10833.333 | BK69: =($G69/12)*BK133 -> 10833.333 | ... BO69: =($G69/12)*BO133 -> 10833.333
A70: Quality Control Specialist - John Smith | B70: 0.05 | C70: 110000 | D70: =+C70*(1+$B$26) -> 110000 | E70: =+D70*(1+$B$26) -> 110000 | F70: =+E70*(1+$B$26) -> 110000 | G70: =+F70*(1+$B$26) -> 110000 | H70: =($C70/12)*H134 -> 0 | I70: =($C70/12)*I134 -> 0 | J70: =($C70/12)*J134 -> 0 | K70: =($C70/12)*K134 -> 0 | L70: =($C70/12)*L134 -> 0 | M70: =($C70/12)*M134 -> 0 | N70: =($C70/12)*N134 -> 0 | O70: =($C70/12)*O134 -> 0 | ... S70: =($C70/12)*S134 -> 0 | T70: =($D$70/12)*T134 -> 0 | U70: =($D$70/12)*U134 -> 0 | V70: =($D$70/12)*V134 -> 0 | W70: =($D$70/12)*W134 -> 0 | X70: =($D$70/12)*X134 -> 0 | Y70: =($D$70/12)*Y134 -> 0 | Z70: =($D$70/12)*Z134 -> 0 | AA70: =($D$70/12)*AA134 -> 9166.6667 | ... AE70: =($D$70/12)*AE134 -> 9166.6667 | AF70: =($E70/12)*AF134 -> 9166.6667 | AG70: =($E70/12)*AG134 -> 9166.6667 | AH70: =($E70/12)*AH134 -> 9166.6667 | AI70: =($E70/12)*AI134 -> 9166.6667 | AJ70: =($E70/12)*AJ134 -> 9166.6667 | AK70: =($E70/12)*AK134 -> 9166.6667 | AL70: =($E70/12)*AL134 -> 9166.6667 | AM70: =($E70/12)*AM134 -> 9166.6667 | ... AQ70: =($E70/12)*AQ134 -> 9166.6667 | AR70: =($F70/12)*AR134 -> 9166.6667 | AS70: =($F70/12)*AS134 -> 9166.6667 | AT70: =($F70/12)*AT134 -> 9166.6667 | AU70: =($F70/12)*AU134 -> 9166.6667 | AV70: =($F70/12)*AV134 -> 9166.6667 | AW70: =($F70/12)*AW134 -> 9166.6667 | AX70: =($F70/12)*AX134 -> 9166.6667 | AY70: =($F70/12)*AY134 -> 9166.6667 | ... BC70: =($F70/12)*BC134 -> 9166.6667 | BD70: =($G70/12)*BD134 -> 9166.6667 | BE70: =($G70/12)*BE134 -> 9166.6667 | BF70: =($G70/12)*BF134 -> 9166.6667 | BG70: =($G70/12)*BG134 -> 9166.6667 | BH70: =($G70/12)*BH134 -> 9166.6667 | BI70: =($G70/12)*BI134 -> 9166.6667 | BJ70: =($G70/12)*BJ134 -> 9166.6667 | BK70: =($G70/12)*BK134 -> 9166.6667 | ... BO70: =($G70/12)*BO134 -> 9166.6667
A71: Logistic Coordinator - Sarah Johnson | B71: 0.05 | C71: 100000 | D71: =+C71*(1+$B$26) -> 100000 | E71: =+D71*(1+$B$26) -> 100000 | F71: =+E71*(1+$B$26) -> 100000 | G71: =+F71*(1+$B$26) -> 100000 | H71: =($C71/12)*H135 -> 0 | I71: =($C71/12)*I135 -> 0 | J71: =($C71/12)*J135 -> 0 | K71: =($C71/12)*K135 -> 0 | L71: =($C71/12)*L135 -> 0 | M71: =($C71/12)*M135 -> 0 | N71: =($C71/12)*N135 -> 0 | O71: =($C71/12)*O135 -> 0 | ... S71: =($C71/12)*S135 -> 0 | T71: =($D$71/12)*T135 -> 0 | U71: =($D$71/12)*U135 -> 0 | V71: =($D$71/12)*V135 -> 0 | W71: =($D$71/12)*W135 -> 0 | X71: =($D$71/12)*X135 -> 0 | Y71: =($D$71/12)*Y135 -> 0 | Z71: =($D$71/12)*Z135 -> 0 | AA71: =($D$71/12)*AA135 -> 8333.3333 | ... AE71: =($D$71/12)*AE135 -> 8333.3333 | AF71: =($E71/12)*AF135 -> 8333.3333 | AG71: =($E71/12)*AG135 -> 8333.3333 | AH71: =($E71/12)*AH135 -> 8333.3333 | AI71: =($E71/12)*AI135 -> 8333.3333 | AJ71: =($E71/12)*AJ135 -> 8333.3333 | AK71: =($E71/12)*AK135 -> 8333.3333 | AL71: =($E71/12)*AL135 -> 8333.3333 | AM71: =($E71/12)*AM135 -> 8333.3333 | ... AQ71: =($E71/12)*AQ135 -> 8333.3333 | AR71: =($F71/12)*AR135 -> 8333.3333 | AS71: =($F71/12)*AS135 -> 8333.3333 | AT71: =($F71/12)*AT135 -> 8333.3333 | AU71: =($F71/12)*AU135 -> 8333.3333 | AV71: =($F71/12)*AV135 -> 8333.3333 | AW71: =($F71/12)*AW135 -> 8333.3333 | AX71: =($F71/12)*AX135 -> 8333.3333 | AY71: =($F71/12)*AY135 -> 8333.3333 | ... BC71: =($F71/12)*BC135 -> 8333.3333 | BD71: =($G71/12)*BD135 -> 8333.3333 | BE71: =($G71/12)*BE135 -> 8333.3333 | BF71: =($G71/12)*BF135 -> 8333.3333 | BG71: =($G71/12)*BG135 -> 8333.3333 | BH71: =($G71/12)*BH135 -> 8333.3333 | BI71: =($G71/12)*BI135 -> 8333.3333 | BJ71: =($G71/12)*BJ135 -> 8333.3333 | BK71: =($G71/12)*BK135 -> 8333.3333 | ... BO71: =($G71/12)*BO135 -> 8333.3333
A72: Product Line Supervisor - Robert Chen | B72: 0.05 | C72: 90000 | D72: =+C72*(1+$B$26) -> 90000 | E72: =+D72*(1+$B$26) -> 90000 | F72: =+E72*(1+$B$26) -> 90000 | G72: =+F72*(1+$B$26) -> 90000 | H72: =($C72/12)*H136 -> 0 | I72: =($C72/12)*I136 -> 0 | J72: =($C72/12)*J136 -> 0 | K72: =($C72/12)*K136 -> 0 | L72: =($C72/12)*L136 -> 0 | M72: =($C72/12)*M136 -> 0 | N72: =($C72/12)*N136 -> 0 | O72: =($C72/12)*O136 -> 0 | ... S72: =($C72/12)*S136 -> 0 | T72: =($D$72/12)*T136 -> 0 | U72: =($D$72/12)*U136 -> 0 | V72: =($D$72/12)*V136 -> 0 | W72: =($D$72/12)*W136 -> 0 | X72: =($D$72/12)*X136 -> 0 | Y72: =($D$72/12)*Y136 -> 0 | Z72: =($D$72/12)*Z136 -> 0 | AA72: =($D$72/12)*AA136 -> 7500 | ... AE72: =($D$72/12)*AE136 -> 7500 | AF72: =($E72/12)*AF136 -> 7500 | AG72: =($E72/12)*AG136 -> 7500 | AH72: =($E72/12)*AH136 -> 7500 | AI72: =($E72/12)*AI136 -> 7500 | AJ72: =($E72/12)*AJ136 -> 7500 | AK72: =($E72/12)*AK136 -> 7500 | AL72: =($E72/12)*AL136 -> 7500 | AM72: =($E72/12)*AM136 -> 7500 | ... AQ72: =($E72/12)*AQ136 -> 7500 | AR72: =($F72/12)*AR136 -> 7500 | AS72: =($F72/12)*AS136 -> 7500 | AT72: =($F72/12)*AT136 -> 7500 | AU72: =($F72/12)*AU136 -> 7500 | AV72: =($F72/12)*AV136 -> 7500 | AW72: =($F72/12)*AW136 -> 7500 | AX72: =($F72/12)*AX136 -> 7500 | AY72: =($F72/12)*AY136 -> 7500 | ... BC72: =($F72/12)*BC136 -> 7500 | BD72: =($G72/12)*BD136 -> 7500 | BE72: =($G72/12)*BE136 -> 7500 | BF72: =($G72/12)*BF136 -> 7500 | BG72: =($G72/12)*BG136 -> 7500 | BH72: =($G72/12)*BH136 -> 7500 | BI72: =($G72/12)*BI136 -> 7500 | BJ72: =($G72/12)*BJ136 -> 7500 | BK72: =($G72/12)*BK136 -> 7500 | ... BO72: =($G72/12)*BO136 -> 7500
A73: Production Line Worker | B73: 0.05 | C73: 60000 | D73: =+C73*(1+$B$26) -> 60000 | E73: =+D73*(1+$B$26) -> 60000 | F73: =+E73*(1+$B$26) -> 60000 | G73: =+F73*(1+$B$26) -> 60000 | H73: =($C73/12)*H137 -> 0 | I73: =($C73/12)*I137 -> 0 | J73: =($C73/12)*J137 -> 0 | K73: =($C73/12)*K137 -> 0 | L73: =($C73/12)*L137 -> 0 | M73: =($C73/12)*M137 -> 0 | N73: =($C73/12)*N137 -> 0 | O73: =($C73/12)*O137 -> 0 | ... S73: =($C73/12)*S137 -> 0 | T73: =($D$73/12)*T137 -> 0 | U73: =($D$73/12)*U137 -> 0 | V73: =($D$73/12)*V137 -> 0 | W73: =($D$73/12)*W137 -> 0 | X73: =($D$73/12)*X137 -> 0 | Y73: =($D$73/12)*Y137 -> 0 | Z73: =($D$73/12)*Z137 -> 0 | AA73: =($D$73/12)*AA137 -> 0 | ... AE73: =($D$73/12)*AE137 -> 50000 | AF73: =($E73/12)*AF137 -> 50000 | AG73: =($E73/12)*AG137 -> 50000 | AH73: =($E73/12)*AH137 -> 50000 | AI73: =($E73/12)*AI137 -> 50000 | AJ73: =($E73/12)*AJ137 -> 50000 | AK73: =($E73/12)*AK137 -> 50000 | AL73: =($E73/12)*AL137 -> 50000 | AM73: =($E73/12)*AM137 -> 50000 | ... AQ73: =($E73/12)*AQ137 -> 50000 | AR73: =($F73/12)*AR137 -> 50000 | AS73: =($F73/12)*AS137 -> 50000 | AT73: =($F73/12)*AT137 -> 50000 | AU73: =($F73/12)*AU137 -> 50000 | AV73: =($F73/12)*AV137 -> 50000 | AW73: =($F73/12)*AW137 -> 50000 | AX73: =($F73/12)*AX137 -> 50000 | AY73: =($F73/12)*AY137 -> 50000 | ... BC73: =($F73/12)*BC137 -> 50000 | BD73: =($G73/12)*BD137 -> 50000 | BE73: =($G73/12)*BE137 -> 50000 | BF73: =($G73/12)*BF137 -> 50000 | BG73: =($G73/12)*BG137 -> 50000 | BH73: =($G73/12)*BH137 -> 50000 | BI73: =($G73/12)*BI137 -> 50000 | BJ73: =($G73/12)*BJ137 -> 50000 | BK73: =($G73/12)*BK137 -> 50000 | ... BO73: =($G73/12)*BO137 -> 50000
A74: Frank Rodriguez, Head of Installation | B74: 0.05 | C74: 130000 | D74: =+C74*(1+$B$26) -> 130000 | E74: =+D74*(1+$B$26) -> 130000 | F74: =+E74*(1+$B$26) -> 130000 | G74: =+F74*(1+$B$26) -> 130000 | H74: =($C74/12)*H138 -> 0 | I74: =($C74/12)*I138 -> 0 | J74: =($C74/12)*J138 -> 0 | K74: =($C74/12)*K138 -> 0 | L74: =($C74/12)*L138 -> 0 | M74: =($C74/12)*M138 -> 0 | N74: =($C74/12)*N138 -> 0 | O74: =($C74/12)*O138 -> 0 | ... S74: =($C74/12)*S138 -> 0 | T74: =($D$74/12)*T138 -> 0 | U74: =($D$74/12)*U138 -> 0 | V74: =($D$74/12)*V138 -> 0 | W74: =($D$74/12)*W138 -> 0 | X74: =($D$74/12)*X138 -> 0 | Y74: =($D$74/12)*Y138 -> 0 | Z74: =($D$74/12)*Z138 -> 0 | AA74: =($D$74/12)*AA138 -> 10833.333 | ... AE74: =($D$74/12)*AE138 -> 10833.333 | AF74: =($E74/12)*AF138 -> 10833.333 | AG74: =($E74/12)*AG138 -> 10833.333 | AH74: =($E74/12)*AH138 -> 10833.333 | AI74: =($E74/12)*AI138 -> 10833.333 | AJ74: =($E74/12)*AJ138 -> 10833.333 | AK74: =($E74/12)*AK138 -> 10833.333 | AL74: =($E74/12)*AL138 -> 10833.333 | AM74: =($E74/12)*AM138 -> 10833.333 | ... AQ74: =($E74/12)*AQ138 -> 10833.333 | AR74: =($F74/12)*AR138 -> 10833.333 | AS74: =($F74/12)*AS138 -> 10833.333 | AT74: =($F74/12)*AT138 -> 10833.333 | AU74: =($F74/12)*AU138 -> 10833.333 | AV74: =($F74/12)*AV138 -> 10833.333 | AW74: =($F74/12)*AW138 -> 10833.333 | AX74: =($F74/12)*AX138 -> 10833.333 | AY74: =($F74/12)*AY138 -> 10833.333 | ... BC74: =($F74/12)*BC138 -> 10833.333 | BD74: =($G74/12)*BD138 -> 10833.333 | BE74: =($G74/12)*BE138 -> 10833.333 | BF74: =($G74/12)*BF138 -> 10833.333 | BG74: =($G74/12)*BG138 -> 10833.333 | BH74: =($G74/12)*BH138 -> 10833.333 | BI74: =($G74/12)*BI138 -> 10833.333 | BJ74: =($G74/12)*BJ138 -> 10833.333 | BK74: =($G74/12)*BK138 -> 10833.333 | ... BO74: =($G74/12)*BO138 -> 10833.333
A75: Alice Kim, Service Manager | B75: 0.05 | C75: 120000 | D75: =+C75*(1+$B$26) -> 120000 | E75: =+D75*(1+$B$26) -> 120000 | F75: =+E75*(1+$B$26) -> 120000 | G75: =+F75*(1+$B$26) -> 120000 | H75: =($C75/12)*H139 -> 0 | I75: =($C75/12)*I139 -> 0 | J75: =($C75/12)*J139 -> 0 | K75: =($C75/12)*K139 -> 0 | L75: =($C75/12)*L139 -> 0 | M75: =($C75/12)*M139 -> 0 | N75: =($C75/12)*N139 -> 0 | O75: =($C75/12)*O139 -> 0 | ... S75: =($C75/12)*S139 -> 0 | T75: =($D$75/12)*T139 -> 0 | U75: =($D$75/12)*U139 -> 0 | V75: =($D$75/12)*V139 -> 0 | W75: =($D$75/12)*W139 -> 0 | X75: =($D$75/12)*X139 -> 0 | Y75: =($D$75/12)*Y139 -> 0 | Z75: =($D$75/12)*Z139 -> 0 | AA75: =($D$75/12)*AA139 -> 10000 | ... AE75: =($D$75/12)*AE139 -> 10000 | AF75: =($E75/12)*AF139 -> 10000 | AG75: =($E75/12)*AG139 -> 10000 | AH75: =($E75/12)*AH139 -> 10000 | AI75: =($E75/12)*AI139 -> 10000 | AJ75: =($E75/12)*AJ139 -> 10000 | AK75: =($E75/12)*AK139 -> 10000 | AL75: =($E75/12)*AL139 -> 10000 | AM75: =($E75/12)*AM139 -> 10000 | ... AQ75: =($E75/12)*AQ139 -> 10000 | AR75: =($F75/12)*AR139 -> 10000 | AS75: =($F75/12)*AS139 -> 10000 | AT75: =($F75/12)*AT139 -> 10000 | AU75: =($F75/12)*AU139 -> 10000 | AV75: =($F75/12)*AV139 -> 10000 | AW75: =($F75/12)*AW139 -> 10000 | AX75: =($F75/12)*AX139 -> 10000 | AY75: =($F75/12)*AY139 -> 10000 | ... BC75: =($F75/12)*BC139 -> 10000 | BD75: =($G75/12)*BD139 -> 10000 | BE75: =($G75/12)*BE139 -> 10000 | BF75: =($G75/12)*BF139 -> 10000 | BG75: =($G75/12)*BG139 -> 10000 | BH75: =($G75/12)*BH139 -> 10000 | BI75: =($G75/12)*BI139 -> 10000 | BJ75: =($G75/12)*BJ139 -> 10000 | BK75: =($G75/12)*BK139 -> 10000 | ... BO75: =($G75/12)*BO139 -> 10000
A76: Tom Nelson, Senior Installation Technician | B76: 0.05 | C76: 90000 | D76: =+C76*(1+$B$26) -> 90000 | E76: =+D76*(1+$B$26) -> 90000 | F76: =+E76*(1+$B$26) -> 90000 | G76: =+F76*(1+$B$26) -> 90000 | H76: =($C76/12)*H140 -> 0 | I76: =($C76/12)*I140 -> 0 | J76: =($C76/12)*J140 -> 0 | K76: =($C76/12)*K140 -> 0 | L76: =($C76/12)*L140 -> 0 | M76: =($C76/12)*M140 -> 0 | N76: =($C76/12)*N140 -> 0 | O76: =($C76/12)*O140 -> 0 | ... S76: =($C76/12)*S140 -> 0 | T76: =($D$76/12)*T140 -> 0 | U76: =($D$76/12)*U140 -> 0 | V76: =($D$76/12)*V140 -> 0 | W76: =($D$76/12)*W140 -> 0 | X76: =($D$76/12)*X140 -> 0 | Y76: =($D$76/12)*Y140 -> 0 | Z76: =($D$76/12)*Z140 -> 0 | AA76: =($D$76/12)*AA140 -> 0 | ... AE76: =($D$76/12)*AE140 -> 7500 | AF76: =($E76/12)*AF140 -> 7500 | AG76: =($E76/12)*AG140 -> 7500 | AH76: =($E76/12)*AH140 -> 7500 | AI76: =($E76/12)*AI140 -> 7500 | AJ76: =($E76/12)*AJ140 -> 7500 | AK76: =($E76/12)*AK140 -> 7500 | AL76: =($E76/12)*AL140 -> 7500 | AM76: =($E76/12)*AM140 -> 7500 | ... AQ76: =($E76/12)*AQ140 -> 7500 | AR76: =($F76/12)*AR140 -> 7500 | AS76: =($F76/12)*AS140 -> 7500 | AT76: =($F76/12)*AT140 -> 7500 | AU76: =($F76/12)*AU140 -> 7500 | AV76: =($F76/12)*AV140 -> 7500 | AW76: =($F76/12)*AW140 -> 7500 | AX76: =($F76/12)*AX140 -> 7500 | AY76: =($F76/12)*AY140 -> 7500 | ... BC76: =($F76/12)*BC140 -> 7500 | BD76: =($G76/12)*BD140 -> 7500 | BE76: =($G76/12)*BE140 -> 7500 | BF76: =($G76/12)*BF140 -> 7500 | BG76: =($G76/12)*BG140 -> 7500 | BH76: =($G76/12)*BH140 -> 7500 | BI76: =($G76/12)*BI140 -> 7500 | BJ76: =($G76/12)*BJ140 -> 7500 | BK76: =($G76/12)*BK140 -> 7500 | ... BO76: =($G76/12)*BO140 -> 7500
A77: Juan Hernandez, Installation Technician | B77: 0.05 | C77: 80000 | D77: =+C77*(1+$B$26) -> 80000 | E77: =+D77*(1+$B$26) -> 80000 | F77: =+E77*(1+$B$26) -> 80000 | G77: =+F77*(1+$B$26) -> 80000 | H77: =($C77/12)*H141 -> 0 | I77: =($C77/12)*I141 -> 0 | J77: =($C77/12)*J141 -> 0 | K77: =($C77/12)*K141 -> 0 | L77: =($C77/12)*L141 -> 0 | M77: =($C77/12)*M141 -> 0 | N77: =($C77/12)*N141 -> 0 | O77: =($C77/12)*O141 -> 0 | ... S77: =($C77/12)*S141 -> 0 | T77: =($D$77/12)*T141 -> 0 | U77: =($D$77/12)*U141 -> 0 | V77: =($D$77/12)*V141 -> 0 | W77: =($D$77/12)*W141 -> 0 | X77: =($D$77/12)*X141 -> 0 | Y77: =($D$77/12)*Y141 -> 0 | Z77: =($D$77/12)*Z141 -> 0 | AA77: =($D$77/12)*AA141 -> 0 | ... AE77: =($D$77/12)*AE141 -> 6666.6667 | AF77: =($E77/12)*AF141 -> 0 | AG77: =($E77/12)*AG141 -> 0 | AH77: =($E77/12)*AH141 -> 0 | AI77: =($E77/12)*AI141 -> 0 | AJ77: =($E77/12)*AJ141 -> 0 | AK77: =($E77/12)*AK141 -> 0 | AL77: =($E77/12)*AL141 -> 0 | AM77: =($E77/12)*AM141 -> 0 | ... AQ77: =($E77/12)*AQ141 -> 0 | AR77: =($F77/12)*AR141 -> 0 | AS77: =($F77/12)*AS141 -> 0 | AT77: =($F77/12)*AT141 -> 0 | AU77: =($F77/12)*AU141 -> 0 | AV77: =($F77/12)*AV141 -> 0 | AW77: =($F77/12)*AW141 -> 0 | AX77: =($F77/12)*AX141 -> 0 | AY77: =($F77/12)*AY141 -> 0 | ... BC77: =($F77/12)*BC141 -> 0 | BD77: =($G77/12)*BD141 -> 0 | BE77: =($G77/12)*BE141 -> 0 | BF77: =($G77/12)*BF141 -> 0 | BG77: =($G77/12)*BG141 -> 0 | BH77: =($G77/12)*BH141 -> 0 | BI77: =($G77/12)*BI141 -> 0 | BJ77: =($G77/12)*BJ141 -> 0 | BK77: =($G77/12)*BK141 -> 0 | ... BO77: =($G77/12)*BO141 -> 0
A78: Lisa Chen, Installation Technician | B78: 0.05 | C78: 80000 | D78: =+C78*(1+$B$26) -> 80000 | E78: =+D78*(1+$B$26) -> 80000 | F78: =+E78*(1+$B$26) -> 80000 | G78: =+F78*(1+$B$26) -> 80000 | H78: =($C78/12)*H142 -> 0 | I78: =($C78/12)*I142 -> 0 | J78: =($C78/12)*J142 -> 0 | K78: =($C78/12)*K142 -> 0 | L78: =($C78/12)*L142 -> 0 | M78: =($C78/12)*M142 -> 0 | N78: =($C78/12)*N142 -> 0 | O78: =($C78/12)*O142 -> 0 | ... S78: =($C78/12)*S142 -> 0 | T78: =($D$78/12)*T142 -> 0 | U78: =($D$78/12)*U142 -> 0 | V78: =($D$78/12)*V142 -> 0 | W78: =($D$78/12)*W142 -> 0 | X78: =($D$78/12)*X142 -> 0 | Y78: =($D$78/12)*Y142 -> 0 | Z78: =($D$78/12)*Z142 -> 0 | AA78: =($D$78/12)*AA142 -> 0 | ... AE78: =($D$78/12)*AE142 -> 6666.6667 | AF78: =($E78/12)*AF142 -> 0 | AG78: =($E78/12)*AG142 -> 0 | AH78: =($E78/12)*AH142 -> 0 | AI78: =($E78/12)*AI142 -> 0 | AJ78: =($E78/12)*AJ142 -> 0 | AK78: =($E78/12)*AK142 -> 0 | AL78: =($E78/12)*AL142 -> 0 | AM78: =($E78/12)*AM142 -> 0 | ... AQ78: =($E78/12)*AQ142 -> 0 | AR78: =($F78/12)*AR142 -> 0 | AS78: =($F78/12)*AS142 -> 0 | AT78: =($F78/12)*AT142 -> 0 | AU78: =($F78/12)*AU142 -> 0 | AV78: =($F78/12)*AV142 -> 0 | AW78: =($F78/12)*AW142 -> 0 | AX78: =($F78/12)*AX142 -> 0 | AY78: =($F78/12)*AY142 -> 0 | ... BC78: =($F78/12)*BC142 -> 0 | BD78: =($G78/12)*BD142 -> 0 | BE78: =($G78/12)*BE142 -> 0 | BF78: =($G78/12)*BF142 -> 0 | BG78: =($G78/12)*BG142 -> 0 | BH78: =($G78/12)*BH142 -> 0 | BI78: =($G78/12)*BI142 -> 0 | BJ78: =($G78/12)*BJ142 -> 0 | BK78: =($G78/12)*BK142 -> 0 | ... BO78: =($G78/12)*BO142 -> 0
A79: Mike Johnson, Service Engineer | B79: 0.05 | C79: 95000 | D79: =+C79*(1+$B$26) -> 95000 | E79: =+D79*(1+$B$26) -> 95000 | F79: =+E79*(1+$B$26) -> 95000 | G79: =+F79*(1+$B$26) -> 95000 | H79: =($C79/12)*H143 -> 0 | I79: =($C79/12)*I143 -> 0 | J79: =($C79/12)*J143 -> 0 | K79: =($C79/12)*K143 -> 0 | L79: =($C79/12)*L143 -> 0 | M79: =($C79/12)*M143 -> 0 | N79: =($C79/12)*N143 -> 0 | O79: =($C79/12)*O143 -> 0 | ... S79: =($C79/12)*S143 -> 0 | T79: =($D$79/12)*T143 -> 0 | U79: =($D$79/12)*U143 -> 0 | V79: =($D$79/12)*V143 -> 0 | W79: =($D$79/12)*W143 -> 0 | X79: =($D$79/12)*X143 -> 0 | Y79: =($D$79/12)*Y143 -> 0 | Z79: =($D$79/12)*Z143 -> 0 | AA79: =($D$79/12)*AA143 -> 0 | ... AE79: =($D$79/12)*AE143 -> 0 | AF79: =($E79/12)*AF143 -> 7916.6667 | AG79: =($E79/12)*AG143 -> 0 | AH79: =($E79/12)*AH143 -> 0 | AI79: =($E79/12)*AI143 -> 0 | AJ79: =($E79/12)*AJ143 -> 0 | AK79: =($E79/12)*AK143 -> 0 | AL79: =($E79/12)*AL143 -> 0 | AM79: =($E79/12)*AM143 -> 0 | ... AQ79: =($E79/12)*AQ143 -> 0 | AR79: =($F79/12)*AR143 -> 0 | AS79: =($F79/12)*AS143 -> 0 | AT79: =($F79/12)*AT143 -> 0 | AU79: =($F79/12)*AU143 -> 0 | AV79: =($F79/12)*AV143 -> 0 | AW79: =($F79/12)*AW143 -> 0 | AX79: =($F79/12)*AX143 -> 0 | AY79: =($F79/12)*AY143 -> 0 | ... BC79: =($F79/12)*BC143 -> 0 | BD79: =($G79/12)*BD143 -> 0 | BE79: =($G79/12)*BE143 -> 0 | BF79: =($G79/12)*BF143 -> 0 | BG79: =($G79/12)*BG143 -> 0 | BH79: =($G79/12)*BH143 -> 0 | BI79: =($G79/12)*BI143 -> 0 | BJ79: =($G79/12)*BJ143 -> 0 | BK79: =($G79/12)*BK143 -> 0 | ... BO79: =($G79/12)*BO143 -> 0
A80: Sarah Lee, Service Engineer | B80: 0.05 | C80: 95000 | D80: =+C80*(1+$B$26) -> 95000 | E80: =+D80*(1+$B$26) -> 95000 | F80: =+E80*(1+$B$26) -> 95000 | G80: =+F80*(1+$B$26) -> 95000 | H80: =($C80/12)*H144 -> 0 | I80: =($C80/12)*I144 -> 0 | J80: =($C80/12)*J144 -> 0 | K80: =($C80/12)*K144 -> 0 | L80: =($C80/12)*L144 -> 0 | M80: =($C80/12)*M144 -> 0 | N80: =($C80/12)*N144 -> 0 | O80: =($C80/12)*O144 -> 0 | ... S80: =($C80/12)*S144 -> 0 | T80: =($D$80/12)*T144 -> 0 | U80: =($D$80/12)*U144 -> 0 | V80: =($D$80/12)*V144 -> 0 | W80: =($D$80/12)*W144 -> 0 | X80: =($D$80/12)*X144 -> 0 | Y80: =($D$80/12)*Y144 -> 0 | Z80: =($D$80/12)*Z144 -> 0 | AA80: =($D$80/12)*AA144 -> 0 | ... AE80: =($D$80/12)*AE144 -> 0 | AF80: =($E80/12)*AF144 -> 7916.6667 | AG80: =($E80/12)*AG144 -> 0 | AH80: =($E80/12)*AH144 -> 0 | AI80: =($E80/12)*AI144 -> 0 | AJ80: =($E80/12)*AJ144 -> 0 | AK80: =($E80/12)*AK144 -> 0 | AL80: =($E80/12)*AL144 -> 0 | AM80: =($E80/12)*AM144 -> 0 | ... AQ80: =($E80/12)*AQ144 -> 0 | AR80: =($F80/12)*AR144 -> 0 | AS80: =($F80/12)*AS144 -> 0 | AT80: =($F80/12)*AT144 -> 0 | AU80: =($F80/12)*AU144 -> 0 | AV80: =($F80/12)*AV144 -> 0 | AW80: =($F80/12)*AW144 -> 0 | AX80: =($F80/12)*AX144 -> 0 | AY80: =($F80/12)*AY144 -> 0 | ... BC80: =($F80/12)*BC144 -> 0 | BD80: =($G80/12)*BD144 -> 0 | BE80: =($G80/12)*BE144 -> 0 | BF80: =($G80/12)*BF144 -> 0 | BG80: =($G80/12)*BG144 -> 0 | BH80: =($G80/12)*BH144 -> 0 | BI80: =($G80/12)*BI144 -> 0 | BJ80: =($G80/12)*BJ144 -> 0 | BK80: =($G80/12)*BK144 -> 0 | ... BO80: =($G80/12)*BO144 -> 0
H81: =(C81/12)*H152 -> 0 | I81: =(D81/12)*I152 -> 0 | J81: =(E81/12)*J152 -> 0 | K81: =(F81/12)*K152 -> 0 | L81: =(G81/12)*L152 -> 0 | M81: =(H81/12)*M152 -> 0 | N81: =(I81/12)*N152 -> 0 | O81: =(J81/12)*O152 -> 0 | ... S81: =(N81/12)*S152 -> 0 | T81: =($D$81/12)*T145 -> 0 | U81: =($D$81/12)*U145 -> 0 | V81: =($D$81/12)*V145 -> 0 | W81: =($D$81/12)*W145 -> 0 | X81: =($D$81/12)*X145 -> 0 | Y81: =($D$81/12)*Y145 -> 0 | Z81: =($D$81/12)*Z145 -> 0 | AA81: =($D$81/12)*AA145 -> 0 | ... AE81: =($D$81/12)*AE145 -> 0 | AF81: =($E81/12)*AF145 -> 0 | AG81: =($E81/12)*AG145 -> 0 | AH81: =($E81/12)*AH145 -> 0 | AI81: =($E81/12)*AI145 -> 0 | AJ81: =($E81/12)*AJ145 -> 0 | AK81: =($E81/12)*AK145 -> 0 | AL81: =($E81/12)*AL145 -> 0 | AM81: =($E81/12)*AM145 -> 0 | ... AQ81: =($E81/12)*AQ145 -> 0 | AR81: =($F81/12)*AR145 -> 0 | AS81: =($F81/12)*AS145 -> 0 | AT81: =($F81/12)*AT145 -> 0 | AU81: =($F81/12)*AU145 -> 0 | AV81: =($F81/12)*AV145 -> 0 | AW81: =($F81/12)*AW145 -> 0 | AX81: =($F81/12)*AX145 -> 0 | AY81: =($F81/12)*AY145 -> 0 | ... BC81: =($F81/12)*BC145 -> 0 | BD81: =($G81/12)*BD145 -> 0 | BE81: =($G81/12)*BE145 -> 0 | BF81: =($G81/12)*BF145 -> 0 | BG81: =($G81/12)*BG145 -> 0 | BH81: =($G81/12)*BH145 -> 0 | BI81: =($G81/12)*BI145 -> 0 | BJ81: =($G81/12)*BJ145 -> 0 | BK81: =($G81/12)*BK145 -> 0 | ... BO81: =($G81/12)*BO145 -> 0
A82: Total Salaries - PD | H82: =SUM(H57:H72) -> 0 | I82: =SUM(I57:I72) -> 0 | J82: =SUM(J57:J72) -> 0 | K82: =SUM(K57:K72) -> 15000 | L82: =SUM(L57:L72) -> 15000 | M82: =SUM(M57:M72) -> 15000 | N82: =SUM(N57:N72) -> 15000 | O82: =SUM(O57:O72) -> 29583.333 | ... BO82: =SUM(BO57:BO72) -> 184166.67
A85: HEADCOUNT
A86: General and Administration
A87: New Specific FTEs - G&A | H87: =+H102 -> 3 | I87: =+I102-H102 -> 0 | J87: =+J102-I102 -> 0 | K87: =+K102-J102 -> 0 | L87: =+L102-K102 -> 0 | M87: =+M102-L102 -> 0 | N87: =+N102-M102 -> 0 | O87: =+O102-N102 -> 0 | P87: =+P102-O102 -> 0 | ... BO87: =+BO102-BN102 -> 0
A88: New Generic FTEs - G&A | H88: 0 | I88: 0 | J88: 0 | K88: 0 | L88: 0 | M88: 0 | N88: 0 | O88: 0 | P88: 0 | Q88: 0 | R88: 0 | S88: 0 | T88: 0 | U88: 0 | V88: 0 | W88: 0 | X88: 0 | Y88: 0 | Z88: 0 | AA88: 0 | AB88: 0 | AC88: 0 | AD88: 0 | AE88: 0 | AF88: 0 | AG88: 0 | AH88: 0 | AI88: 0 | AJ88: 0 | AK88: 0 | AL88: 0 | AM88: 0 | AN88: 0 | AO88: 0 | AP88: 0 | AQ88: 0 | AR88: 0 | AS88: 0 | AT88: 0 | AU88: 0 | AV88: 0 | AW88: 0 | AX88: 0 | AY88: 0 | AZ88: 0 | BA88: 0 | BB88: 0 | BC88: 0 | BD88: 0 | BE88: 0 | BF88: 0 | BG88: 0 | BH88: 0 | BI88: 0 | BJ88: 0 | BK88: 0 | BL88: 0 | BM88: 0 | BN88: 0 | BO88: 0
A89: Total FTEs, Contract - G&A | B89: inflation | H89: =SUM(H87:H88) -> 3 | I89: =SUM(I87:I88)+H89 -> 3 | J89: =SUM(J87:J88)+I89 -> 3 | K89: =SUM(K87:K88)+J89 -> 3 | L89: =SUM(L87:L88)+K89 -> 3 | M89: =SUM(M87:M88)+L89 -> 3 | N89: =SUM(N87:N88)+M89 -> 3 | O89: =SUM(O87:O88)+N89 -> 3 | P89: =SUM(P87:P88)+O89 -> 3 | ... BO89: =SUM(BO87:BO88)+BN89 -> 12
A90: =+A26 -> Elena Rodriguez, CEO | C90: =S90 -> 1 | D90: =AE90 -> 1 | E90: =+AQ90 -> 1 | F90: =BC90 -> 1 | G90: =+BO90 -> 1 | H90: 1 | I90: =+H90 -> 1 | J90: =+I90 -> 1 | K90: =+J90 -> 1 | L90: =+K90 -> 1 | M90: =+L90 -> 1 | N90: =+M90 -> 1 | O90: =+N90 -> 1 | P90: =+O90 -> 1 | ... BO90: =+BN90 -> 1
A91: =+A27 -> Dr. Rachel Chen, CTO | C91: =S91 -> 1 | D91: =AE91 -> 1 | E91: =+AQ91 -> 1 | F91: =BC91 -> 1 | G91: =+BO91 -> 1 | H91: 1 | I91: =+H91 -> 1 | J91: =+I91 -> 1 | K91: =+J91 -> 1 | L91: =+K91 -> 1 | M91: =+L91 -> 1 | N91: =+M91 -> 1 | O91: =+N91 -> 1 | P91: =+O91 -> 1 | ... BO91: =+BN91 -> 1
A92: =+A28 -> Marcus Blackwood, CFO | C92: =S92 -> 1 | D92: =AE92 -> 1 | E92: =+AQ92 -> 1 | F92: =BC92 -> 1 | G92: =+BO92 -> 1 | H92: 1 | I92: =+H92 -> 1 | J92: =+I92 -> 1 | K92: =+J92 -> 1 | L92: =+K92 -> 1 | M92: =+L92 -> 1 | N92: =+M92 -> 1 | O92: =+N92 -> 1 | P92: =+O92 -> 1 | ... BO92: =+BN92 -> 1
A93: =+A29 -> Thomas Lee, COO | C93: =S93 -> 0 | D93: =AE93 -> 1 | E93: =+AQ93 -> 1 | F93: =BC93 -> 1 | G93: =+BO93 -> 1 | H93: 0 | I93: 0 | J93: =+I93 -> 0 | K93: =+J93 -> 0 | L93: =+K93 -> 0 | M93: =+L93 -> 0 | N93: =+M93 -> 0 | O93: =+N93 -> 0 | P93: =+O93 -> 0 | Q93: =+P93 -> 0 | ... Z93: =+Y93 -> 0 | AA93: 1 | AB93: =+AA93 -> 1 | AC93: =+AB93 -> 1 | AD93: =+AC93 -> 1 | AE93: =+AD93 -> 1 | AF93: =+AE93 -> 1 | AG93: =+AF93 -> 1 | AH93: =+AG93 -> 1 | AI93: =+AH93 -> 1 | ... BO93: =+BN93 -> 1
A94: =+A30 -> Olivia Martinez, HR Manager | C94: =S94 -> 0 | D94: =AE94 -> 1 | E94: =+AQ94 -> 1 | F94: =BC94 -> 1 | G94: =+BO94 -> 1 | H94: 0 | I94: 0 | J94: =+I94 -> 0 | K94: =+J94 -> 0 | L94: =+K94 -> 0 | M94: =+L94 -> 0 | N94: =+M94 -> 0 | O94: =+N94 -> 0 | P94: =+O94 -> 0 | Q94: =+P94 -> 0 | ... Z94: =+Y94 -> 0 | AA94: 1 | AB94: =+AA94 -> 1 | AC94: =+AB94 -> 1 | AD94: =+AC94 -> 1 | AE94: =+AD94 -> 1 | AF94: =+AE94 -> 1 | AG94: =+AF94 -> 1 | AH94: =+AG94 -> 1 | AI94: =+AH94 -> 1 | ... BO94: =+BN94 -> 1
A95: =+A31 -> Jason Wu, IT Manager | C95: =S95 -> 0 | D95: =AE95 -> 1 | E95: =+AQ95 -> 1 | F95: =BC95 -> 1 | G95: =+BO95 -> 1 | H95: 0 | I95: 0 | J95: =+I95 -> 0 | K95: =+J95 -> 0 | L95: =+K95 -> 0 | M95: =+L95 -> 0 | N95: =+M95 -> 0 | O95: =+N95 -> 0 | P95: =+O95 -> 0 | Q95: =+P95 -> 0 | ... Z95: =+Y95 -> 0 | AA95: 1 | AB95: =+AA95 -> 1 | AC95: =+AB95 -> 1 | AD95: =+AC95 -> 1 | AE95: =+AD95 -> 1 | AF95: =+AE95 -> 1 | AG95: =+AF95 -> 1 | AH95: =+AG95 -> 1 | AI95: =+AH95 -> 1 | ... BO95: =+BN95 -> 1
A96: =+A32 -> Patricia Alvarez, Office Manager | C96: =S96 -> 0 | D96: =AE96 -> 0 | E96: =+AQ96 -> 1 | F96: =BC96 -> 1 | G96: =+BO96 -> 1 | H96: 0 | I96: 0 | J96: =+I96 -> 0 | K96: =+J96 -> 0 | L96: =+K96 -> 0 | M96: =+L96 -> 0 | N96: =+M96 -> 0 | O96: =+N96 -> 0 | P96: =+O96 -> 0 | Q96: =+P96 -> 0 | ... AE96: =+AD96 -> 0 | AF96: 1 | AG96: =+AF96 -> 1 | AH96: =+AG96 -> 1 | AI96: =+AH96 -> 1 | AJ96: =+AI96 -> 1 | AK96: =+AJ96 -> 1 | AL96: =+AK96 -> 1 | AM96: =+AL96 -> 1 | AN96: =+AM96 -> 1 | ... BO96: =+BN96 -> 1
A97: =+A33 -> Chris Taylor, IT Support | C97: =S97 -> 0 | D97: =AE97 -> 0 | E97: =+AQ97 -> 1 | F97: =BC97 -> 1 | G97: =+BO97 -> 1 | H97: 0 | I97: 0 | J97: =+I97 -> 0 | K97: =+J97 -> 0 | L97: =+K97 -> 0 | M97: =+L97 -> 0 | N97: =+M97 -> 0 | O97: =+N97 -> 0 | P97: =+O97 -> 0 | Q97: =+P97 -> 0 | ... AG97: =+AF97 -> 0 | AH97: 1 | AI97: =+AH97 -> 1 | AJ97: =+AI97 -> 1 | AK97: =+AJ97 -> 1 | AL97: =+AK97 -> 1 | AM97: =+AL97 -> 1 | AN97: =+AM97 -> 1 | AO97: =+AN97 -> 1 | AP97: =+AO97 -> 1 | ... BO97: =+BN97 -> 1
A98: =+A34 -> Kevin Park, Accounting Specialist | C98: =S98 -> 0 | D98: =AE98 -> 0 | E98: =+AQ98 -> 1 | F98: =BC98 -> 1 | G98: =+BO98 -> 1 | H98: 0 | I98: 0 | J98: 0 | K98: 0 | L98: 0 | M98: 0 | N98: 0 | O98: 0 | P98: 0 | Q98: 0 | R98: 0 | S98: 0 | T98: =+S98 -> 0 | U98: =+T98 -> 0 | V98: =+U98 -> 0 | W98: =+V98 -> 0 | X98: =+W98 -> 0 | Y98: =+X98 -> 0 | Z98: =+Y98 -> 0 | AA98: =+Z98 -> 0 | ... AH98: =+AG98 -> 0 | AI98: 1 | AJ98: =+AI98 -> 1 | AK98: =+AJ98 -> 1 | AL98: =+AK98 -> 1 | AM98: =+AL98 -> 1 | AN98: =+AM98 -> 1 | AO98: =+AN98 -> 1 | AP98: =+AO98 -> 1 | AQ98: =+AP98 -> 1 | ... BO98: =+BN98 -> 1
A99: =+A35 -> Karen Lee, Finance Manager | C99: =S99 -> 0 | D99: =AE99 -> 1 | E99: =+AQ99 -> 1 | F99: =BC99 -> 1 | G99: =+BO99 -> 1 | H99: 0 | I99: 0 | J99: 0 | K99: 0 | L99: 0 | M99: 0 | N99: 0 | O99: 0 | P99: 0 | Q99: 0 | R99: 0 | S99: 0 | T99: 0 | U99: =+T99 -> 0 | V99: =+U99 -> 0 | W99: =+V99 -> 0 | X99: =+W99 -> 0 | Y99: =+X99 -> 0 | Z99: =+Y99 -> 0 | AA99: 1 | AB99: =+AA99 -> 1 | AC99: =+AB99 -> 1 | AD99: =+AC99 -> 1 | AE99: =+AD99 -> 1 | AF99: =+AE99 -> 1 | AG99: =+AF99 -> 1 | AH99: =+AG99 -> 1 | AI99: =+AH99 -> 1 | ... BO99: =+BN99 -> 1
A100: =+A36 -> Laura Sanchez, Executive Assistant | C100: =S100 -> 0 | D100: =AE100 -> 0 | E100: =+AQ100 -> 1 | F100: =BC100 -> 1 | G100: =+BO100 -> 1 | H100: 0 | I100: 0 | J100: =+I100 -> 0 | K100: =+J100 -> 0 | L100: =+K100 -> 0 | M100: =+L100 -> 0 | N100: =+M100 -> 0 | O100: =+N100 -> 0 | P100: =+O100 -> 0 | Q100: =+P100 -> 0 | ... Z100: =+Y100 -> 0 | AA100: 0 | AB100: =+AA100 -> 0 | AC100: =+AB100 -> 0 | AD100: =+AC100 -> 0 | AE100: =+AD100 -> 0 | AF100: =+AE100 -> 0 | AG100: =+AF100 -> 0 | AH100: =+AG100 -> 0 | AI100: =+AH100 -> 0 | AJ100: 1 | AK100: =+AJ100 -> 1 | AL100: =+AK100 -> 1 | AM100: =+AL100 -> 1 | AN100: =+AM100 -> 1 | AO100: =+AN100 -> 1 | AP100: =+AO100 -> 1 | AQ100: =+AP100 -> 1 | AR100: =+AQ100 -> 1 | ... BO100: =+BN100 -> 1
A101: =+A37 -> Michelle Wong, HR Specialist | D101: =AE101 -> 0 | E101: =+AQ101 -> 1 | F101: =BC101 -> 1 | G101: =+BO101 -> 1 | H101: 0 | I101: 0 | J101: 0 | K101: 0 | L101: 0 | M101: 0 | N101: 0 | O101: 0 | P101: 0 | Q101: 0 | R101: 0 | S101: 0 | T101: 0 | U101: 0 | V101: 0 | W101: 0 | X101: 0 | Y101: 0 | Z101: 0 | AA101: 0 | AB101: 0 | AC101: 0 | AD101: 0 | AE101: 0 | AF101: 0 | AG101: 0 | AH101: 1 | AI101: =AH101 -> 1 | AJ101: =AI101 -> 1 | AK101: =AJ101 -> 1 | AL101: =AK101 -> 1 | AM101: =AL101 -> 1 | AN101: =AM101 -> 1 | AO101: =AN101 -> 1 | AP101: =AO101 -> 1 | ... BO101: =BN101 -> 1
A102: Headcount Totals | H102: =SUM(H90:H101) -> 3 | I102: =SUM(I90:I101) -> 3 | J102: =SUM(J90:J101) -> 3 | K102: =SUM(K90:K101) -> 3 | L102: =SUM(L90:L101) -> 3 | M102: =SUM(M90:M101) -> 3 | N102: =SUM(N90:N101) -> 3 | O102: =SUM(O90:O101) -> 3 | ... BO102: =SUM(BO90:BO101) -> 12
A103: Sales and Marketing
A104: HEADCOUNT
...

Sheet People Summary
A1: UrbanWind
A2: People Cost Summary
A3: Assumption Inputs
A4: Exeptions
A5: Note: If waterfall specific employees must manually input # of "New Specific FTEs" for month [Line 23] and put $0 in months b4 start month for employee
C7: Plan Years | H7: 44551
C8: 1 | D8: 2 | E8: 3 | F8: 4 | G8: 5 | H8: Month 1 | I8: Month 2 | J8: Month 3 | K8: Month 4 | L8: Month 5 | M8: Month 6 | N8: Month 7 | O8: Month 8 | P8: Month 9 | Q8: Month 10 | R8: Month 11 | S8: Month 12 | T8: Month 13 | U8: Month 14 | V8: Month 15 | W8: Month 16 | X8: Month 17 | Y8: Month 18 | Z8: Month 19 | AA8: Month 20 | AB8: Month 21 | AC8: Month 22 | AD8: Month 23 | AE8: Month 24 | AF8: Month 25 | AG8: Month 26 | AH8: Month 27 | AI8: Month 28 | AJ8: Month 29 | AK8: Month 30 | AL8: Month 31 | AM8: Month 32 | AN8: Month 33 | AO8: Month 34 | AP8: Month 35 | AQ8: Month 36 | AR8: Month 37 | AS8: Month 38 | AT8: Month 39 | AU8: Month 40 | AV8: Month 41 | AW8: Month 42 | AX8: Month 43 | AY8: Month 44 | AZ8: Month 45 | BA8: Month 46 | BB8: Month 47 | BC8: Month 48 | BD8: Month 49 | BE8: Month 50 | BF8: Month 51 | BG8: Month 52 | BH8: Month 53 | BI8: Month 54 | BJ8: Month 55 | BK8: Month 56 | BL8: Month 57 | BM8: Month 58 | BN8: Month 59 | BO8: Month 60
A9: Total Salaries ($)
A10: General and Administration | C10: =SUM(H10:S10) -> 700000 | D10: =SUM(T10:AE10) -> 949375 | E10: =SUM(AF10:AQ10) -> 1559578.1 | F10: =SUM(AR10:BC10) -> 1678556.2 | G10: =SUM(BD10:BO10) -> 2734889.1 | H10: =H36 -> 58333.333 | I10: =I36 -> 58333.333 | J10: =J36 -> 58333.333 | K10: =K36 -> 58333.333 | L10: =L36 -> 58333.333 | M10: =M36 -> 58333.333 | N10: =N36 -> 58333.333 | O10: =O36 -> 58333.333 | ... BO10: =BO36 -> 227907.42
A11: Sales and Marketing | C11: =SUM(H11:S11) -> 0 | D11: =SUM(T11:AE11) -> 511000 | E11: =SUM(AF11:AQ11) -> 1411200 | F11: =SUM(AR11:BC11) -> 1481760 | G11: =SUM(BD11:BO11) -> 1555848 | H11: =H50 -> 0 | I11: =I50 -> 0 | J11: =J50 -> 0 | K11: =K50 -> 0 | L11: =L50 -> 0 | M11: =M50 -> 0 | N11: =N50 -> 0 | O11: =O50 -> 0 | ... BO11: =BO50 -> 129654
A12: Product Engineering | C12: =SUM(H12:S12) -> 625416.67 | D12: =SUM(T12:AE12) -> 2431000 | E12: =SUM(AF12:AQ12) -> 3101250 | F12: =SUM(AR12:BC12) -> 3239062.5 | G12: =SUM(BD12:BO12) -> 3383765.6 | H12: =H73 -> 0 | I12: =I73 -> 0 | J12: =J73 -> 0 | K12: =K73 -> 15000 | L12: =L73 -> 15000 | M12: =M73 -> 15000 | N12: =N73 -> 15000 | O12: =O73 -> 29583.333 | ... BO12: =BO73 -> 281980.47
A13: Total Salaries | C13: =SUM(H13:S13) -> 1325416.7 | D13: =SUM(T13:AE13) -> 3891375 | E13: =SUM(AF13:AQ13) -> 6072028.1 | F13: =SUM(AR13:BC13) -> 6399378.8 | G13: =SUM(BD13:BO13) -> 7674502.7 | H13: =SUM(H10:H12) -> 58333.333 | I13: =SUM(I10:I12) -> 58333.333 | J13: =SUM(J10:J12) -> 58333.333 | K13: =SUM(K10:K12) -> 73333.333 | L13: =SUM(L10:L12) -> 73333.333 | M13: =SUM(M10:M12) -> 73333.333 | N13: =SUM(N10:N12) -> 73333.333 | O13: =SUM(O10:O12) -> 87916.667 | ... BO13: =SUM(BO10:BO12) -> 639541.89
A14: Employee Related Costs ($)
A15: Payroll Taxes (see rate proof below) | C15: =C138 -> 0.1415 | D15: =D138 -> 0.1415 | E15: =E138 -> 0.1415 | F15: =F138 -> 0.1415 | G15: =G138 -> 0.1415 | H15: =H13*$C$15 -> 8254.1667 | I15: =I13*$C$15 -> 8254.1667 | J15: =J13*$C$15 -> 8254.1667 | K15: =K13*$C$15 -> 10376.667 | L15: =L13*$C$15 -> 10376.667 | M15: =M13*$C$15 -> 10376.667 | N15: =N13*$C$15 -> 10376.667 | O15: =O13*$C$15 -> 12440.208 | ... S15: =S13*$C$15 -> 31424.792 | T15: =T13*$D$15 -> 33783.125 | U15: =U13*$D$15 -> 34773.625 | V15: =V13*$D$15 -> 34773.625 | W15: =W13*$D$15 -> 34773.625 | X15: =X13*$D$15 -> 34773.625 | Y15: =Y13*$D$15 -> 34773.625 | Z15: =Z13*$D$15 -> 34773.625 | AA15: =AA13*$D$15 -> 57678.938 | ... AE15: =AE13*$D$15 -> 65602.938 | AF15: =AF13*$E$15 -> 69849.706 | AG15: =AG13*$E$15 -> 69849.706 | AH15: =AH13*$E$15 -> 70954.733 | AI15: =AI13*$E$15 -> 72059.759 | AJ15: =AJ13*$E$15 -> 72059.759 | AK15: =AK13*$E$15 -> 72059.759 | AL15: =AL13*$E$15 -> 72059.759 | AM15: =AM13*$E$15 -> 72059.759 | ... AQ15: =AQ13*$E$15 -> 72059.759 | AR15: =AR13*$F$15 -> 75459.341 | AS15: =AS13*$F$15 -> 75459.341 | AT15: =AT13*$F$15 -> 75459.341 | AU15: =AU13*$F$15 -> 75459.341 | AV15: =AV13*$F$15 -> 75459.341 | AW15: =AW13*$F$15 -> 75459.341 | AX15: =AX13*$F$15 -> 75459.341 | AY15: =AY13*$F$15 -> 75459.341 | ... BC15: =BC13*$F$15 -> 75459.341 | BD15: =BD13*$G$15 -> 90495.178 | BE15: =BE13*$G$15 -> 90495.178 | BF15: =BF13*$G$15 -> 90495.178 | BG15: =BG13*$G$15 -> 90495.178 | BH15: =BH13*$G$15 -> 90495.178 | BI15: =BI13*$G$15 -> 90495.178 | BJ15: =BJ13*$G$15 -> 90495.178 | BK15: =BK13*$G$15 -> 90495.178 | ... BO15: =BO13*$G$15 -> 90495.178
